Workbook

Sheet P&L
A1: M J P T & Co LLP
A2: Pristine Worldwide Private Limited
A4: P&L Analysis
A5: For the month of Mar 2026 | L5: Mar'26 | N5: (April to Mar) | X5: YTD'26
A6: Particulars | B6: Bluestreak | C6: Clarus | D6: IT | E6: Factory | F6: Office | G6: Common | H6: Spices - A to Z | I6: Spices - Vashi | J6: Total (without share trading) | K6: Share Trading | L6: Total (including share trading) | N6: Bluestreak | O6: Clarus | P6: IT | Q6: Factory | R6: Office | S6: Common | T6: Spices - A to Z | U6: Spices - Vashi | V6: Total (without share trading) | W6: Share Trading | X6: Total (including share trading)
A7: Sales | B7: =-SUMIFS('List of Ledgers '!$L:$L,'List of Ledgers '!$F:$F,'P&L'!$A$7,'List of Ledgers '!$G:$G,'P&L'!B6) -> 0 | C7: =-SUMIFS('List of Ledgers '!$L:$L,'List of Ledgers '!$F:$F,'P&L'!$A$7,'List of Ledgers '!$G:$G,'P&L'!C6) -> 28434.72 | D7: =-SUMIFS('List of Ledgers '!$L:$L,'List of Ledgers '!$F:$F,'P&L'!$A$7,'List of Ledgers '!$G:$G,'P&L'!D6) -> 0 | E7: =-SUMIFS('List of Ledgers '!$L:$L,'List of Ledgers '!$F:$F,'P&L'!$A$7,'List of Ledgers '!$G:$G,'P&L'!E6) -> 0 | F7: =-SUMIFS('List of Ledgers '!$L:$L,'List of Ledgers '!$F:$F,'P&L'!$A$7,'List of Ledgers '!$G:$G,'P&L'!F6) -> 0 | G7: =-SUMIFS('List of Ledgers '!$L:$L,'List of Ledgers '!$F:$F,'P&L'!$A$7,'List of Ledgers '!$G:$G,'P&L'!G6) -> 0 | H7: =-SUMIFS('List of Ledgers '!$L:$L,'List of Ledgers '!$F:$F,'P&L'!$A$7,'List of Ledgers '!$G:$G,'P&L'!H6) -> 0 | I7: =-SUMIFS('List of Ledgers '!$L:$L,'List of Ledgers '!$F:$F,'P&L'!$A$7,'List of Ledgers '!$G:$G,'P&L'!I6) -> 75012625 | J7: =SUM(B7:I7) -> 75041060 | K7: ='Shares(FIFO) '!J5 -> 0 | L7: =J7+K7 -> 75041060 | N7: =-SUMIFS('List of Ledgers '!$Q:$Q,'List of Ledgers '!$F:$F,'P&L'!$A$7,'List of Ledgers '!$G:$G,'P&L'!N6) -> 1770750.3 | O7: =-SUMIFS('List of Ledgers '!$Q:$Q,'List of Ledgers '!$F:$F,'P&L'!$A$7,'List of Ledgers '!$G:$G,'P&L'!O6) -> 837740.01 | P7: =-SUMIFS('List of Ledgers '!$Q:$Q,'List of Ledgers '!$F:$F,'P&L'!$A$7,'List of Ledgers '!$G:$G,'P&L'!P6) -> 1.0581533e+08 | Q7: =-SUMIFS('List of Ledgers '!$Q:$Q,'List of Ledgers '!$F:$F,'P&L'!$A$7,'List of Ledgers '!$G:$G,'P&L'!Q6) -> 0 | R7: =-SUMIFS('List of Ledgers '!$Q:$Q,'List of Ledgers '!$F:$F,'P&L'!$A$7,'List of Ledgers '!$G:$G,'P&L'!R6) -> 0 | S7: =-SUMIFS('List of Ledgers '!$Q:$Q,'List of Ledgers '!$F:$F,'P&L'!$A$7,'List of Ledgers '!$G:$G,'P&L'!S6) -> 0 | T7: =-SUMIFS('List of Ledgers '!$Q:$Q,'List of Ledgers '!$F:$F,'P&L'!$A$7,'List of Ledgers '!$G:$G,'P&L'!T6) -> 0 | U7: =-SUMIFS('List of Ledgers '!$Q:$Q,'List of Ledgers '!$F:$F,'P&L'!$A$7,'List of Ledgers '!$G:$G,'P&L'!U6)-1124270 -> 1.1989178e+08 | V7: =SUM(N7:U7) -> 2.283156e+08 | W7: ='Shares FIFO YTD'!J5 -> 0 | X7: =V7+W7 -> 2.283156e+08 | Y7: =V7-X7 -> 0
A8: Less: COGS | B8: =COGS!B11 -> 0 | C8: =COGS!C11 -> 28434.72 | D8: =COGS!D11 -> 16865.55 | E8: =COGS!E11 -> 0 | F8: =COGS!F11 -> 0 | G8: =COGS!G11 -> 16540 | I8: =COGS!H11 -> 69588312 | J8: =SUM(B8:I8) -> 69650152 | K8: =COGS!J11 -> 0 | L8: =J8+K8 -> 69650152 | N8: =COGS!B18 -> 1831803.4 | O8: =COGS!C18 -> 509355.46 | P8: =COGS!D18 -> 1.0231259e+08 | Q8: =COGS!E18 -> 0 | R8: =COGS!F18 -> 0 | S8: =COGS!G18 -> 17570 | U8: =COGS!H18 -> 1.1065439e+08 | V8: =SUM(N8:U8) -> 2.1532572e+08 | W8: =COGS!J18 -> 0 | X8: =V8+W8 -> 2.1532572e+08 | Y8: =V8-X8 -> 0
A9: 3. Direct Expense | B9: =SUM(B10:B14) -> 0 | C9: =SUM(C10:C14) -> 0 | D9: =SUM(D10:D14) -> 79554.92 | E9: =SUM(E10:E14) -> 0 | F9: =SUM(F10:F14) -> 0 | G9: =SUM(G10:G14) -> 18510 | H9: =SUM(H10:H14) -> 0 | I9: =SUM(I10:I14) -> 2088133.3 | J9: =SUM(B9:I9) -> 2186198.2 | K9: =SUM(K10:K14) -> 0 | L9: =J9+K9 -> 2186198.2 | N9: =SUM(N10:N14) -> 0 | O9: =SUM(O10:O14) -> 0 | P9: =SUM(P10:P14) -> 621733.82 | Q9: =SUM(Q10:Q14) -> 0 | R9: =SUM(R10:R14) -> 0 | S9: =SUM(S10:S14) -> 60190 | T9: =SUM(T10:T14) -> 0 | U9: =SUM(U10:U14) -> 3597029.3 | V9: =SUM(N9:U9) -> 4278953.1 | X9: =V9+W9 -> 4278953.1 | Y9: =V9-X9 -> 0
A10: Port Expenses | B10: =SUMIFS('List of Ledgers '!$L:$L,'List of Ledgers '!$F:$F,'P&L'!$A10,'List of Ledgers '!$G:$G,'P&L'!B$6) -> 0 | C10: =SUMIFS('List of Ledgers '!$L:$L,'List of Ledgers '!$F:$F,'P&L'!$A10,'List of Ledgers '!$G:$G,'P&L'!C$6) -> 0 | D10: =SUMIFS('List of Ledgers '!$L:$L,'List of Ledgers '!$F:$F,'P&L'!$A10,'List of Ledgers '!$G:$G,'P&L'!D$6) -> 0 | E10: =SUMIFS('List of Ledgers '!$L:$L,'List of Ledgers '!$F:$F,'P&L'!$A10,'List of Ledgers '!$G:$G,'P&L'!E$6) -> 0 | F10: =SUMIFS('List of Ledgers '!$L:$L,'List of Ledgers '!$F:$F,'P&L'!$A10,'List of Ledgers '!$G:$G,'P&L'!F$6) -> 0 | G10: =SUMIFS('List of Ledgers '!$L:$L,'List of Ledgers '!$F:$F,'P&L'!$A10,'List of Ledgers '!$G:$G,'P&L'!G$6) -> 0 | H10: =SUMIFS('List of Ledgers '!$L:$L,'List of Ledgers '!$F:$F,'P&L'!$A10,'List of Ledgers '!$G:$G,'P&L'!H$6) -> 0 | I10: =SUMIFS('List of Ledgers '!$L:$L,'List of Ledgers '!$F:$F,'P&L'!$A10,'List of Ledgers '!$G:$G,'P&L'!I$6) -> 1836553.2 | J10: =SUM(B10:I10) -> 1836553.2 | K10: =SUMIFS('List of Ledgers '!$L:$L,'List of Ledgers '!$F:$F,'P&L'!$A10,'List of Ledgers '!$G:$G,'P&L'!K$6) -> 0 | L10: =J10+K10 -> 1836553.2 | N10: =SUMIFS('List of Ledgers '!$Q:$Q,'List of Ledgers '!$F:$F,'P&L'!$A$10,'List of Ledgers '!$G:$G,'P&L'!N6) -> 0 | O10: =SUMIFS('List of Ledgers '!$Q:$Q,'List of Ledgers '!$F:$F,'P&L'!$A$10,'List of Ledgers '!$G:$G,'P&L'!O6) -> 0 | P10: =SUMIFS('List of Ledgers '!$Q:$Q,'List of Ledgers '!$F:$F,'P&L'!$A$10,'List of Ledgers '!$G:$G,'P&L'!P6) -> 242217.9 | Q10: =SUMIFS('List of Ledgers '!$Q:$Q,'List of Ledgers '!$F:$F,'P&L'!$A$10,'List of Ledgers '!$G:$G,'P&L'!Q6) -> 0 | R10: =SUMIFS('List of Ledgers '!$Q:$Q,'List of Ledgers '!$F:$F,'P&L'!$A$10,'List of Ledgers '!$G:$G,'P&L'!R6) -> 0 | S10: =SUMIFS('List of Ledgers '!$Q:$Q,'List of Ledgers '!$F:$F,'P&L'!$A$10,'List of Ledgers '!$G:$G,'P&L'!S6) -> 0 | T10: =SUMIFS('List of Ledgers '!$Q:$Q,'List of Ledgers '!$F:$F,'P&L'!$A$10,'List of Ledgers '!$G:$G,'P&L'!T6) -> 0 | U10: =SUMIFS('List of Ledgers '!$Q:$Q,'List of Ledgers '!$F:$F,'P&L'!$A$10,'List of Ledgers '!$G:$G,'P&L'!U6) -> 2785094.6 | V10: =SUM(N10:U10) -> 3027312.5 | X10: =V10+W10 -> 3027312.5 | Y10: =V10-X10 -> 0
A11: Loading & Unloading charges | B11: =SUMIFS('List of Ledgers '!$L:$L,'List of Ledgers '!$F:$F,'P&L'!$A11,'List of Ledgers '!$G:$G,'P&L'!B$6) -> 0 | C11: =SUMIFS('List of Ledgers '!$L:$L,'List of Ledgers '!$F:$F,'P&L'!$A11,'List of Ledgers '!$G:$G,'P&L'!C$6) -> 0 | D11: =SUMIFS('List of Ledgers '!$L:$L,'List of Ledgers '!$F:$F,'P&L'!$A11,'List of Ledgers '!$G:$G,'P&L'!D$6) -> 0 | E11: =SUMIFS('List of Ledgers '!$L:$L,'List of Ledgers '!$F:$F,'P&L'!$A11,'List of Ledgers '!$G:$G,'P&L'!E$6) -> 0 | F11: =SUMIFS('List of Ledgers '!$L:$L,'List of Ledgers '!$F:$F,'P&L'!$A11,'List of Ledgers '!$G:$G,'P&L'!F$6) -> 0 | G11: =SUMIFS('List of Ledgers '!$L:$L,'List of Ledgers '!$F:$F,'P&L'!$A11,'List of Ledgers '!$G:$G,'P&L'!G$6) -> 18510 | H11: =SUMIFS('List of Ledgers '!$L:$L,'List of Ledgers '!$F:$F,'P&L'!$A11,'List of Ledgers '!$G:$G,'P&L'!H$6) -> 0 | I11: =SUMIFS('List of Ledgers '!$L:$L,'List of Ledgers '!$F:$F,'P&L'!$A11,'List of Ledgers '!$G:$G,'P&L'!I$6) -> 0 | J11: =SUM(B11:I11) -> 18510 | K11: =SUMIFS('List of Ledgers '!$L:$L,'List of Ledgers '!$F:$F,'P&L'!$A11,'List of Ledgers '!$G:$G,'P&L'!K$6) -> 0 | L11: =J11+K11 -> 18510 | N11: =SUMIFS('List of Ledgers '!$Q:$Q,'List of Ledgers '!$F:$F,'P&L'!$A$11,'List of Ledgers '!$G:$G,'P&L'!N6) -> 0 | O11: =SUMIFS('List of Ledgers '!$Q:$Q,'List of Ledgers '!$F:$F,'P&L'!$A$11,'List of Ledgers '!$G:$G,'P&L'!O6) -> 0 | P11: =SUMIFS('List of Ledgers '!$Q:$Q,'List of Ledgers '!$F:$F,'P&L'!$A$11,'List of Ledgers '!$G:$G,'P&L'!P6) -> 4750 | Q11: =SUMIFS('List of Ledgers '!$Q:$Q,'List of Ledgers '!$F:$F,'P&L'!$A$11,'List of Ledgers '!$G:$G,'P&L'!Q6) -> 0 | R11: =SUMIFS('List of Ledgers '!$Q:$Q,'List of Ledgers '!$F:$F,'P&L'!$A$11,'List of Ledgers '!$G:$G,'P&L'!R6) -> 0 | S11: =SUMIFS('List of Ledgers '!$Q:$Q,'List of Ledgers '!$F:$F,'P&L'!$A$11,'List of Ledgers '!$G:$G,'P&L'!S6) -> 60190 | T11: =SUMIFS('List of Ledgers '!$Q:$Q,'List of Ledgers '!$F:$F,'P&L'!$A$11,'List of Ledgers '!$G:$G,'P&L'!T6) -> 0 | U11: =SUMIFS('List of Ledgers '!$Q:$Q,'List of Ledgers '!$F:$F,'P&L'!$A$11,'List of Ledgers '!$G:$G,'P&L'!U6) -> 0 | V11: =SUM(N11:U11) -> 64940 | X11: =V11+W11 -> 64940 | Y11: =V11-X11 -> 0
A12: Freight & Shipping charges | B12: =SUMIFS('List of Ledgers '!$L:$L,'List of Ledgers '!$F:$F,'P&L'!$A12,'List of Ledgers '!$G:$G,'P&L'!B$6) -> 0 | C12: =SUMIFS('List of Ledgers '!$L:$L,'List of Ledgers '!$F:$F,'P&L'!$A12,'List of Ledgers '!$G:$G,'P&L'!C$6) -> 0 | D12: =SUMIFS('List of Ledgers '!$L:$L,'List of Ledgers '!$F:$F,'P&L'!$A12,'List of Ledgers '!$G:$G,'P&L'!D$6) -> 81550.92 | E12: =SUMIFS('List of Ledgers '!$L:$L,'List of Ledgers '!$F:$F,'P&L'!$A12,'List of Ledgers '!$G:$G,'P&L'!E$6) -> 0 | F12: =SUMIFS('List of Ledgers '!$L:$L,'List of Ledgers '!$F:$F,'P&L'!$A12,'List of Ledgers '!$G:$G,'P&L'!F$6) -> 0 | G12: =SUMIFS('List of Ledgers '!$L:$L,'List of Ledgers '!$F:$F,'P&L'!$A12,'List of Ledgers '!$G:$G,'P&L'!G$6) -> 0 | H12: =SUMIFS('List of Ledgers '!$L:$L,'List of Ledgers '!$F:$F,'P&L'!$A12,'List of Ledgers '!$G:$G,'P&L'!H$6) -> 0 | I12: =SUMIFS('List of Ledgers '!$L:$L,'List of Ledgers '!$F:$F,'P&L'!$A12,'List of Ledgers '!$G:$G,'P&L'!I$6) -> 251580.08 | J12: =SUM(B12:I12) -> 333131 | K12: =SUMIFS('List of Ledgers '!$L:$L,'List of Ledgers '!$F:$F,'P&L'!$A12,'List of Ledgers '!$G:$G,'P&L'!K$6) -> 0 | L12: =J12+K12 -> 333131 | N12: =SUMIFS('List of Ledgers '!$Q:$Q,'List of Ledgers '!$F:$F,'P&L'!$A$12,'List of Ledgers '!$G:$G,'P&L'!N6) -> 0 | O12: =SUMIFS('List of Ledgers '!$Q:$Q,'List of Ledgers '!$F:$F,'P&L'!$A$12,'List of Ledgers '!$G:$G,'P&L'!O6) -> 0 | P12: =SUMIFS('List of Ledgers '!$Q:$Q,'List of Ledgers '!$F:$F,'P&L'!$A$12,'List of Ledgers '!$G:$G,'P&L'!P6) -> 196185.92 | Q12: =SUMIFS('List of Ledgers '!$Q:$Q,'List of Ledgers '!$F:$F,'P&L'!$A$12,'List of Ledgers '!$G:$G,'P&L'!Q6) -> 0 | R12: =SUMIFS('List of Ledgers '!$Q:$Q,'List of Ledgers '!$F:$F,'P&L'!$A$12,'List of Ledgers '!$G:$G,'P&L'!R6) -> 0 | S12: =SUMIFS('List of Ledgers '!$Q:$Q,'List of Ledgers '!$F:$F,'P&L'!$A$12,'List of Ledgers '!$G:$G,'P&L'!S6) -> 0 | T12: =SUMIFS('List of Ledgers '!$Q:$Q,'List of Ledgers '!$F:$F,'P&L'!$A$12,'List of Ledgers '!$G:$G,'P&L'!T6) -> 0 | U12: =SUMIFS('List of Ledgers '!$Q:$Q,'List of Ledgers '!$F:$F,'P&L'!$A$12,'List of Ledgers '!$G:$G,'P&L'!U6) -> 811934.68 | V12: =SUM(N12:U12) -> 1008120.6 | X12: =V12+W12 -> 1008120.6 | Y12: =V12-X12 -> 0
A13: Export charges | B13: =SUMIFS('List of Ledgers '!$L:$L,'List of Ledgers '!$F:$F,'P&L'!$A13,'List of Ledgers '!$G:$G,'P&L'!B$6) -> 0 | C13: =SUMIFS('List of Ledgers '!$L:$L,'List of Ledgers '!$F:$F,'P&L'!$A13,'List of Ledgers '!$G:$G,'P&L'!C$6) -> 0 | D13: =SUMIFS('List of Ledgers '!$L:$L,'List of Ledgers '!$F:$F,'P&L'!$A13,'List of Ledgers '!$G:$G,'P&L'!D$6) -> -16833 | E13: =SUMIFS('List of Ledgers '!$L:$L,'List of Ledgers '!$F:$F,'P&L'!$A13,'List of Ledgers '!$G:$G,'P&L'!E$6) -> 0 | F13: =SUMIFS('List of Ledgers '!$L:$L,'List of Ledgers '!$F:$F,'P&L'!$A13,'List of Ledgers '!$G:$G,'P&L'!F$6) -> 0 | G13: =SUMIFS('List of Ledgers '!$L:$L,'List of Ledgers '!$F:$F,'P&L'!$A13,'List of Ledgers '!$G:$G,'P&L'!G$6) -> 0 | H13: =SUMIFS('List of Ledgers '!$L:$L,'List of Ledgers '!$F:$F,'P&L'!$A13,'List of Ledgers '!$G:$G,'P&L'!H$6) -> 0 | I13: =SUMIFS('List of Ledgers '!$L:$L,'List of Ledgers '!$F:$F,'P&L'!$A13,'List of Ledgers '!$G:$G,'P&L'!I$6) -> 0 | J13: =SUM(B13:I13) -> -16833 | K13: =SUMIFS('List of Ledgers '!$L:$L,'List of Ledgers '!$F:$F,'P&L'!$A13,'List of Ledgers '!$G:$G,'P&L'!K$6) -> 0 | L13: =J13+K13 -> -16833 | N13: =SUMIFS('List of Ledgers '!$Q:$Q,'List of Ledgers '!$F:$F,'P&L'!$A$13,'List of Ledgers '!$G:$G,'P&L'!N6) -> 0 | O13: =SUMIFS('List of Ledgers '!$Q:$Q,'List of Ledgers '!$F:$F,'P&L'!$A$13,'List of Ledgers '!$G:$G,'P&L'!O6) -> 0 | P13: =SUMIFS('List of Ledgers '!$Q:$Q,'List of Ledgers '!$F:$F,'P&L'!$A$13,'List of Ledgers '!$G:$G,'P&L'!P6) -> 1575 | Q13: =SUMIFS('List of Ledgers '!$Q:$Q,'List of Ledgers '!$F:$F,'P&L'!$A$13,'List of Ledgers '!$G:$G,'P&L'!Q6) -> 0 | R13: =SUMIFS('List of Ledgers '!$Q:$Q,'List of Ledgers '!$F:$F,'P&L'!$A$13,'List of Ledgers '!$G:$G,'P&L'!R6) -> 0 | S13: =SUMIFS('List of Ledgers '!$Q:$Q,'List of Ledgers '!$F:$F,'P&L'!$A$13,'List of Ledgers '!$G:$G,'P&L'!S6) -> 0 | T13: =SUMIFS('List of Ledgers '!$Q:$Q,'List of Ledgers '!$F:$F,'P&L'!$A$13,'List of Ledgers '!$G:$G,'P&L'!T6) -> 0 | U13: =SUMIFS('List of Ledgers '!$Q:$Q,'List of Ledgers '!$F:$F,'P&L'!$A$13,'List of Ledgers '!$G:$G,'P&L'!U6) -> 0 | V13: =SUM(N13:U13) -> 1575 | X13: =V13+W13 -> 1575 | Y13: =V13-X13 -> 0
A14: Insurance expenses | B14: =SUMIFS('List of Ledgers '!$L:$L,'List of Ledgers '!$F:$F,'P&L'!$A14,'List of Ledgers '!$G:$G,'P&L'!B$6) -> 0 | C14: =SUMIFS('List of Ledgers '!$L:$L,'List of Ledgers '!$F:$F,'P&L'!$A14,'List of Ledgers '!$G:$G,'P&L'!C$6) -> 0 | D14: =SUMIFS('List of Ledgers '!$L:$L,'List of Ledgers '!$F:$F,'P&L'!$A14,'List of Ledgers '!$G:$G,'P&L'!D$6) -> 14837 | E14: =SUMIFS('List of Ledgers '!$L:$L,'List of Ledgers '!$F:$F,'P&L'!$A14,'List of Ledgers '!$G:$G,'P&L'!E$6) -> 0 | F14: =SUMIFS('List of Ledgers '!$L:$L,'List of Ledgers '!$F:$F,'P&L'!$A14,'List of Ledgers '!$G:$G,'P&L'!F$6) -> 0 | G14: =SUMIFS('List of Ledgers '!$L:$L,'List of Ledgers '!$F:$F,'P&L'!$A14,'List of Ledgers '!$G:$G,'P&L'!G$6) -> 0 | H14: =SUMIFS('List of Ledgers '!$L:$L,'List of Ledgers '!$F:$F,'P&L'!$A14,'List of Ledgers '!$G:$G,'P&L'!H$6) -> 0 | I14: =SUMIFS('List of Ledgers '!$L:$L,'List of Ledgers '!$F:$F,'P&L'!$A14,'List of Ledgers '!$G:$G,'P&L'!I$6) -> 0 | J14: =SUM(B14:I14) -> 14837 | K14: =SUMIFS('List of Ledgers '!$L:$L,'List of Ledgers '!$F:$F,'P&L'!$A14,'List of Ledgers '!$G:$G,'P&L'!K$6) -> 0 | L14: =J14+K14 -> 14837 | N14: =SUMIFS('List of Ledgers '!$Q:$Q,'List of Ledgers '!$F:$F,'P&L'!$A$14,'List of Ledgers '!$G:$G,'P&L'!N6,'List of Ledgers '!E:E,'P&L'!A9) -> 0 | O14: =SUMIFS('List of Ledgers '!$Q:$Q,'List of Ledgers '!$F:$F,'P&L'!$A$14,'List of Ledgers '!$G:$G,'P&L'!O6,'List of Ledgers '!F:F,'P&L'!B9) -> 0 | P14: =SUMIFS('List of Ledgers '!$Q:$Q,'List of Ledgers '!$F:$F,'P&L'!$A$14,'List of Ledgers '!$G:$G,'P&L'!P6,'List of Ledgers '!E:E,'P&L'!A9) -> 177005 | Q14: =SUMIFS('List of Ledgers '!$Q:$Q,'List of Ledgers '!$F:$F,'P&L'!$A$14,'List of Ledgers '!$G:$G,'P&L'!Q6) -> 0 | R14: =SUMIFS('List of Ledgers '!$Q:$Q,'List of Ledgers '!$F:$F,'P&L'!$A$14,'List of Ledgers '!$G:$G,'P&L'!R6) -> 0 | S14: =SUMIFS('List of Ledgers '!$Q:$Q,'List of Ledgers '!$F:$F,'P&L'!$A$14,'List of Ledgers '!$G:$G,'P&L'!S6,'List of Ledgers '!H:H,'P&L'!D9) -> 0 | T14: =SUMIFS('List of Ledgers '!$Q:$Q,'List of Ledgers '!$F:$F,'P&L'!$A$14,'List of Ledgers '!$G:$G,'P&L'!T6) -> 0 | U14: =SUMIFS('List of Ledgers '!$Q:$Q,'List of Ledgers '!$F:$F,'P&L'!$A$14,'List of Ledgers '!$G:$G,'P&L'!U6) -> 0 | V14: =SUM(N14:U14) -> 177005 | X14: =V14+W14 -> 177005 | Y14: =V14-X14 -> 0
Y15: =V15-X15 -> 0
A16: Gross margin | B16: =B7-B8-B9 -> 0 | C16: =C7-C8-C9 -> 2.910383e-11 | D16: =D7-D8-D9 -> -96420.47 | E16: =E7-E8-E9 -> 0 | F16: =F7-F8-F9 -> 0 | G16: =G7-G8-G9 -> -35050 | H16: =H7-H8-H9 -> 0 | I16: =I7-I8-I9 -> 3336179.8 | ... L16: =L7-L8-L9 -> 3204709.3 | N16: =N7-N8-N9 -> -61053.05 | O16: =O7-O8-O9 -> 328384.55 | P16: =P7-P8-P9 -> 2881002.3 | Q16: =Q7-Q8-Q9 -> 0 | R16: =R7-R8-R9 -> 0 | S16: =S7-S8-S9 -> -77760 | T16: =T7-T8-T9 -> 0 | U16: =U7-U8-U9 -> 5640355.4 | V16: =V7-V8-V9 -> 8710929.3 | W16: =W7-W8 -> 0 | X16: =X7-X8-X9 -> 8710929.3 | Y16: =V16-X16 -> 0
A17: Gross margin % | B17: =IFERROR(B16/B7,0) -> 0 | C17: =IFERROR(C16/C7,0) -> 1.0235315e-15 | D17: =IFERROR(D16/D7,0) -> 0 | E17: =IFERROR(E16/E7,0) -> 0 | F17: =IFERROR(F16/F7,0) -> 0 | G17: =IFERROR(G16/G7,0) -> 0 | H17: =IFERROR(H16/H7,0) -> 0 | I17: =IFERROR(I16/I7,0) -> 0.04447491 | ... L17: =IFERROR(L16/L7,0) -> 0.042706077 | N17: =IFERROR(N16/N7,0) -> -0.034478633 | O17: =IFERROR(O16/O7,0) -> 0.39198862 | P17: =IFERROR(P16/P7,0) -> 0.027226701 | Q17: =IFERROR(Q16/Q7,0) -> 0 | R17: =IFERROR(R16/R7,0) -> 0 | S17: =IFERROR(S16/S7,0) -> 0 | T17: =IFERROR(T16/T7,0) -> 0 | U17: =IFERROR(U16/U7,0) -> 0.04704539 | ... X17: =IFERROR(X16/X7,0) -> 0.038153019 | Y17: =V17-X17 -> 0
A18: Gross margin % (previous month) | B18: 0 | C18: -3.20414 | D18: 0 | E18: 0 | F18: 0 | G18: 0 | H18: 0 | I18: 0.080499262 | J18: 0.07626975 | K18: 0 | L18: 0.07626975 | N18: -0.034478633 | O18: 0.44505527 | P18: 0.0092295017 | Q18: 0 | R18: 0 | S18: 0 | T18: 0 | U18: 0.10579676 | V18: 0.041737929 | W18: 0 | X18: 0.041737929 | Y18: =V18-X18 -> 0
Y19: =V19-X19 -> 0
A20: Indirect Income | B20: =SUM(B21:B27) -> 0 | C20: =SUM(C21:C27) -> 0 | D20: =SUM(D21:D27) -> 17000000 | E20: =SUM(E21:E27) -> 0 | F20: =SUM(F21:F27) -> 0 | G20: =SUM(G21:G27) -> 0 | H20: =SUM(H21:H27) -> 200000 | I20: =SUM(I21:I27) -> 0 | J20: =SUM(B20:I20) -> 17200000 | K20: =SUM(K21:K27) -> 0 | L20: =SUM(L21:L27) -> 17200000 | N20: =SUM(N21:N28) -> 0 | O20: =SUM(O21:O28) -> 0 | P20: =SUM(P21:P28) -> 17548744 | Q20: =SUM(Q21:Q28) -> 0 | R20: =SUM(R21:R28) -> 0 | S20: =SUM(S21:S28) -> 691117.44 | T20: =SUM(T21:T28) -> 200000 | U20: =SUM(U21:U28) -> 0 | ... W20: =SUM(W21:W28) -> -211354.2 | X20: =SUM(V20:W20) -> 18228507 | Y20: =V20-X20 -> 211354.2
A21: Foreign Exchange Gain | B21: =SUMIFS('List of Ledgers '!$L:$L,'List of Ledgers '!$F:$F,'P&L'!$A$21,'List of Ledgers '!$G:$G,'P&L'!B6) -> 0 | C21: =SUMIFS('List of Ledgers '!$L:$L,'List of Ledgers '!$F:$F,'P&L'!$A$21,'List of Ledgers '!$G:$G,'P&L'!C6) -> 0 | D21: =SUMIFS('List of Ledgers '!$L:$L,'List of Ledgers '!$F:$F,'P&L'!$A$21,'List of Ledgers '!$G:$G,'P&L'!D6) -> 0 | E21: =SUMIFS('List of Ledgers '!$L:$L,'List of Ledgers '!$F:$F,'P&L'!$A$21,'List of Ledgers '!$G:$G,'P&L'!E6) -> 0 | F21: =SUMIFS('List of Ledgers '!$L:$L,'List of Ledgers '!$F:$F,'P&L'!$A$21,'List of Ledgers '!$G:$G,'P&L'!F6) -> 0 | G21: =-SUMIFS('List of Ledgers '!$L:$L,'List of Ledgers '!$F:$F,'P&L'!$A$21,'List of Ledgers '!$G:$G,'P&L'!G6) -> 0 | H21: =SUMIFS('List of Ledgers '!$L:$L,'List of Ledgers '!$F:$F,'P&L'!$A$21,'List of Ledgers '!$G:$G,'P&L'!H6) -> 0 | I21: =SUMIFS('List of Ledgers '!$L:$L,'List of Ledgers '!$F:$F,'P&L'!$A$21,'List of Ledgers '!$G:$G,'P&L'!I6) -> 0 | J21: =SUM(B21:I21) -> 0 | K21: =SUMIFS('List of Ledgers '!$L:$L,'List of Ledgers '!$F:$F,'P&L'!$A$21,'List of Ledgers '!$G:$G,'P&L'!K6) -> 0 | L21: =J21+K21 -> 0 | N21: =-SUMIFS('List of Ledgers '!$Q:$Q,'List of Ledgers '!$F:$F,'P&L'!$A$21,'List of Ledgers '!$G:$G,'P&L'!N6) -> 0 | O21: =-SUMIFS('List of Ledgers '!$Q:$Q,'List of Ledgers '!$F:$F,'P&L'!$A$21,'List of Ledgers '!$G:$G,'P&L'!O6) -> 0 | P21: =-SUMIFS('List of Ledgers '!$Q:$Q,'List of Ledgers '!$F:$F,'P&L'!$A$21,'List of Ledgers '!$G:$G,'P&L'!P6) -> 0 | Q21: =-SUMIFS('List of Ledgers '!$Q:$Q,'List of Ledgers '!$F:$F,'P&L'!$A$21,'List of Ledgers '!$G:$G,'P&L'!Q6) -> 0 | R21: =-SUMIFS('List of Ledgers '!$Q:$Q,'List of Ledgers '!$F:$F,'P&L'!$A$21,'List of Ledgers '!$G:$G,'P&L'!R6) -> 0 | S21: =-SUMIFS('List of Ledgers '!$Q:$Q,'List of Ledgers '!$F:$F,'P&L'!$A$21,'List of Ledgers '!$G:$G,'P&L'!S6) -> 566542.44 | T21: =-SUMIFS('List of Ledgers '!$Q:$Q,'List of Ledgers '!$F:$F,'P&L'!$A$21,'List of Ledgers '!$G:$G,'P&L'!T6) -> 0 | U21: =-SUMIFS('List of Ledgers '!$Q:$Q,'List of Ledgers '!$F:$F,'P&L'!$A$21,'List of Ledgers '!$G:$G,'P&L'!U6) -> 0 | V21: =SUM(N21:U21) -> 566542.44 | W21: =-SUMIFS('List of Ledgers '!$Q:$Q,'List of Ledgers '!$F:$F,'P&L'!$A$21,'List of Ledgers '!$G:$G,'P&L'!W6) -> 0 | X21: =SUM(V21:W21) -> 566542.44 | Y21: =V21-X21 -> 0
A22: Exhibtion Income | B22: =SUMIFS('List of Ledgers '!$L:$L,'List of Ledgers '!$F:$F,'P&L'!$A$22,'List of Ledgers '!$G:$G,'P&L'!B6) -> 0 | C22: =SUMIFS('List of Ledgers '!$L:$L,'List of Ledgers '!$F:$F,'P&L'!$A$22,'List of Ledgers '!$G:$G,'P&L'!C6) -> 0 | D22: =SUMIFS('List of Ledgers '!$L:$L,'List of Ledgers '!$F:$F,'P&L'!$A$22,'List of Ledgers '!$G:$G,'P&L'!D6) -> 0 | E22: =SUMIFS('List of Ledgers '!$L:$L,'List of Ledgers '!$F:$F,'P&L'!$A$22,'List of Ledgers '!$G:$G,'P&L'!E6) -> 0 | F22: =SUMIFS('List of Ledgers '!$L:$L,'List of Ledgers '!$F:$F,'P&L'!$A$22,'List of Ledgers '!$G:$G,'P&L'!F6) -> 0 | G22: =SUMIFS('List of Ledgers '!$L:$L,'List of Ledgers '!$F:$F,'P&L'!$A$22,'List of Ledgers '!$G:$G,'P&L'!G6) -> 0 | H22: =-SUMIFS('List of Ledgers '!$L:$L,'List of Ledgers '!$F:$F,'P&L'!$A$22,'List of Ledgers '!$G:$G,'P&L'!H6) -> 200000 | I22: =SUMIFS('List of Ledgers '!$L:$L,'List of Ledgers '!$F:$F,'P&L'!$A$22,'List of Ledgers '!$G:$G,'P&L'!I6) -> 0 | J22: =SUM(B22:I22) -> 200000 | K22: =SUMIFS('List of Ledgers '!$L:$L,'List of Ledgers '!$F:$F,'P&L'!$A$22,'List of Ledgers '!$G:$G,'P&L'!K6) -> 0 | L22: =J22+K22 -> 200000 | N22: =-SUMIFS('List of Ledgers '!$Q:$Q,'List of Ledgers '!$F:$F,'P&L'!$A$22,'List of Ledgers '!$G:$G,'P&L'!N6) -> 0 | O22: =-SUMIFS('List of Ledgers '!$Q:$Q,'List of Ledgers '!$F:$F,'P&L'!$A$22,'List of Ledgers '!$G:$G,'P&L'!O6) -> 0 | P22: =-SUMIFS('List of Ledgers '!$Q:$Q,'List of Ledgers '!$F:$F,'P&L'!$A$22,'List of Ledgers '!$G:$G,'P&L'!P6) -> 0 | Q22: =-SUMIFS('List of Ledgers '!$Q:$Q,'List of Ledgers '!$F:$F,'P&L'!$A$22,'List of Ledgers '!$G:$G,'P&L'!Q6) -> 0 | R22: =-SUMIFS('List of Ledgers '!$Q:$Q,'List of Ledgers '!$F:$F,'P&L'!$A$22,'List of Ledgers '!$G:$G,'P&L'!R6) -> 0 | S22: =-SUMIFS('List of Ledgers '!$Q:$Q,'List of Ledgers '!$F:$F,'P&L'!$A$22,'List of Ledgers '!$G:$G,'P&L'!S6) -> 0 | T22: =-SUMIFS('List of Ledgers '!$Q:$Q,'List of Ledgers '!$F:$F,'P&L'!$A$22,'List of Ledgers '!$G:$G,'P&L'!T6) -> 200000 | U22: =-SUMIFS('List of Ledgers '!$Q:$Q,'List of Ledgers '!$F:$F,'P&L'!$A$22,'List of Ledgers '!$G:$G,'P&L'!U6) -> 0 | V22: =SUM(N22:U22) -> 200000 | W22: =-SUMIFS('List of Ledgers '!$Q:$Q,'List of Ledgers '!$F:$F,'P&L'!$A$21,'List of Ledgers '!$G:$G,'P&L'!W7) -> 0
A23: Commission | B23: =SUMIFS('List of Ledgers '!$L:$L,'List of Ledgers '!$F:$F,'P&L'!$A$23,'List of Ledgers '!$G:$G,'P&L'!B6) -> 0 | C23: =SUMIFS('List of Ledgers '!$L:$L,'List of Ledgers '!$F:$F,'P&L'!$A$23,'List of Ledgers '!$G:$G,'P&L'!C6) -> 0 | D23: =-SUMIFS('List of Ledgers '!$L:$L,'List of Ledgers '!$F:$F,'P&L'!$A$23,'List of Ledgers '!$G:$G,'P&L'!D6) -> 17000000 | E23: =SUMIFS('List of Ledgers '!$L:$L,'List of Ledgers '!$F:$F,'P&L'!$A$23,'List of Ledgers '!$G:$G,'P&L'!E6) -> 0 | F23: =SUMIFS('List of Ledgers '!$L:$L,'List of Ledgers '!$F:$F,'P&L'!$A$23,'List of Ledgers '!$G:$G,'P&L'!F6) -> 0 | G23: =SUMIFS('List of Ledgers '!$L:$L,'List of Ledgers '!$F:$F,'P&L'!$A$23,'List of Ledgers '!$G:$G,'P&L'!G6) -> 0 | H23: =SUMIFS('List of Ledgers '!$L:$L,'List of Ledgers '!$F:$F,'P&L'!$A$23,'List of Ledgers '!$G:$G,'P&L'!H6) -> 0 | I23: =SUMIFS('List of Ledgers '!$L:$L,'List of Ledgers '!$F:$F,'P&L'!$A$23,'List of Ledgers '!$G:$G,'P&L'!I6) -> 0 | J23: =SUM(B23:I23) -> 17000000 | K23: =SUMIFS('List of Ledgers '!$L:$L,'List of Ledgers '!$F:$F,'P&L'!$A$21,'List of Ledgers '!$G:$G,'P&L'!K7) -> 0 | L23: =J23+K23 -> 17000000 | N23: =-SUMIFS('List of Ledgers '!$Q:$Q,'List of Ledgers '!$F:$F,'P&L'!$A$23,'List of Ledgers '!$G:$G,'P&L'!N6) -> 0 | O23: =-SUMIFS('List of Ledgers '!$Q:$Q,'List of Ledgers '!$F:$F,'P&L'!$A$23,'List of Ledgers '!$G:$G,'P&L'!O6) -> 0 | P23: =-SUMIFS('List of Ledgers '!$Q:$Q,'List of Ledgers '!$F:$F,'P&L'!$A$23,'List of Ledgers '!$G:$G,'P&L'!P6) -> 17548744 | Q23: =-SUMIFS('List of Ledgers '!$Q:$Q,'List of Ledgers '!$F:$F,'P&L'!$A$23,'List of Ledgers '!$G:$G,'P&L'!Q6) -> 0 | R23: =-SUMIFS('List of Ledgers '!$Q:$Q,'List of Ledgers '!$F:$F,'P&L'!$A$23,'List of Ledgers '!$G:$G,'P&L'!R6) -> 0 | S23: =-SUMIFS('List of Ledgers '!$Q:$Q,'List of Ledgers '!$F:$F,'P&L'!$A$23,'List of Ledgers '!$G:$G,'P&L'!S6) -> 0 | T23: =-SUMIFS('List of Ledgers '!$Q:$Q,'List of Ledgers '!$F:$F,'P&L'!$A$23,'List of Ledgers '!$G:$G,'P&L'!T6) -> 0 | U23: =-SUMIFS('List of Ledgers '!$Q:$Q,'List of Ledgers '!$F:$F,'P&L'!$A$23,'List of Ledgers '!$G:$G,'P&L'!U6) -> 0 | V23: =SUM(N23:U23) -> 17548744 | W23: =-SUMIFS('List of Ledgers '!$Q:$Q,'List of Ledgers '!$F:$F,'P&L'!$A$23,'List of Ledgers '!$G:$G,'P&L'!W6) -> 0 | X23: =SUM(V23:W23) -> 17548744 | Y23: =V23-X23 -> 0
A24: Dividend | B24: =SUMIFS('List of Ledgers '!$L:$L,'List of Ledgers '!$F:$F,'P&L'!$A$24,'List of Ledgers '!$G:$G,'P&L'!B6) -> 0 | C24: =SUMIFS('List of Ledgers '!$L:$L,'List of Ledgers '!$F:$F,'P&L'!$A$24,'List of Ledgers '!$G:$G,'P&L'!C6) -> 0 | D24: =SUMIFS('List of Ledgers '!$L:$L,'List of Ledgers '!$F:$F,'P&L'!$A$24,'List of Ledgers '!$G:$G,'P&L'!D6) -> 0 | E24: =SUMIFS('List of Ledgers '!$L:$L,'List of Ledgers '!$F:$F,'P&L'!$A$24,'List of Ledgers '!$G:$G,'P&L'!E6) -> 0 | F24: =SUMIFS('List of Ledgers '!$L:$L,'List of Ledgers '!$F:$F,'P&L'!$A$24,'List of Ledgers '!$G:$G,'P&L'!F6) -> 0 | G24: =SUMIFS('List of Ledgers '!$L:$L,'List of Ledgers '!$F:$F,'P&L'!$A$24,'List of Ledgers '!$G:$G,'P&L'!G6) -> 0 | H24: =SUMIFS('List of Ledgers '!$L:$L,'List of Ledgers '!$F:$F,'P&L'!$A$24,'List of Ledgers '!$G:$G,'P&L'!H6) -> 0 | I24: =SUMIFS('List of Ledgers '!$L:$L,'List of Ledgers '!$F:$F,'P&L'!$A$24,'List of Ledgers '!$G:$G,'P&L'!I6) -> 0 | J24: =SUM(B24:I24) -> 0 | K24: =SUMIFS('List of Ledgers '!$L:$L,'List of Ledgers '!$F:$F,'P&L'!$A$21,'List of Ledgers '!$G:$G,'P&L'!K8) -> 0 | L24: =J24+K24 -> 0 | N24: =-SUMIFS('List of Ledgers '!$Q:$Q,'List of Ledgers '!$F:$F,'P&L'!$A$24,'List of Ledgers '!$G:$G,'P&L'!N6) -> 0 | O24: =-SUMIFS('List of Ledgers '!$Q:$Q,'List of Ledgers '!$F:$F,'P&L'!$A$24,'List of Ledgers '!$G:$G,'P&L'!O6) -> 0 | P24: =-SUMIFS('List of Ledgers '!$Q:$Q,'List of Ledgers '!$F:$F,'P&L'!$A$24,'List of Ledgers '!$G:$G,'P&L'!P6) -> 0 | Q24: =-SUMIFS('List of Ledgers '!$Q:$Q,'List of Ledgers '!$F:$F,'P&L'!$A$24,'List of Ledgers '!$G:$G,'P&L'!Q6) -> 0 | R24: =-SUMIFS('List of Ledgers '!$Q:$Q,'List of Ledgers '!$F:$F,'P&L'!$A$24,'List of Ledgers '!$G:$G,'P&L'!R6) -> 0 | S24: =-SUMIFS('List of Ledgers '!$Q:$Q,'List of Ledgers '!$F:$F,'P&L'!$A$24,'List of Ledgers '!$G:$G,'P&L'!S6) -> 0 | T24: =-SUMIFS('List of Ledgers '!$Q:$Q,'List of Ledgers '!$F:$F,'P&L'!$A$24,'List of Ledgers '!$G:$G,'P&L'!T6) -> 0 | U24: =-SUMIFS('List of Ledgers '!$Q:$Q,'List of Ledgers '!$F:$F,'P&L'!$A$24,'List of Ledgers '!$G:$G,'P&L'!U6) -> 0 | V24: =SUM(N24:U24) -> 0 | W24: =-SUMIFS('List of Ledgers '!$Q:$Q,'List of Ledgers '!$F:$F,'P&L'!$A$24,'List of Ledgers '!$G:$G,'P&L'!W6) -> 10487 | X24: =SUM(V24:W24) -> 10487 | Y24: =V24-X24 -> -10487
A25: Interest Income | B25: =SUMIFS('List of Ledgers '!$L:$L,'List of Ledgers '!$F:$F,'P&L'!$A$25,'List of Ledgers '!$G:$G,'P&L'!B6) -> 0 | C25: =SUMIFS('List of Ledgers '!$L:$L,'List of Ledgers '!$F:$F,'P&L'!$A$25,'List of Ledgers '!$G:$G,'P&L'!C6) -> 0 | D25: =SUMIFS('List of Ledgers '!$L:$L,'List of Ledgers '!$F:$F,'P&L'!$A$25,'List of Ledgers '!$G:$G,'P&L'!D6) -> 0 | E25: =SUMIFS('List of Ledgers '!$L:$L,'List of Ledgers '!$F:$F,'P&L'!$A$25,'List of Ledgers '!$G:$G,'P&L'!E6) -> 0 | F25: =SUMIFS('List of Ledgers '!$L:$L,'List of Ledgers '!$F:$F,'P&L'!$A$25,'List of Ledgers '!$G:$G,'P&L'!F6) -> 0 | G25: =SUMIFS('List of Ledgers '!$L:$L,'List of Ledgers '!$F:$F,'P&L'!$A$25,'List of Ledgers '!$G:$G,'P&L'!G6) -> 0 | H25: =SUMIFS('List of Ledgers '!$L:$L,'List of Ledgers '!$F:$F,'P&L'!$A$25,'List of Ledgers '!$G:$G,'P&L'!H6) -> 0 | I25: =SUMIFS('List of Ledgers '!$L:$L,'List of Ledgers '!$F:$F,'P&L'!$A$25,'List of Ledgers '!$G:$G,'P&L'!I6) -> 0 | J25: =SUM(B25:I25) -> 0 | K25: =SUMIFS('List of Ledgers '!$L:$L,'List of Ledgers '!$F:$F,'P&L'!$A$21,'List of Ledgers '!$G:$G,'P&L'!K9) -> 0 | L25: =J25+K25 -> 0 | N25: =-SUMIFS('List of Ledgers '!$Q:$Q,'List of Ledgers '!$F:$F,'P&L'!$A$25,'List of Ledgers '!$G:$G,'P&L'!N6) -> 0 | O25: =-SUMIFS('List of Ledgers '!$Q:$Q,'List of Ledgers '!$F:$F,'P&L'!$A$25,'List of Ledgers '!$G:$G,'P&L'!O6) -> 0 | P25: =-SUMIFS('List of Ledgers '!$Q:$Q,'List of Ledgers '!$F:$F,'P&L'!$A$25,'List of Ledgers '!$G:$G,'P&L'!P6) -> 0 | Q25: =-SUMIFS('List of Ledgers '!$Q:$Q,'List of Ledgers '!$F:$F,'P&L'!$A$25,'List of Ledgers '!$G:$G,'P&L'!Q6) -> 0 | R25: =-SUMIFS('List of Ledgers '!$Q:$Q,'List of Ledgers '!$F:$F,'P&L'!$A$25,'List of Ledgers '!$G:$G,'P&L'!R6) -> 0 | S25: =-SUMIFS('List of Ledgers '!$Q:$Q,'List of Ledgers '!$F:$F,'P&L'!$A$25,'List of Ledgers '!$G:$G,'P&L'!S6) -> 124575 | T25: =-SUMIFS('List of Ledgers '!$Q:$Q,'List of Ledgers '!$F:$F,'P&L'!$A$25,'List of Ledgers '!$G:$G,'P&L'!T6) -> 0 | U25: =-SUMIFS('List of Ledgers '!$Q:$Q,'List of Ledgers '!$F:$F,'P&L'!$A$25,'List of Ledgers '!$G:$G,'P&L'!U6) -> 0 | V25: =SUM(N25:U25) -> 124575 | W25: =-SUMIFS('List of Ledgers '!$Q:$Q,'List of Ledgers '!$F:$F,'P&L'!$A$25,'List of Ledgers '!$G:$G,'P&L'!W6) -> 0 | X25: =SUM(V25:W25) -> 124575 | Y25: =V25-X25 -> 0
A26: Short term Capital Gain | B26: =SUMIFS('List of Ledgers '!$L:$L,'List of Ledgers '!$F:$F,'P&L'!$A$26,'List of Ledgers '!$G:$G,'P&L'!B6) -> 0 | C26: =SUMIFS('List of Ledgers '!$L:$L,'List of Ledgers '!$F:$F,'P&L'!$A$26,'List of Ledgers '!$G:$G,'P&L'!C6) -> 0 | D26: =SUMIFS('List of Ledgers '!$L:$L,'List of Ledgers '!$F:$F,'P&L'!$A$26,'List of Ledgers '!$G:$G,'P&L'!D6) -> 0 | E26: =SUMIFS('List of Ledgers '!$L:$L,'List of Ledgers '!$F:$F,'P&L'!$A$26,'List of Ledgers '!$G:$G,'P&L'!E6) -> 0 | F26: =SUMIFS('List of Ledgers '!$L:$L,'List of Ledgers '!$F:$F,'P&L'!$A$26,'List of Ledgers '!$G:$G,'P&L'!F6) -> 0 | G26: =SUMIFS('List of Ledgers '!$L:$L,'List of Ledgers '!$F:$F,'P&L'!$A$26,'List of Ledgers '!$G:$G,'P&L'!G6) -> 0 | H26: =SUMIFS('List of Ledgers '!$L:$L,'List of Ledgers '!$F:$F,'P&L'!$A$26,'List of Ledgers '!$G:$G,'P&L'!H6) -> 0 | I26: =SUMIFS('List of Ledgers '!$L:$L,'List of Ledgers '!$F:$F,'P&L'!$A$26,'List of Ledgers '!$G:$G,'P&L'!I6) -> 0 | J26: =SUM(B26:I26) -> 0 | K26: =SUMIFS('List of Ledgers '!$L:$L,'List of Ledgers '!$F:$F,'P&L'!$A$21,'List of Ledgers '!$G:$G,'P&L'!K10) -> 0 | L26: =J26+K26 -> 0 | N26: =-SUMIFS('List of Ledgers '!$Q:$Q,'List of Ledgers '!$F:$F,'P&L'!$A$26,'List of Ledgers '!$G:$G,'P&L'!N6) -> 0 | O26: =-SUMIFS('List of Ledgers '!$Q:$Q,'List of Ledgers '!$F:$F,'P&L'!$A$26,'List of Ledgers '!$G:$G,'P&L'!O6) -> 0 | P26: =-SUMIFS('List of Ledgers '!$Q:$Q,'List of Ledgers '!$F:$F,'P&L'!$A$26,'List of Ledgers '!$G:$G,'P&L'!P6) -> 0 | Q26: =-SUMIFS('List of Ledgers '!$Q:$Q,'List of Ledgers '!$F:$F,'P&L'!$A$26,'List of Ledgers '!$G:$G,'P&L'!Q6) -> 0 | R26: =-SUMIFS('List of Ledgers '!$Q:$Q,'List of Ledgers '!$F:$F,'P&L'!$A$26,'List of Ledgers '!$G:$G,'P&L'!R6) -> 0 | S26: =-SUMIFS('List of Ledgers '!$Q:$Q,'List of Ledgers '!$F:$F,'P&L'!$A$26,'List of Ledgers '!$G:$G,'P&L'!S6) -> 0 | T26: =-SUMIFS('List of Ledgers '!$Q:$Q,'List of Ledgers '!$F:$F,'P&L'!$A$26,'List of Ledgers '!$G:$G,'P&L'!T6) -> 0 | U26: =-SUMIFS('List of Ledgers '!$Q:$Q,'List of Ledgers '!$F:$F,'P&L'!$A$26,'List of Ledgers '!$G:$G,'P&L'!U6) -> 0 | V26: =SUM(N26:U26) -> 0 | W26: =-SUMIFS('List of Ledgers '!$Q:$Q,'List of Ledgers '!$F:$F,'P&L'!$A$26,'List of Ledgers '!$G:$G,'P&L'!W6) -> 465583.48 | X26: =SUM(V26:W26) -> 465583.48 | Y26: =V26-X26 -> -465583.48
A27: Profit on sale of Investment | B27: =SUMIFS('List of Ledgers '!$L:$L,'List of Ledgers '!$F:$F,'P&L'!$A$27,'List of Ledgers '!$G:$G,'P&L'!B6) -> 0 | C27: =SUMIFS('List of Ledgers '!$L:$L,'List of Ledgers '!$F:$F,'P&L'!$A$27,'List of Ledgers '!$G:$G,'P&L'!C6) -> 0 | D27: =SUMIFS('List of Ledgers '!$L:$L,'List of Ledgers '!$F:$F,'P&L'!$A$27,'List of Ledgers '!$G:$G,'P&L'!D6) -> 0 | E27: =SUMIFS('List of Ledgers '!$L:$L,'List of Ledgers '!$F:$F,'P&L'!$A$27,'List of Ledgers '!$G:$G,'P&L'!E6) -> 0 | F27: =SUMIFS('List of Ledgers '!$L:$L,'List of Ledgers '!$F:$F,'P&L'!$A$27,'List of Ledgers '!$G:$G,'P&L'!F6) -> 0 | G27: =SUMIFS('List of Ledgers '!$L:$L,'List of Ledgers '!$F:$F,'P&L'!$A$27,'List of Ledgers '!$G:$G,'P&L'!G6) -> 0 | H27: =SUMIFS('List of Ledgers '!$L:$L,'List of Ledgers '!$F:$F,'P&L'!$A$27,'List of Ledgers '!$G:$G,'P&L'!H6) -> 0 | I27: =SUMIFS('List of Ledgers '!$L:$L,'List of Ledgers '!$F:$F,'P&L'!$A$27,'List of Ledgers '!$G:$G,'P&L'!I6) -> 0 | J27: =SUM(B27:I27) -> 0 | K27: =SUMIFS('List of Ledgers '!$L:$L,'List of Ledgers '!$F:$F,'P&L'!$A$21,'List of Ledgers '!$G:$G,'P&L'!K11) -> 0 | L27: =J27+K27 -> 0 | N27: =-SUMIFS('List of Ledgers '!$Q:$Q,'List of Ledgers '!$F:$F,'P&L'!$A$27,'List of Ledgers '!$G:$G,'P&L'!N6) -> 0 | O27: =-SUMIFS('List of Ledgers '!$Q:$Q,'List of Ledgers '!$F:$F,'P&L'!$A$27,'List of Ledgers '!$G:$G,'P&L'!O6) -> 0 | P27: =-SUMIFS('List of Ledgers '!$Q:$Q,'List of Ledgers '!$F:$F,'P&L'!$A$27,'List of Ledgers '!$G:$G,'P&L'!P6) -> 0 | Q27: =-SUMIFS('List of Ledgers '!$Q:$Q,'List of Ledgers '!$F:$F,'P&L'!$A$27,'List of Ledgers '!$G:$G,'P&L'!Q6) -> 0 | R27: =-SUMIFS('List of Ledgers '!$Q:$Q,'List of Ledgers '!$F:$F,'P&L'!$A$27,'List of Ledgers '!$G:$G,'P&L'!R6) -> 0 | S27: =-SUMIFS('List of Ledgers '!$Q:$Q,'List of Ledgers '!$F:$F,'P&L'!$A$27,'List of Ledgers '!$G:$G,'P&L'!S6) -> 0 | T27: =-SUMIFS('List of Ledgers '!$Q:$Q,'List of Ledgers '!$F:$F,'P&L'!$A$27,'List of Ledgers '!$G:$G,'P&L'!T6) -> 0 | U27: =-SUMIFS('List of Ledgers '!$Q:$Q,'List of Ledgers '!$F:$F,'P&L'!$A$27,'List of Ledgers '!$G:$G,'P&L'!U6) -> 0 | V27: =SUM(N27:U27) -> 0 | W27: =-SUMIFS('List of Ledgers '!$Q:$Q,'List of Ledgers '!$F:$F,'P&L'!$A$27,'List of Ledgers '!$G:$G,'P&L'!W6) -> 23630.29 | X27: =SUM(V27:W27) -> 23630.29 | Y27: =V27-X27 -> -23630.29
A28: Capital Loss | B28: =SUMIFS('List of Ledgers '!$L:$L,'List of Ledgers '!$F:$F,'P&L'!$A$28,'List of Ledgers '!$G:$G,'P&L'!B6) -> 0 | C28: =SUMIFS('List of Ledgers '!$L:$L,'List of Ledgers '!$F:$F,'P&L'!$A$28,'List of Ledgers '!$G:$G,'P&L'!C6) -> 0 | D28: =SUMIFS('List of Ledgers '!$L:$L,'List of Ledgers '!$F:$F,'P&L'!$A$28,'List of Ledgers '!$G:$G,'P&L'!D6) -> 0 | E28: =SUMIFS('List of Ledgers '!$L:$L,'List of Ledgers '!$F:$F,'P&L'!$A$28,'List of Ledgers '!$G:$G,'P&L'!E6) -> 0 | F28: =SUMIFS('List of Ledgers '!$L:$L,'List of Ledgers '!$F:$F,'P&L'!$A$28,'List of Ledgers '!$G:$G,'P&L'!F6) -> 0 | G28: =SUMIFS('List of Ledgers '!$L:$L,'List of Ledgers '!$F:$F,'P&L'!$A$28,'List of Ledgers '!$G:$G,'P&L'!G6) -> 0 | H28: =SUMIFS('List of Ledgers '!$L:$L,'List of Ledgers '!$F:$F,'P&L'!$A$28,'List of Ledgers '!$G:$G,'P&L'!H6) -> 0 | I28: =SUMIFS('List of Ledgers '!$L:$L,'List of Ledgers '!$F:$F,'P&L'!$A$28,'List of Ledgers '!$G:$G,'P&L'!I6) -> 0 | J28: =SUM(B28:I28) -> 0 | K28: =SUMIFS('List of Ledgers '!$L:$L,'List of Ledgers '!$F:$F,'P&L'!$A$28,'List of Ledgers '!$G:$G,'P&L'!K6) -> 0 | L28: =J28+K28 -> 0 | N28: =-SUMIFS('List of Ledgers '!$Q:$Q,'List of Ledgers '!$F:$F,$A$28,'List of Ledgers '!$G:$G,'P&L'!N6) -> 0 | O28: =-SUMIFS('List of Ledgers '!$Q:$Q,'List of Ledgers '!$F:$F,$A$28,'List of Ledgers '!$G:$G,'P&L'!O6) -> 0 | P28: =-SUMIFS('List of Ledgers '!$Q:$Q,'List of Ledgers '!$F:$F,$A$28,'List of Ledgers '!$G:$G,'P&L'!P6) -> 0 | Q28: =-SUMIFS('List of Ledgers '!$Q:$Q,'List of Ledgers '!$F:$F,$A$28,'List of Ledgers '!$G:$G,'P&L'!Q6) -> 0 | R28: =-SUMIFS('List of Ledgers '!$Q:$Q,'List of Ledgers '!$F:$F,$A$28,'List of Ledgers '!$G:$G,'P&L'!R6) -> 0 | S28: =-SUMIFS('List of Ledgers '!$Q:$Q,'List of Ledgers '!$F:$F,$A$28,'List of Ledgers '!$G:$G,'P&L'!S6) -> 0 | T28: =-SUMIFS('List of Ledgers '!$Q:$Q,'List of Ledgers '!$F:$F,$A$28,'List of Ledgers '!$G:$G,'P&L'!T6) -> 0 | U28: =-SUMIFS('List of Ledgers '!$Q:$Q,'List of Ledgers '!$F:$F,$A$28,'List of Ledgers '!$G:$G,'P&L'!U6) -> 0 | ... W28: =-SUMIFS('List of Ledgers '!$Q:$Q,'List of Ledgers '!$F:$F,$A$28,'List of Ledgers '!$G:$G,'P&L'!W6) -> -711054.97 | X28: =SUM(V28:W28) -> -711054.97 | Y28: =V28-X28 -> 711054.97
Y29: =V29-X29 -> 0
A30: Depreciation & amortization | B30: 0 | C30: 0 | D30: 0 | E30: 0 | F30: 0 | K30: 0 | L30: =SUM(J30:K30) -> 0 | N30: 0 | O30: 0 | P30: 0 | Q30: 0 | R30: 0 | W30: 0 | X30: =SUM(V30:W30) -> 0 | Y30: =V30-X30 -> 0
A31: Net income | B31: =B20+B16 -> 0 | C31: =C20+C16 -> 2.910383e-11 | D31: =D20+D16 -> 16903580 | E31: =E20+E16 -> 0 | F31: =F20+F16 -> 0 | G31: =G20+G16 -> -35050 | H31: =H20+H16 -> 200000 | I31: =I20+I16 -> 3336179.8 | ... L31: =L20+L16 -> 20404709 | N31: =N20+N16 -> -61053.05 | O31: =O20+O16 -> 328384.55 | P31: =P20+P16 -> 20429747 | Q31: =Q20+Q16 -> 0 | R31: =R20+R16 -> 0 | S31: =S20+S16 -> 613357.44 | T31: =T20+T16 -> 200000 | U31: =U20+U16 -> 5640355.4 | ... X31: =X20+X16 -> 26939437 | Y31: =V31-X31 -> 211354.2
A32: Net allocable income | B32: 0 | C32: =G31*C7/J7 -> -13.281222 | D32: {=SUM($G$30:$G$30/4)} -> 0 | E32: 0 | F32: 0 | G32: =-G31 -> 35050 | H32: {=SUM($G$30:$G$30/4)} -> 0 | I32: =G31*I7/J7 -> -35036.719 | J32: =SUM(B32:I32) -> 0 | K32: =-K31 -> 0 | L32: =SUM(J32:K32) -> 0 | N32: =S31*N7/V7 -> 4757.0245 | O32: =S31*O7/V7 -> 2250.543 | P32: =S31*P7/V7 -> 284267.13 | R32: 0 | S32: =-S31 -> -613357.44 | T32: =-T31 -> -200000 | U32: =S31*U7/V7 -> 322082.74 | V32: =SUM(N32:U32) -> -200000 | W32: =-W31 -> 211354.2 | X32: =SUM(V32:W32) -> 11354.2 | Y32: =V32-X32 -> -211354.2
Y33: =V33-X33 -> 0
Y34: =V34-X34 -> 0
A35: 6. Indirect Expense | Y35: =V35-X35 -> 0
A36: Audit Fees | B36: =SUMIFS('List of Ledgers '!$L:$L,'List of Ledgers '!$F:$F,'P&L'!$A$36,'List of Ledgers '!$G:$G,'P&L'!B$6) -> 0 | C36: =SUMIFS('List of Ledgers '!$L:$L,'List of Ledgers '!$F:$F,'P&L'!$A$36,'List of Ledgers '!$G:$G,'P&L'!C6) -> 0 | D36: =SUMIFS('List of Ledgers '!$L:$L,'List of Ledgers '!$F:$F,'P&L'!$A$36,'List of Ledgers '!$G:$G,'P&L'!D6) -> 0 | E36: =SUMIFS('List of Ledgers '!$L:$L,'List of Ledgers '!$F:$F,'P&L'!$A$36,'List of Ledgers '!$G:$G,'P&L'!E6) -> 0 | F36: =SUMIFS('List of Ledgers '!$L:$L,'List of Ledgers '!$F:$F,'P&L'!$A$36,'List of Ledgers '!$G:$G,'P&L'!F6) -> 0 | G36: =SUMIFS('List of Ledgers '!$L:$L,'List of Ledgers '!$F:$F,'P&L'!$A$36,'List of Ledgers '!$G:$G,'P&L'!G6) -> 0 | H36: =SUMIFS('List of Ledgers '!$L:$L,'List of Ledgers '!$F:$F,'P&L'!$A$36,'List of Ledgers '!$G:$G,'P&L'!H6) -> 0 | I36: =SUMIFS('List of Ledgers '!$L:$L,'List of Ledgers '!$F:$F,'P&L'!$A$36,'List of Ledgers '!$G:$G,'P&L'!I6) -> 0 | J36: =SUM(B36:I36) -> 0 | K36: =SUMIFS('List of Ledgers '!$L:$L,'List of Ledgers '!$F:$F,'P&L'!$A36,'List of Ledgers '!$G:$G,'P&L'!$K$6) -> 0 | L36: =J36+K36 -> 0 | N36: =SUMIFS('List of Ledgers '!$Q:$Q,'List of Ledgers '!$F:$F,'P&L'!$A36,'List of Ledgers '!$G:$G,'P&L'!N$6) -> 0 | O36: =SUMIFS('List of Ledgers '!$Q:$Q,'List of Ledgers '!$F:$F,'P&L'!$A36,'List of Ledgers '!$G:$G,'P&L'!O$6) -> 0 | P36: =SUMIFS('List of Ledgers '!$Q:$Q,'List of Ledgers '!$F:$F,'P&L'!$A36,'List of Ledgers '!$G:$G,'P&L'!P$6) -> 0 | Q36: =SUMIFS('List of Ledgers '!$Q:$Q,'List of Ledgers '!$F:$F,'P&L'!$A36,'List of Ledgers '!$G:$G,'P&L'!Q$6) -> 0 | R36: =SUMIFS('List of Ledgers '!$Q:$Q,'List of Ledgers '!$F:$F,'P&L'!$A36,'List of Ledgers '!$G:$G,'P&L'!R$6) -> 0 | S36: =SUMIFS('List of Ledgers '!$Q:$Q,'List of Ledgers '!$F:$F,'P&L'!$A36,'List of Ledgers '!$G:$G,'P&L'!S$6) -> 220000 | T36: =SUMIFS('List of Ledgers '!$Q:$Q,'List of Ledgers '!$F:$F,'P&L'!$A36,'List of Ledgers '!$G:$G,'P&L'!T$6) -> 0 | U36: =SUMIFS('List of Ledgers '!$Q:$Q,'List of Ledgers '!$F:$F,'P&L'!$A36,'List of Ledgers '!$G:$G,'P&L'!U$6) -> 0 | V36: =SUM(N36:U36) -> 220000 | W36: =SUMIFS('List of Ledgers '!$Q:$Q,'List of Ledgers '!$F:$F,'P&L'!$A36,'List of Ledgers '!$G:$G,'P&L'!W$6) -> 0 | X36: =V36+W36 -> 220000 | Y36: =V36-X36 -> 0
A37: Accomodation expenses | B37: =SUMIFS('List of Ledgers '!$L:$L,'List of Ledgers '!$F:$F,'P&L'!$A37,'List of Ledgers '!$G:$G,'P&L'!B$6) -> 0 | C37: =SUMIFS('List of Ledgers '!$L:$L,'List of Ledgers '!$F:$F,'P&L'!$A37,'List of Ledgers '!$G:$G,'P&L'!C$6) -> 0 | D37: =SUMIFS('List of Ledgers '!$L:$L,'List of Ledgers '!$F:$F,'P&L'!$A37,'List of Ledgers '!$G:$G,'P&L'!D$6) -> 81813.94 | E37: =SUMIFS('List of Ledgers '!$L:$L,'List of Ledgers '!$F:$F,'P&L'!$A37,'List of Ledgers '!$G:$G,'P&L'!E$6) -> 0 | F37: =SUMIFS('List of Ledgers '!$L:$L,'List of Ledgers '!$F:$F,'P&L'!$A37,'List of Ledgers '!$G:$G,'P&L'!F$6) -> 0 | G37: =SUMIFS('List of Ledgers '!$L:$L,'List of Ledgers '!$F:$F,'P&L'!$A37,'List of Ledgers '!$G:$G,'P&L'!G$6) -> 0 | H37: =SUMIFS('List of Ledgers '!$L:$L,'List of Ledgers '!$F:$F,'P&L'!$A37,'List of Ledgers '!$G:$G,'P&L'!H$6) -> 0 | I37: =SUMIFS('List of Ledgers '!$L:$L,'List of Ledgers '!$F:$F,'P&L'!$A37,'List of Ledgers '!$G:$G,'P&L'!I$6) -> 0 | J37: =SUM(B37:I37) -> 81813.94 | K37: =SUMIFS('List of Ledgers '!$L:$L,'List of Ledgers '!$F:$F,'P&L'!$A37,'List of Ledgers '!$G:$G,'P&L'!$K$6) -> 0 | L37: =J37+K37 -> 81813.94 | N37: =SUMIFS('List of Ledgers '!$Q:$Q,'List of Ledgers '!$F:$F,'P&L'!$A37,'List of Ledgers '!$G:$G,'P&L'!N$6) -> 0 | O37: =SUMIFS('List of Ledgers '!$Q:$Q,'List of Ledgers '!$F:$F,'P&L'!$A37,'List of Ledgers '!$G:$G,'P&L'!O$6) -> 0 | P37: =SUMIFS('List of Ledgers '!$Q:$Q,'List of Ledgers '!$F:$F,'P&L'!$A37,'List of Ledgers '!$G:$G,'P&L'!P$6) -> 299599.94 | Q37: =SUMIFS('List of Ledgers '!$Q:$Q,'List of Ledgers '!$F:$F,'P&L'!$A37,'List of Ledgers '!$G:$G,'P&L'!Q$6) -> 0 | R37: =SUMIFS('List of Ledgers '!$Q:$Q,'List of Ledgers '!$F:$F,'P&L'!$A37,'List of Ledgers '!$G:$G,'P&L'!R$6) -> 0 | S37: =SUMIFS('List of Ledgers '!$Q:$Q,'List of Ledgers '!$F:$F,'P&L'!$A37,'List of Ledgers '!$G:$G,'P&L'!S$6) -> 0 | V37: =SUM(N37:U37) -> 299599.94 | W37: =SUMIFS('List of Ledgers '!$Q:$Q,'List of Ledgers '!$F:$F,'P&L'!$A37,'List of Ledgers '!$G:$G,'P&L'!W$6) -> 0 | X37: =V37+W37 -> 299599.94 | Y37: =V37-X37 -> 0
A38: Advertisement | B38: =SUMIFS('List of Ledgers '!$L:$L,'List of Ledgers '!$F:$F,'P&L'!$A38,'List of Ledgers '!$G:$G,'P&L'!B$6) -> 0 | C38: =SUMIFS('List of Ledgers '!$L:$L,'List of Ledgers '!$F:$F,'P&L'!$A38,'List of Ledgers '!$G:$G,'P&L'!C$6) -> 0 | D38: =SUMIFS('List of Ledgers '!$L:$L,'List of Ledgers '!$F:$F,'P&L'!$A38,'List of Ledgers '!$G:$G,'P&L'!D$6) -> 0 | E38: =SUMIFS('List of Ledgers '!$L:$L,'List of Ledgers '!$F:$F,'P&L'!$A38,'List of Ledgers '!$G:$G,'P&L'!E$6) -> 0 | F38: =SUMIFS('List of Ledgers '!$L:$L,'List of Ledgers '!$F:$F,'P&L'!$A38,'List of Ledgers '!$G:$G,'P&L'!F$6) -> 0 | G38: =SUMIFS('List of Ledgers '!$L:$L,'List of Ledgers '!$F:$F,'P&L'!$A38,'List of Ledgers '!$G:$G,'P&L'!G$6) -> 0 | H38: =SUMIFS('List of Ledgers '!$L:$L,'List of Ledgers '!$F:$F,'P&L'!$A38,'List of Ledgers '!$G:$G,'P&L'!H$6) -> 0 | I38: =SUMIFS('List of Ledgers '!$L:$L,'List of Ledgers '!$F:$F,'P&L'!$A38,'List of Ledgers '!$G:$G,'P&L'!I$6) -> 0 | J38: =SUM(B38:I38) -> 0 | K38: =SUMIFS('List of Ledgers '!$L:$L,'List of Ledgers '!$F:$F,'P&L'!$A38,'List of Ledgers '!$G:$G,'P&L'!$K$6) -> 0 | L38: =J38+K38 -> 0 | N38: =SUMIFS('List of Ledgers '!$Q:$Q,'List of Ledgers '!$F:$F,'P&L'!$A38,'List of Ledgers '!$G:$G,'P&L'!N$6) -> 0 | O38: =SUMIFS('List of Ledgers '!$Q:$Q,'List of Ledgers '!$F:$F,'P&L'!$A38,'List of Ledgers '!$G:$G,'P&L'!O$6) -> 0 | P38: =SUMIFS('List of Ledgers '!$Q:$Q,'List of Ledgers '!$F:$F,'P&L'!$A38,'List of Ledgers '!$G:$G,'P&L'!P$6) -> 0 | Q38: =SUMIFS('List of Ledgers '!$Q:$Q,'List of Ledgers '!$F:$F,'P&L'!$A38,'List of Ledgers '!$G:$G,'P&L'!Q$6) -> 0 | R38: =SUMIFS('List of Ledgers '!$Q:$Q,'List of Ledgers '!$F:$F,'P&L'!$A38,'List of Ledgers '!$G:$G,'P&L'!R$6) -> 0 | S38: =SUMIFS('List of Ledgers '!$Q:$Q,'List of Ledgers '!$F:$F,'P&L'!$A38,'List of Ledgers '!$G:$G,'P&L'!S$6) -> 0 | T38: =SUMIFS('List of Ledgers '!$Q:$Q,'List of Ledgers '!$F:$F,'P&L'!$A38,'List of Ledgers '!$G:$G,'P&L'!T$6) -> 0 | U38: =SUMIFS('List of Ledgers '!$Q:$Q,'List of Ledgers '!$F:$F,'P&L'!$A38,'List of Ledgers '!$G:$G,'P&L'!U$6) -> 0 | V38: =SUM(N38:U38) -> 0 | W38: =SUMIFS('List of Ledgers '!$Q:$Q,'List of Ledgers '!$F:$F,'P&L'!$A38,'List of Ledgers '!$G:$G,'P&L'!W$6) -> 0 | X38: =V38+W38 -> 0 | Y38: =V38-X38 -> 0
A39: Bad debt | B39: =SUMIFS('List of Ledgers '!$L:$L,'List of Ledgers '!$F:$F,'P&L'!$A39,'List of Ledgers '!$G:$G,'P&L'!B$6) -> 0 | C39: =SUMIFS('List of Ledgers '!$L:$L,'List of Ledgers '!$F:$F,'P&L'!$A39,'List of Ledgers '!$G:$G,'P&L'!C$6) -> 0 | D39: =SUMIFS('List of Ledgers '!$L:$L,'List of Ledgers '!$F:$F,'P&L'!$A39,'List of Ledgers '!$G:$G,'P&L'!D$6) -> 0 | E39: =SUMIFS('List of Ledgers '!$L:$L,'List of Ledgers '!$F:$F,'P&L'!$A39,'List of Ledgers '!$G:$G,'P&L'!E$6) -> 0 | F39: =SUMIFS('List of Ledgers '!$L:$L,'List of Ledgers '!$F:$F,'P&L'!$A39,'List of Ledgers '!$G:$G,'P&L'!F$6) -> 0 | G39: =SUMIFS('List of Ledgers '!$L:$L,'List of Ledgers '!$F:$F,'P&L'!$A39,'List of Ledgers '!$G:$G,'P&L'!G$6) -> 0 | H39: =SUMIFS('List of Ledgers '!$L:$L,'List of Ledgers '!$F:$F,'P&L'!$A39,'List of Ledgers '!$G:$G,'P&L'!H$6) -> 0 | I39: =SUMIFS('List of Ledgers '!$L:$L,'List of Ledgers '!$F:$F,'P&L'!$A39,'List of Ledgers '!$G:$G,'P&L'!I$6) -> 0 | J39: =SUM(B39:I39) -> 0 | K39: =SUMIFS('List of Ledgers '!$L:$L,'List of Ledgers '!$F:$F,'P&L'!$A39,'List of Ledgers '!$G:$G,'P&L'!$K$6) -> 0 | L39: =J39+K39 -> 0 | N39: =SUMIFS('List of Ledgers '!$Q:$Q,'List of Ledgers '!$F:$F,'P&L'!$A39,'List of Ledgers '!$G:$G,'P&L'!N$6) -> 0 | O39: =SUMIFS('List of Ledgers '!$Q:$Q,'List of Ledgers '!$F:$F,'P&L'!$A39,'List of Ledgers '!$G:$G,'P&L'!O$6) -> 0 | P39: =SUMIFS('List of Ledgers '!$Q:$Q,'List of Ledgers '!$F:$F,'P&L'!$A39,'List of Ledgers '!$G:$G,'P&L'!P$6) -> 0 | Q39: =SUMIFS('List of Ledgers '!$Q:$Q,'List of Ledgers '!$F:$F,'P&L'!$A39,'List of Ledgers '!$G:$G,'P&L'!Q$6) -> 0 | R39: =SUMIFS('List of Ledgers '!$Q:$Q,'List of Ledgers '!$F:$F,'P&L'!$A39,'List of Ledgers '!$G:$G,'P&L'!R$6) -> 0 | S39: =SUMIFS('List of Ledgers '!$Q:$Q,'List of Ledgers '!$F:$F,'P&L'!$A39,'List of Ledgers '!$G:$G,'P&L'!S$6) -> 0 | T39: =SUMIFS('List of Ledgers '!$Q:$Q,'List of Ledgers '!$F:$F,'P&L'!$A39,'List of Ledgers '!$G:$G,'P&L'!T$6) -> 0 | U39: =SUMIFS('List of Ledgers '!$Q:$Q,'List of Ledgers '!$F:$F,'P&L'!$A39,'List of Ledgers '!$G:$G,'P&L'!U$6) -> 0 | V39: =SUM(N39:U39) -> 0 | W39: =SUMIFS('List of Ledgers '!$Q:$Q,'List of Ledgers '!$F:$F,'P&L'!$A39,'List of Ledgers '!$G:$G,'P&L'!W$6) -> 0 | X39: =V39+W39 -> 0 | Y39: =V39-X39 -> 0
A40: Marketing Expense | B40: ='Marketing Expenses'!B12 -> 0 | C40: ='Marketing Expenses'!C12 -> 0 | D40: ='Marketing Expenses'!D12 -> 30000 | E40: ='Marketing Expenses'!E12 -> 0 | F40: ='Marketing Expenses'!F12 -> 0 | G40: ='Marketing Expenses'!G12 -> 0 | H40: ='Marketing Expenses'!H12 -> 4000 | I40: ='Marketing Expenses'!I12 -> 0 | J40: =SUM(B40:I40) -> 34000 | K40: =SUMIFS('List of Ledgers '!$L:$L,'List of Ledgers '!$F:$F,'P&L'!$A40,'List of Ledgers '!$G:$G,'P&L'!$K$6) -> 0 | L40: =J40+K40 -> 34000 | N40: ='Marketing Expenses'!N12 -> 0 | O40: ='Marketing Expenses'!O12 -> 0 | P40: ='Marketing Expenses'!P12 -> 194200.82 | Q40: ='Marketing Expenses'!Q12 -> 0 | R40: ='Marketing Expenses'!R12 -> 0 | S40: ='Marketing Expenses'!S12 -> 11572 | T40: ='Marketing Expenses'!T12 -> 691055 | U40: ='Marketing Expenses'!U12 -> 552704 | V40: =SUM(N40:U40) -> 1449531.8 | W40: ='Marketing Expenses'!W12 -> 0 | X40: =V40+W40 -> 1449531.8 | Y40: =V40-X40 -> 0
A41: Bank charges | B41: =SUMIFS('List of Ledgers '!$L:$L,'List of Ledgers '!$F:$F,'P&L'!$A41,'List of Ledgers '!$G:$G,'P&L'!B$6) -> 0 | C41: =SUMIFS('List of Ledgers '!$L:$L,'List of Ledgers '!$F:$F,'P&L'!$A41,'List of Ledgers '!$G:$G,'P&L'!C$6) -> 0 | D41: =SUMIFS('List of Ledgers '!$L:$L,'List of Ledgers '!$F:$F,'P&L'!$A41,'List of Ledgers '!$G:$G,'P&L'!D$6) -> 600 | E41: =SUMIFS('List of Ledgers '!$L:$L,'List of Ledgers '!$F:$F,'P&L'!$A41,'List of Ledgers '!$G:$G,'P&L'!E$6) -> 0 | F41: =SUMIFS('List of Ledgers '!$L:$L,'List of Ledgers '!$F:$F,'P&L'!$A41,'List of Ledgers '!$G:$G,'P&L'!F$6) -> 0 | G41: =SUMIFS('List of Ledgers '!$L:$L,'List of Ledgers '!$F:$F,'P&L'!$A41,'List of Ledgers '!$G:$G,'P&L'!G$6) -> 624.32 | H41: =SUMIFS('List of Ledgers '!$L:$L,'List of Ledgers '!$F:$F,'P&L'!$A41,'List of Ledgers '!$G:$G,'P&L'!H$6) -> 0 | I41: =SUMIFS('List of Ledgers '!$L:$L,'List of Ledgers '!$F:$F,'P&L'!$A41,'List of Ledgers '!$G:$G,'P&L'!I$6) -> 1817.7 | J41: =SUM(B41:I41) -> 3042.02 | K41: =SUMIFS('List of Ledgers '!$L:$L,'List of Ledgers '!$F:$F,'P&L'!$A41,'List of Ledgers '!$G:$G,'P&L'!$K$6) -> 0 | L41: =J41+K41 -> 3042.02 | N41: =SUMIFS('List of Ledgers '!$Q:$Q,'List of Ledgers '!$F:$F,'P&L'!$A41,'List of Ledgers '!$G:$G,'P&L'!N$6) -> 0 | O41: =SUMIFS('List of Ledgers '!$Q:$Q,'List of Ledgers '!$F:$F,'P&L'!$A41,'List of Ledgers '!$G:$G,'P&L'!O$6) -> 0 | P41: =SUMIFS('List of Ledgers '!$Q:$Q,'List of Ledgers '!$F:$F,'P&L'!$A41,'List of Ledgers '!$G:$G,'P&L'!P$6) -> 2650 | Q41: =SUMIFS('List of Ledgers '!$Q:$Q,'List of Ledgers '!$F:$F,'P&L'!$A41,'List of Ledgers '!$G:$G,'P&L'!Q$6) -> 0 | R41: =SUMIFS('List of Ledgers '!$Q:$Q,'List of Ledgers '!$F:$F,'P&L'!$A41,'List of Ledgers '!$G:$G,'P&L'!R$6) -> 0 | S41: =SUMIFS('List of Ledgers '!$Q:$Q,'List of Ledgers '!$F:$F,'P&L'!$A41,'List of Ledgers '!$G:$G,'P&L'!S$6) -> 7258.68 | T41: =SUMIFS('List of Ledgers '!$Q:$Q,'List of Ledgers '!$F:$F,'P&L'!$A41,'List of Ledgers '!$G:$G,'P&L'!T$6) -> 0 | U41: =SUMIFS('List of Ledgers '!$Q:$Q,'List of Ledgers '!$F:$F,'P&L'!$A41,'List of Ledgers '!$G:$G,'P&L'!U$6) -> 4385.4 | V41: =SUM(N41:U41) -> 14294.08 | W41: =SUMIFS('List of Ledgers '!$Q:$Q,'List of Ledgers '!$F:$F,'P&L'!$A41,'List of Ledgers '!$G:$G,'P&L'!W$6) -> 0 | X41: =V41+W41 -> 14294.08 | Y41: =V41-X41 -> 0
A42: Brokerage and commission | B42: =SUMIFS('List of Ledgers '!$L:$L,'List of Ledgers '!$F:$F,'P&L'!$A42,'List of Ledgers '!$G:$G,'P&L'!B$6) -> 0 | C42: =SUMIFS('List of Ledgers '!$L:$L,'List of Ledgers '!$F:$F,'P&L'!$A42,'List of Ledgers '!$G:$G,'P&L'!C$6) -> 0 | D42: =SUMIFS('List of Ledgers '!$L:$L,'List of Ledgers '!$F:$F,'P&L'!$A42,'List of Ledgers '!$G:$G,'P&L'!D$6) -> 0 | E42: =SUMIFS('List of Ledgers '!$L:$L,'List of Ledgers '!$F:$F,'P&L'!$A42,'List of Ledgers '!$G:$G,'P&L'!E$6) -> 0 | F42: =SUMIFS('List of Ledgers '!$L:$L,'List of Ledgers '!$F:$F,'P&L'!$A42,'List of Ledgers '!$G:$G,'P&L'!F$6) -> 0 | G42: =SUMIFS('List of Ledgers '!$L:$L,'List of Ledgers '!$F:$F,'P&L'!$A42,'List of Ledgers '!$G:$G,'P&L'!G$6) -> 0 | H42: =SUMIFS('List of Ledgers '!$L:$L,'List of Ledgers '!$F:$F,'P&L'!$A42,'List of Ledgers '!$G:$G,'P&L'!H$6) -> 0 | I42: =SUMIFS('List of Ledgers '!$L:$L,'List of Ledgers '!$F:$F,'P&L'!$A42,'List of Ledgers '!$G:$G,'P&L'!I$6) -> 0 | J42: =SUM(B42:I42) -> 0 | K42: =SUMIFS('List of Ledgers '!$L:$L,'List of Ledgers '!$F:$F,'P&L'!$A42,'List of Ledgers '!$G:$G,'P&L'!$K$6) -> 0 | L42: =J42+K42 -> 0 | N42: =SUMIFS('List of Ledgers '!$Q:$Q,'List of Ledgers '!$F:$F,'P&L'!$A42,'List of Ledgers '!$G:$G,'P&L'!N$6) -> 0 | O42: =SUMIFS('List of Ledgers '!$Q:$Q,'List of Ledgers '!$F:$F,'P&L'!$A42,'List of Ledgers '!$G:$G,'P&L'!O$6) -> 0 | P42: =SUMIFS('List of Ledgers '!$Q:$Q,'List of Ledgers '!$F:$F,'P&L'!$A42,'List of Ledgers '!$G:$G,'P&L'!P$6) -> 0 | Q42: =SUMIFS('List of Ledgers '!$Q:$Q,'List of Ledgers '!$F:$F,'P&L'!$A42,'List of Ledgers '!$G:$G,'P&L'!Q$6) -> 0 | R42: =SUMIFS('List of Ledgers '!$Q:$Q,'List of Ledgers '!$F:$F,'P&L'!$A42,'List of Ledgers '!$G:$G,'P&L'!R$6) -> 0 | S42: =SUMIFS('List of Ledgers '!$Q:$Q,'List of Ledgers '!$F:$F,'P&L'!$A42,'List of Ledgers '!$G:$G,'P&L'!S$6) -> 0 | T42: =SUMIFS('List of Ledgers '!$Q:$Q,'List of Ledgers '!$F:$F,'P&L'!$A42,'List of Ledgers '!$G:$G,'P&L'!T$6) -> 0 | U42: =SUMIFS('List of Ledgers '!$Q:$Q,'List of Ledgers '!$F:$F,'P&L'!$A42,'List of Ledgers '!$G:$G,'P&L'!U$6) -> 24600 | V42: =SUM(N42:U42) -> 24600 | W42: =SUMIFS('List of Ledgers '!$Q:$Q,'List of Ledgers '!$F:$F,'P&L'!$A42,'List of Ledgers '!$G:$G,'P&L'!W$6) -> 0 | X42: =V42+W42 -> 24600 | Y42: =V42-X42 -> 0
A43: Conveyance expenses | B43: =SUMIFS('List of Ledgers '!$L:$L,'List of Ledgers '!$F:$F,'P&L'!$A43,'List of Ledgers '!$G:$G,'P&L'!B$6) -> 0 | C43: =SUMIFS('List of Ledgers '!$L:$L,'List of Ledgers '!$F:$F,'P&L'!$A43,'List of Ledgers '!$G:$G,'P&L'!C$6) -> 0 | D43: =SUMIFS('List of Ledgers '!$L:$L,'List of Ledgers '!$F:$F,'P&L'!$A43,'List of Ledgers '!$G:$G,'P&L'!D$6) -> 0 | E43: =SUMIFS('List of Ledgers '!$L:$L,'List of Ledgers '!$F:$F,'P&L'!$A43,'List of Ledgers '!$G:$G,'P&L'!E$6) -> 0 | F43: =SUMIFS('List of Ledgers '!$L:$L,'List of Ledgers '!$F:$F,'P&L'!$A43,'List of Ledgers '!$G:$G,'P&L'!F$6) -> 0 | G43: =SUMIFS('List of Ledgers '!$L:$L,'List of Ledgers '!$F:$F,'P&L'!$A43,'List of Ledgers '!$G:$G,'P&L'!G$6) -> 1324 | H43: =SUMIFS('List of Ledgers '!$L:$L,'List of Ledgers '!$F:$F,'P&L'!$A43,'List of Ledgers '!$G:$G,'P&L'!H$6) -> 0 | I43: =SUMIFS('List of Ledgers '!$L:$L,'List of Ledgers '!$F:$F,'P&L'!$A43,'List of Ledgers '!$G:$G,'P&L'!I$6) -> 7582.09 | J43: =SUM(B43:I43) -> 8906.09 | K43: =SUMIFS('List of Ledgers '!$L:$L,'List of Ledgers '!$F:$F,'P&L'!$A43,'List of Ledgers '!$G:$G,'P&L'!$K$6) -> 0 | L43: =J43+K43 -> 8906.09 | N43: =SUMIFS('List of Ledgers '!$Q:$Q,'List of Ledgers '!$F:$F,'P&L'!$A43,'List of Ledgers '!$G:$G,'P&L'!N$6) -> 0 | O43: =SUMIFS('List of Ledgers '!$Q:$Q,'List of Ledgers '!$F:$F,'P&L'!$A43,'List of Ledgers '!$G:$G,'P&L'!O$6) -> 0 | P43: =SUMIFS('List of Ledgers '!$Q:$Q,'List of Ledgers '!$F:$F,'P&L'!$A43,'List of Ledgers '!$G:$G,'P&L'!P$6) -> 0 | Q43: =SUMIFS('List of Ledgers '!$Q:$Q,'List of Ledgers '!$F:$F,'P&L'!$A43,'List of Ledgers '!$G:$G,'P&L'!Q$6) -> 0 | R43: =SUMIFS('List of Ledgers '!$Q:$Q,'List of Ledgers '!$F:$F,'P&L'!$A43,'List of Ledgers '!$G:$G,'P&L'!R$6) -> 0 | S43: =SUMIFS('List of Ledgers '!$Q:$Q,'List of Ledgers '!$F:$F,'P&L'!$A43,'List of Ledgers '!$G:$G,'P&L'!S$6) -> 297018 | T43: =SUMIFS('List of Ledgers '!$Q:$Q,'List of Ledgers '!$F:$F,'P&L'!$A43,'List of Ledgers '!$G:$G,'P&L'!T$6) -> 0 | U43: =SUMIFS('List of Ledgers '!$Q:$Q,'List of Ledgers '!$F:$F,'P&L'!$A43,'List of Ledgers '!$G:$G,'P&L'!U$6) -> 44500.64 | V43: =SUM(N43:U43) -> 341518.64 | W43: =SUMIFS('List of Ledgers '!$Q:$Q,'List of Ledgers '!$F:$F,'P&L'!$A43,'List of Ledgers '!$G:$G,'P&L'!W$6) -> 0 | X43: =V43+W43 -> 341518.64 | Y43: =V43-X43 -> 0
A44: Courier charges | B44: =SUMIFS('List of Ledgers '!$L:$L,'List of Ledgers '!$F:$F,'P&L'!$A44,'List of Ledgers '!$G:$G,'P&L'!B$6) -> 0 | C44: =SUMIFS('List of Ledgers '!$L:$L,'List of Ledgers '!$F:$F,'P&L'!$A44,'List of Ledgers '!$G:$G,'P&L'!C$6) -> 0 | D44: =SUMIFS('List of Ledgers '!$L:$L,'List of Ledgers '!$F:$F,'P&L'!$A44,'List of Ledgers '!$G:$G,'P&L'!D$6) -> 0 | E44: =SUMIFS('List of Ledgers '!$L:$L,'List of Ledgers '!$F:$F,'P&L'!$A44,'List of Ledgers '!$G:$G,'P&L'!E$6) -> 0 | F44: =SUMIFS('List of Ledgers '!$L:$L,'List of Ledgers '!$F:$F,'P&L'!$A44,'List of Ledgers '!$G:$G,'P&L'!F$6) -> 0 | G44: =SUMIFS('List of Ledgers '!$L:$L,'List of Ledgers '!$F:$F,'P&L'!$A44,'List of Ledgers '!$G:$G,'P&L'!G$6) -> 35265.56 | H44: =SUMIFS('List of Ledgers '!$L:$L,'List of Ledgers '!$F:$F,'P&L'!$A44,'List of Ledgers '!$G:$G,'P&L'!H$6) -> 0 | I44: =SUMIFS('List of Ledgers '!$L:$L,'List of Ledgers '!$F:$F,'P&L'!$A44,'List of Ledgers '!$G:$G,'P&L'!I$6) -> 350 | J44: =SUM(B44:I44) -> 35615.56 | K44: =SUMIFS('List of Ledgers '!$L:$L,'List of Ledgers '!$F:$F,'P&L'!$A44,'List of Ledgers '!$G:$G,'P&L'!$K$6) -> 0 | L44: =J44+K44 -> 35615.56 | N44: =SUMIFS('List of Ledgers '!$Q:$Q,'List of Ledgers '!$F:$F,'P&L'!$A44,'List of Ledgers '!$G:$G,'P&L'!N$6) -> 0 | O44: =SUMIFS('List of Ledgers '!$Q:$Q,'List of Ledgers '!$F:$F,'P&L'!$A44,'List of Ledgers '!$G:$G,'P&L'!O$6) -> 0 | P44: =SUMIFS('List of Ledgers '!$Q:$Q,'List of Ledgers '!$F:$F,'P&L'!$A44,'List of Ledgers '!$G:$G,'P&L'!P$6) -> 0 | Q44: =SUMIFS('List of Ledgers '!$Q:$Q,'List of Ledgers '!$F:$F,'P&L'!$A44,'List of Ledgers '!$G:$G,'P&L'!Q$6) -> 0 | R44: =SUMIFS('List of Ledgers '!$Q:$Q,'List of Ledgers '!$F:$F,'P&L'!$A44,'List of Ledgers '!$G:$G,'P&L'!R$6) -> 0 | S44: =SUMIFS('List of Ledgers '!$Q:$Q,'List of Ledgers '!$F:$F,'P&L'!$A44,'List of Ledgers '!$G:$G,'P&L'!S$6) -> 162454.82 | T44: =SUMIFS('List of Ledgers '!$Q:$Q,'List of Ledgers '!$F:$F,'P&L'!$A44,'List of Ledgers '!$G:$G,'P&L'!T$6) -> 0 | U44: =SUMIFS('List of Ledgers '!$Q:$Q,'List of Ledgers '!$F:$F,'P&L'!$A44,'List of Ledgers '!$G:$G,'P&L'!U$6) -> 700 | V44: =SUM(N44:U44) -> 163154.82 | W44: =SUMIFS('List of Ledgers '!$Q:$Q,'List of Ledgers '!$F:$F,'P&L'!$A44,'List of Ledgers '!$G:$G,'P&L'!W$6) -> 0 | X44: =V44+W44 -> 163154.82 | Y44: =V44-X44 -> 0
A45: Donation | B45: =SUMIFS('List of Ledgers '!$L:$L,'List of Ledgers '!$F:$F,'P&L'!$A45,'List of Ledgers '!$G:$G,'P&L'!B$6) -> 0 | C45: =SUMIFS('List of Ledgers '!$L:$L,'List of Ledgers '!$F:$F,'P&L'!$A45,'List of Ledgers '!$G:$G,'P&L'!C$6) -> 0 | D45: =SUMIFS('List of Ledgers '!$L:$L,'List of Ledgers '!$F:$F,'P&L'!$A45,'List of Ledgers '!$G:$G,'P&L'!D$6) -> 0 | E45: =SUMIFS('List of Ledgers '!$L:$L,'List of Ledgers '!$F:$F,'P&L'!$A45,'List of Ledgers '!$G:$G,'P&L'!E$6) -> 0 | F45: =SUMIFS('List of Ledgers '!$L:$L,'List of Ledgers '!$F:$F,'P&L'!$A45,'List of Ledgers '!$G:$G,'P&L'!F$6) -> 0 | G45: =SUMIFS('List of Ledgers '!$L:$L,'List of Ledgers '!$F:$F,'P&L'!$A45,'List of Ledgers '!$G:$G,'P&L'!G$6) -> 400 | H45: =SUMIFS('List of Ledgers '!$L:$L,'List of Ledgers '!$F:$F,'P&L'!$A45,'List of Ledgers '!$G:$G,'P&L'!H$6) -> 0 | I45: =SUMIFS('List of Ledgers '!$L:$L,'List of Ledgers '!$F:$F,'P&L'!$A45,'List of Ledgers '!$G:$G,'P&L'!I$6) -> 0 | J45: =SUM(B45:I45) -> 400 | K45: =SUMIFS('List of Ledgers '!$L:$L,'List of Ledgers '!$F:$F,'P&L'!$A45,'List of Ledgers '!$G:$G,'P&L'!$K$6) -> 0 | L45: =J45+K45 -> 400 | N45: =SUMIFS('List of Ledgers '!$Q:$Q,'List of Ledgers '!$F:$F,'P&L'!$A45,'List of Ledgers '!$G:$G,'P&L'!N$6) -> 0 | O45: =SUMIFS('List of Ledgers '!$Q:$Q,'List of Ledgers '!$F:$F,'P&L'!$A45,'List of Ledgers '!$G:$G,'P&L'!O$6) -> 0 | P45: =SUMIFS('List of Ledgers '!$Q:$Q,'List of Ledgers '!$F:$F,'P&L'!$A45,'List of Ledgers '!$G:$G,'P&L'!P$6) -> 0 | Q45: =SUMIFS('List of Ledgers '!$Q:$Q,'List of Ledgers '!$F:$F,'P&L'!$A45,'List of Ledgers '!$G:$G,'P&L'!Q$6) -> 0 | R45: =SUMIFS('List of Ledgers '!$Q:$Q,'List of Ledgers '!$F:$F,'P&L'!$A45,'List of Ledgers '!$G:$G,'P&L'!R$6) -> 0 | S45: =SUMIFS('List of Ledgers '!$Q:$Q,'List of Ledgers '!$F:$F,'P&L'!$A45,'List of Ledgers '!$G:$G,'P&L'!S$6) -> 700 | T45: =SUMIFS('List of Ledgers '!$Q:$Q,'List of Ledgers '!$F:$F,'P&L'!$A45,'List of Ledgers '!$G:$G,'P&L'!T$6) -> 0 | U45: =SUMIFS('List of Ledgers '!$Q:$Q,'List of Ledgers '!$F:$F,'P&L'!$A45,'List of Ledgers '!$G:$G,'P&L'!U$6) -> 0 | V45: =SUM(N45:U45) -> 700 | W45: =SUMIFS('List of Ledgers '!$Q:$Q,'List of Ledgers '!$F:$F,'P&L'!$A45,'List of Ledgers '!$G:$G,'P&L'!W$6) -> 0 | X45: =V45+W45 -> 700 | Y45: =V45-X45 -> 0
A46: Domain Expenses | B46: =SUMIFS('List of Ledgers '!$L:$L,'List of Ledgers '!$F:$F,'P&L'!$A46,'List of Ledgers '!$G:$G,'P&L'!B$6) -> 0 | C46: =SUMIFS('List of Ledgers '!$L:$L,'List of Ledgers '!$F:$F,'P&L'!$A46,'List of Ledgers '!$G:$G,'P&L'!C$6) -> 0 | D46: =SUMIFS('List of Ledgers '!$L:$L,'List of Ledgers '!$F:$F,'P&L'!$A46,'List of Ledgers '!$G:$G,'P&L'!D$6) -> 0 | E46: =SUMIFS('List of Ledgers '!$L:$L,'List of Ledgers '!$F:$F,'P&L'!$A46,'List of Ledgers '!$G:$G,'P&L'!E$6) -> 0 | F46: =SUMIFS('List of Ledgers '!$L:$L,'List of Ledgers '!$F:$F,'P&L'!$A46,'List of Ledgers '!$G:$G,'P&L'!F$6) -> 0 | G46: =SUMIFS('List of Ledgers '!$L:$L,'List of Ledgers '!$F:$F,'P&L'!$A46,'List of Ledgers '!$G:$G,'P&L'!G$6) -> 0 | H46: =SUMIFS('List of Ledgers '!$L:$L,'List of Ledgers '!$F:$F,'P&L'!$A46,'List of Ledgers '!$G:$G,'P&L'!H$6) -> 0 | I46: =SUMIFS('List of Ledgers '!$L:$L,'List of Ledgers '!$F:$F,'P&L'!$A46,'List of Ledgers '!$G:$G,'P&L'!I$6) -> 0 | J46: =SUM(B46:I46) -> 0 | K46: =SUMIFS('List of Ledgers '!$L:$L,'List of Ledgers '!$F:$F,'P&L'!$A46,'List of Ledgers '!$G:$G,'P&L'!$K$6) -> 0 | L46: =J46+K46 -> 0 | N46: =SUMIFS('List of Ledgers '!$Q:$Q,'List of Ledgers '!$F:$F,'P&L'!$A46,'List of Ledgers '!$G:$G,'P&L'!N$6) -> 0 | O46: =SUMIFS('List of Ledgers '!$Q:$Q,'List of Ledgers '!$F:$F,'P&L'!$A46,'List of Ledgers '!$G:$G,'P&L'!O$6) -> 0 | P46: =SUMIFS('List of Ledgers '!$Q:$Q,'List of Ledgers '!$F:$F,'P&L'!$A46,'List of Ledgers '!$G:$G,'P&L'!P$6) -> 0 | Q46: =SUMIFS('List of Ledgers '!$Q:$Q,'List of Ledgers '!$F:$F,'P&L'!$A46,'List of Ledgers '!$G:$G,'P&L'!Q$6) -> 0 | R46: =SUMIFS('List of Ledgers '!$Q:$Q,'List of Ledgers '!$F:$F,'P&L'!$A46,'List of Ledgers '!$G:$G,'P&L'!R$6) -> 0 | S46: =SUMIFS('List of Ledgers '!$Q:$Q,'List of Ledgers '!$F:$F,'P&L'!$A46,'List of Ledgers '!$G:$G,'P&L'!S$6) -> 0 | T46: =SUMIFS('List of Ledgers '!$Q:$Q,'List of Ledgers '!$F:$F,'P&L'!$A46,'List of Ledgers '!$G:$G,'P&L'!T$6) -> 0 | U46: =SUMIFS('List of Ledgers '!$Q:$Q,'List of Ledgers '!$F:$F,'P&L'!$A46,'List of Ledgers '!$G:$G,'P&L'!U$6) -> 0 | V46: =SUM(N46:U46) -> 0 | W46: =SUMIFS('List of Ledgers '!$Q:$Q,'List of Ledgers '!$F:$F,'P&L'!$A46,'List of Ledgers '!$G:$G,'P&L'!W$6) -> 0 | X46: =V46+W46 -> 0 | Y46: =V46-X46 -> 0
A47: Depreciation | B47: =SUMIFS('List of Ledgers '!$L:$L,'List of Ledgers '!$F:$F,'P&L'!$A47,'List of Ledgers '!$G:$G,'P&L'!B$6) -> 0 | C47: =SUMIFS('List of Ledgers '!$L:$L,'List of Ledgers '!$F:$F,'P&L'!$A47,'List of Ledgers '!$G:$G,'P&L'!C$6) -> 0 | D47: =SUMIFS('List of Ledgers '!$L:$L,'List of Ledgers '!$F:$F,'P&L'!$A47,'List of Ledgers '!$G:$G,'P&L'!D$6) -> 0 | E47: =SUMIFS('List of Ledgers '!$L:$L,'List of Ledgers '!$F:$F,'P&L'!$A47,'List of Ledgers '!$G:$G,'P&L'!E$6) -> 0 | F47: =SUMIFS('List of Ledgers '!$L:$L,'List of Ledgers '!$F:$F,'P&L'!$A47,'List of Ledgers '!$G:$G,'P&L'!F$6) -> 0 | G47: =SUMIFS('List of Ledgers '!$L:$L,'List of Ledgers '!$F:$F,'P&L'!$A47,'List of Ledgers '!$G:$G,'P&L'!G$6) -> 0 | H47: =SUMIFS('List of Ledgers '!$L:$L,'List of Ledgers '!$F:$F,'P&L'!$A47,'List of Ledgers '!$G:$G,'P&L'!H$6) -> 0 | I47: =SUMIFS('List of Ledgers '!$L:$L,'List of Ledgers '!$F:$F,'P&L'!$A47,'List of Ledgers '!$G:$G,'P&L'!I$6) -> 0 | J47: =SUM(B47:I47) -> 0 | K47: =SUMIFS('List of Ledgers '!$L:$L,'List of Ledgers '!$F:$F,'P&L'!$A47,'List of Ledgers '!$G:$G,'P&L'!$K$6) -> 0 | L47: =J47+K47 -> 0 | N47: =SUMIFS('List of Ledgers '!$Q:$Q,'List of Ledgers '!$F:$F,'P&L'!$A47,'List of Ledgers '!$G:$G,'P&L'!N$6) -> 0 | O47: =SUMIFS('List of Ledgers '!$Q:$Q,'List of Ledgers '!$F:$F,'P&L'!$A47,'List of Ledgers '!$G:$G,'P&L'!O$6) -> 0 | P47: =SUMIFS('List of Ledgers '!$Q:$Q,'List of Ledgers '!$F:$F,'P&L'!$A47,'List of Ledgers '!$G:$G,'P&L'!P$6) -> 0 | Q47: =SUMIFS('List of Ledgers '!$Q:$Q,'List of Ledgers '!$F:$F,'P&L'!$A47,'List of Ledgers '!$G:$G,'P&L'!Q$6) -> 0 | R47: =SUMIFS('List of Ledgers '!$Q:$Q,'List of Ledgers '!$F:$F,'P&L'!$A47,'List of Ledgers '!$G:$G,'P&L'!R$6) -> 0 | S47: =SUMIFS('List of Ledgers '!$Q:$Q,'List of Ledgers '!$F:$F,'P&L'!$A47,'List of Ledgers '!$G:$G,'P&L'!S$6) -> 0 | T47: =SUMIFS('List of Ledgers '!$Q:$Q,'List of Ledgers '!$F:$F,'P&L'!$A47,'List of Ledgers '!$G:$G,'P&L'!T$6) -> 0 | U47: =SUMIFS('List of Ledgers '!$Q:$Q,'List of Ledgers '!$F:$F,'P&L'!$A47,'List of Ledgers '!$G:$G,'P&L'!U$6) -> 0 | V47: =SUM(N47:U47) -> 0 | W47: =SUMIFS('List of Ledgers '!$Q:$Q,'List of Ledgers '!$F:$F,'P&L'!$A47,'List of Ledgers '!$G:$G,'P&L'!W$6) -> 0 | X47: =V47+W47 -> 0 | Y47: =V47-X47 -> 0
A48: Electricity charges | B48: =SUMIFS('List of Ledgers '!$L:$L,'List of Ledgers '!$F:$F,'P&L'!$A48,'List of Ledgers '!$G:$G,'P&L'!B$6) -> 0 | C48: =SUMIFS('List of Ledgers '!$L:$L,'List of Ledgers '!$F:$F,'P&L'!$A48,'List of Ledgers '!$G:$G,'P&L'!C$6) -> 0 | D48: =SUMIFS('List of Ledgers '!$L:$L,'List of Ledgers '!$F:$F,'P&L'!$A48,'List of Ledgers '!$G:$G,'P&L'!D$6) -> 0 | E48: =SUMIFS('List of Ledgers '!$L:$L,'List of Ledgers '!$F:$F,'P&L'!$A48,'List of Ledgers '!$G:$G,'P&L'!E$6) -> 0 | F48: =SUMIFS('List of Ledgers '!$L:$L,'List of Ledgers '!$F:$F,'P&L'!$A48,'List of Ledgers '!$G:$G,'P&L'!F$6) -> 0 | G48: =SUMIFS('List of Ledgers '!$L:$L,'List of Ledgers '!$F:$F,'P&L'!$A48,'List of Ledgers '!$G:$G,'P&L'!G$6) -> 8470 | H48: =SUMIFS('List of Ledgers '!$L:$L,'List of Ledgers '!$F:$F,'P&L'!$A48,'List of Ledgers '!$G:$G,'P&L'!H$6) -> 0 | I48: =SUMIFS('List of Ledgers '!$L:$L,'List of Ledgers '!$F:$F,'P&L'!$A48,'List of Ledgers '!$G:$G,'P&L'!I$6) -> 1160 | J48: =SUM(B48:I48) -> 9630 | K48: =SUMIFS('List of Ledgers '!$L:$L,'List of Ledgers '!$F:$F,'P&L'!$A48,'List of Ledgers '!$G:$G,'P&L'!$K$6) -> 0 | L48: =J48+K48 -> 9630 | N48: =SUMIFS('List of Ledgers '!$Q:$Q,'List of Ledgers '!$F:$F,'P&L'!$A48,'List of Ledgers '!$G:$G,'P&L'!N$6) -> 1590 | O48: =SUMIFS('List of Ledgers '!$Q:$Q,'List of Ledgers '!$F:$F,'P&L'!$A48,'List of Ledgers '!$G:$G,'P&L'!O$6) -> 0 | P48: =SUMIFS('List of Ledgers '!$Q:$Q,'List of Ledgers '!$F:$F,'P&L'!$A48,'List of Ledgers '!$G:$G,'P&L'!P$6) -> 0 | Q48: =SUMIFS('List of Ledgers '!$Q:$Q,'List of Ledgers '!$F:$F,'P&L'!$A48,'List of Ledgers '!$G:$G,'P&L'!Q$6) -> 0 | R48: =SUMIFS('List of Ledgers '!$Q:$Q,'List of Ledgers '!$F:$F,'P&L'!$A48,'List of Ledgers '!$G:$G,'P&L'!R$6) -> 0 | S48: =SUMIFS('List of Ledgers '!$Q:$Q,'List of Ledgers '!$F:$F,'P&L'!$A48,'List of Ledgers '!$G:$G,'P&L'!S$6) -> 136950 | T48: =SUMIFS('List of Ledgers '!$Q:$Q,'List of Ledgers '!$F:$F,'P&L'!$A48,'List of Ledgers '!$G:$G,'P&L'!T$6) -> 0 | U48: =SUMIFS('List of Ledgers '!$Q:$Q,'List of Ledgers '!$F:$F,'P&L'!$A48,'List of Ledgers '!$G:$G,'P&L'!U$6) -> 2210 | V48: =SUM(N48:U48) -> 140750 | W48: =SUMIFS('List of Ledgers '!$Q:$Q,'List of Ledgers '!$F:$F,'P&L'!$A48,'List of Ledgers '!$G:$G,'P&L'!W$6) -> 0 | X48: =V48+W48 -> 140750 | Y48: =V48-X48 -> 0
A49: Fuel Expenses | B49: =SUMIFS('List of Ledgers '!$L:$L,'List of Ledgers '!$F:$F,'P&L'!$A49,'List of Ledgers '!$G:$G,'P&L'!B$6) -> 0 | C49: =SUMIFS('List of Ledgers '!$L:$L,'List of Ledgers '!$F:$F,'P&L'!$A49,'List of Ledgers '!$G:$G,'P&L'!C$6) -> 0 | D49: =SUMIFS('List of Ledgers '!$L:$L,'List of Ledgers '!$F:$F,'P&L'!$A49,'List of Ledgers '!$G:$G,'P&L'!D$6) -> 0 | E49: =SUMIFS('List of Ledgers '!$L:$L,'List of Ledgers '!$F:$F,'P&L'!$A49,'List of Ledgers '!$G:$G,'P&L'!E$6) -> 0 | F49: =SUMIFS('List of Ledgers '!$L:$L,'List of Ledgers '!$F:$F,'P&L'!$A49,'List of Ledgers '!$G:$G,'P&L'!F$6) -> 0 | G49: =SUMIFS('List of Ledgers '!$L:$L,'List of Ledgers '!$F:$F,'P&L'!$A49,'List of Ledgers '!$G:$G,'P&L'!G$6) -> 5000 | H49: =SUMIFS('List of Ledgers '!$L:$L,'List of Ledgers '!$F:$F,'P&L'!$A49,'List of Ledgers '!$G:$G,'P&L'!H$6) -> 0 | I49: =SUMIFS('List of Ledgers '!$L:$L,'List of Ledgers '!$F:$F,'P&L'!$A49,'List of Ledgers '!$G:$G,'P&L'!I$6) -> 0 | J49: =SUM(B49:I49) -> 5000 | K49: =SUMIFS('List of Ledgers '!$L:$L,'List of Ledgers '!$F:$F,'P&L'!$A49,'List of Ledgers '!$G:$G,'P&L'!$K$6) -> 0 | L49: =J49+K49 -> 5000 | N49: =SUMIFS('List of Ledgers '!$Q:$Q,'List of Ledgers '!$F:$F,'P&L'!$A49,'List of Ledgers '!$G:$G,'P&L'!N$6) -> 0 | O49: =SUMIFS('List of Ledgers '!$Q:$Q,'List of Ledgers '!$F:$F,'P&L'!$A49,'List of Ledgers '!$G:$G,'P&L'!O$6) -> 0 | P49: =SUMIFS('List of Ledgers '!$Q:$Q,'List of Ledgers '!$F:$F,'P&L'!$A49,'List of Ledgers '!$G:$G,'P&L'!P$6) -> 0 | Q49: =SUMIFS('List of Ledgers '!$Q:$Q,'List of Ledgers '!$F:$F,'P&L'!$A49,'List of Ledgers '!$G:$G,'P&L'!Q$6) -> 0 | R49: =SUMIFS('List of Ledgers '!$Q:$Q,'List of Ledgers '!$F:$F,'P&L'!$A49,'List of Ledgers '!$G:$G,'P&L'!R$6) -> 0 | S49: =SUMIFS('List of Ledgers '!$Q:$Q,'List of Ledgers '!$F:$F,'P&L'!$A49,'List of Ledgers '!$G:$G,'P&L'!S$6) -> 35542 | T49: =SUMIFS('List of Ledgers '!$Q:$Q,'List of Ledgers '!$F:$F,'P&L'!$A49,'List of Ledgers '!$G:$G,'P&L'!T$6) -> 0 | U49: =SUMIFS('List of Ledgers '!$Q:$Q,'List of Ledgers '!$F:$F,'P&L'!$A49,'List of Ledgers '!$G:$G,'P&L'!U$6) -> 0 | V49: =SUM(N49:U49) -> 35542 | W49: =SUMIFS('List of Ledgers '!$Q:$Q,'List of Ledgers '!$F:$F,'P&L'!$A49,'List of Ledgers '!$G:$G,'P&L'!W$6) -> 0 | X49: =V49+W49 -> 35542 | Y49: =V49-X49 -> 0
A50: Insurance | B50: =SUMIFS('List of Ledgers '!$L:$L,'List of Ledgers '!$F:$F,'P&L'!$A50,'List of Ledgers '!$G:$G,'P&L'!B$6) -> 0 | C50: =SUMIFS('List of Ledgers '!$L:$L,'List of Ledgers '!$F:$F,'P&L'!$A50,'List of Ledgers '!$G:$G,'P&L'!C$6) -> 0 | D50: =SUMIFS('List of Ledgers '!$L:$L,'List of Ledgers '!$F:$F,'P&L'!$A50,'List of Ledgers '!$G:$G,'P&L'!D$6) -> 7012 | E50: =SUMIFS('List of Ledgers '!$L:$L,'List of Ledgers '!$F:$F,'P&L'!$A50,'List of Ledgers '!$G:$G,'P&L'!E$6) -> 0 | F50: =SUMIFS('List of Ledgers '!$L:$L,'List of Ledgers '!$F:$F,'P&L'!$A50,'List of Ledgers '!$G:$G,'P&L'!F$6) -> 0 | G50: =SUMIFS('List of Ledgers '!$L:$L,'List of Ledgers '!$F:$F,'P&L'!$A50,'List of Ledgers '!$G:$G,'P&L'!G$6) -> 0 | H50: =SUMIFS('List of Ledgers '!$L:$L,'List of Ledgers '!$F:$F,'P&L'!$A50,'List of Ledgers '!$G:$G,'P&L'!H$6) -> 0 | I50: =SUMIFS('List of Ledgers '!$L:$L,'List of Ledgers '!$F:$F,'P&L'!$A50,'List of Ledgers '!$G:$G,'P&L'!I$6) -> 0 | J50: =SUM(B50:I50) -> 7012 | K50: =SUMIFS('List of Ledgers '!$L:$L,'List of Ledgers '!$F:$F,'P&L'!$A50,'List of Ledgers '!$G:$G,'P&L'!$K$6) -> 0 | L50: =J50+K50 -> 7012 | N50: =SUMIFS('List of Ledgers '!$Q:$Q,'List of Ledgers '!$F:$F,'P&L'!$A50,'List of Ledgers '!$G:$G,'P&L'!N$6) -> 0 | O50: =SUMIFS('List of Ledgers '!$Q:$Q,'List of Ledgers '!$F:$F,'P&L'!$A50,'List of Ledgers '!$G:$G,'P&L'!O$6) -> 0 | P50: =SUMIFS('List of Ledgers '!$Q:$Q,'List of Ledgers '!$F:$F,$A$50,'List of Ledgers '!$G:$G,P6,'List of Ledgers '!E:E,A35) -> 191038 | Q50: =SUMIFS('List of Ledgers '!$Q:$Q,'List of Ledgers '!$F:$F,'P&L'!$A50,'List of Ledgers '!$G:$G,'P&L'!Q$6) -> 0 | R50: =SUMIFS('List of Ledgers '!$Q:$Q,'List of Ledgers '!$F:$F,'P&L'!$A50,'List of Ledgers '!$G:$G,'P&L'!R$6) -> 0 | S50: =SUMIFS('List of Ledgers '!$Q:$Q,'List of Ledgers '!$F:$F,$A$50,'List of Ledgers '!$G:$G,S6,'List of Ledgers '!E:E,A35) -> 207364.84 | T50: =SUMIFS('List of Ledgers '!$Q:$Q,'List of Ledgers '!$F:$F,'P&L'!$A50,'List of Ledgers '!$G:$G,'P&L'!T$6) -> 0 | U50: =SUMIFS('List of Ledgers '!$Q:$Q,'List of Ledgers '!$F:$F,'P&L'!$A50,'List of Ledgers '!$G:$G,'P&L'!U$6) -> 0 | V50: =SUM(N50:U50) -> 398402.84 | W50: =SUMIFS('List of Ledgers '!$Q:$Q,'List of Ledgers '!$F:$F,'P&L'!$A50,'List of Ledgers '!$G:$G,'P&L'!W$6) -> 0 | X50: =V50+W50 -> 398402.84 | Y50: =V50-X50 -> 0
A51: Interest expense | B51: =SUMIFS('List of Ledgers '!$L:$L,'List of Ledgers '!$F:$F,'P&L'!$A51,'List of Ledgers '!$G:$G,'P&L'!B$6) -> 0 | C51: =SUMIFS('List of Ledgers '!$L:$L,'List of Ledgers '!$F:$F,'P&L'!$A51,'List of Ledgers '!$G:$G,'P&L'!C$6) -> 0 | D51: =SUMIFS('List of Ledgers '!$L:$L,'List of Ledgers '!$F:$F,'P&L'!$A51,'List of Ledgers '!$G:$G,'P&L'!D$6) -> 0 | E51: =SUMIFS('List of Ledgers '!$L:$L,'List of Ledgers '!$F:$F,'P&L'!$A51,'List of Ledgers '!$G:$G,'P&L'!E$6) -> 0 | F51: =SUMIFS('List of Ledgers '!$L:$L,'List of Ledgers '!$F:$F,'P&L'!$A51,'List of Ledgers '!$G:$G,'P&L'!F$6) -> 0 | G51: =SUMIFS('List of Ledgers '!$L:$L,'List of Ledgers '!$F:$F,'P&L'!$A51,'List of Ledgers '!$G:$G,'P&L'!G$6) -> 2632602 | H51: =SUMIFS('List of Ledgers '!$L:$L,'List of Ledgers '!$F:$F,'P&L'!$A51,'List of Ledgers '!$G:$G,'P&L'!H$6) -> 0 | I51: =SUMIFS('List of Ledgers '!$L:$L,'List of Ledgers '!$F:$F,'P&L'!$A51,'List of Ledgers '!$G:$G,'P&L'!I$6) -> 0 | J51: =SUM(B51:I51) -> 2632602 | K51: =SUMIFS('List of Ledgers '!$L:$L,'List of Ledgers '!$F:$F,'P&L'!$A51,'List of Ledgers '!$G:$G,'P&L'!$K$6) -> 0 | L51: =J51+K51 -> 2632602 | N51: =SUMIFS('List of Ledgers '!$Q:$Q,'List of Ledgers '!$F:$F,'P&L'!$A51,'List of Ledgers '!$G:$G,'P&L'!N$6) -> 0 | O51: =SUMIFS('List of Ledgers '!$Q:$Q,'List of Ledgers '!$F:$F,'P&L'!$A51,'List of Ledgers '!$G:$G,'P&L'!O$6) -> 0 | P51: =SUMIFS('List of Ledgers '!$Q:$Q,'List of Ledgers '!$F:$F,'P&L'!$A51,'List of Ledgers '!$G:$G,'P&L'!P$6) -> 0 | Q51: =SUMIFS('List of Ledgers '!$Q:$Q,'List of Ledgers '!$F:$F,'P&L'!$A51,'List of Ledgers '!$G:$G,'P&L'!Q$6) -> 0 | R51: =SUMIFS('List of Ledgers '!$Q:$Q,'List of Ledgers '!$F:$F,'P&L'!$A51,'List of Ledgers '!$G:$G,'P&L'!R$6) -> 0 | S51: =SUMIFS('List of Ledgers '!$Q:$Q,'List of Ledgers '!$F:$F,'P&L'!$A51,'List of Ledgers '!$G:$G,'P&L'!S$6) -> 2632602 | T51: =SUMIFS('List of Ledgers '!$Q:$Q,'List of Ledgers '!$F:$F,'P&L'!$A51,'List of Ledgers '!$G:$G,'P&L'!T$6) -> 0 | U51: =SUMIFS('List of Ledgers '!$Q:$Q,'List of Ledgers '!$F:$F,'P&L'!$A51,'List of Ledgers '!$G:$G,'P&L'!U$6) -> 0 | V51: =SUM(N51:U51) -> 2632602 | W51: =SUMIFS('List of Ledgers '!$Q:$Q,'List of Ledgers '!$F:$F,'P&L'!$A51,'List of Ledgers '!$G:$G,'P&L'!W$6) -> 0 | X51: =V51+W51 -> 2632602 | Y51: =V51-X51 -> 0
A52: Labour charges | B52: =SUMIFS('List of Ledgers '!$L:$L,'List of Ledgers '!$F:$F,'P&L'!$A52,'List of Ledgers '!$G:$G,'P&L'!B$6) -> 0 | C52: =SUMIFS('List of Ledgers '!$L:$L,'List of Ledgers '!$F:$F,'P&L'!$A52,'List of Ledgers '!$G:$G,'P&L'!C$6) -> 0 | D52: =SUMIFS('List of Ledgers '!$L:$L,'List of Ledgers '!$F:$F,'P&L'!$A52,'List of Ledgers '!$G:$G,'P&L'!D$6) -> 0 | E52: =SUMIFS('List of Ledgers '!$L:$L,'List of Ledgers '!$F:$F,'P&L'!$A52,'List of Ledgers '!$G:$G,'P&L'!E$6) -> 0 | F52: =SUMIFS('List of Ledgers '!$L:$L,'List of Ledgers '!$F:$F,'P&L'!$A52,'List of Ledgers '!$G:$G,'P&L'!F$6) -> 0 | G52: =SUMIFS('List of Ledgers '!$L:$L,'List of Ledgers '!$F:$F,'P&L'!$A52,'List of Ledgers '!$G:$G,'P&L'!G$6) -> 0 | H52: =SUMIFS('List of Ledgers '!$L:$L,'List of Ledgers '!$F:$F,'P&L'!$A52,'List of Ledgers '!$G:$G,'P&L'!H$6) -> 0 | I52: =SUMIFS('List of Ledgers '!$L:$L,'List of Ledgers '!$F:$F,'P&L'!$A52,'List of Ledgers '!$G:$G,'P&L'!I$6) -> 260000 | J52: =SUM(B52:I52) -> 260000 | K52: =SUMIFS('List of Ledgers '!$L:$L,'List of Ledgers '!$F:$F,'P&L'!$A52,'List of Ledgers '!$G:$G,'P&L'!$K$6) -> 0 | L52: =J52+K52 -> 260000 | N52: =SUMIFS('List of Ledgers '!$Q:$Q,'List of Ledgers '!$F:$F,'P&L'!$A52,'List of Ledgers '!$G:$G,'P&L'!N$6) -> 13260 | O52: =SUMIFS('List of Ledgers '!$Q:$Q,'List of Ledgers '!$F:$F,'P&L'!$A52,'List of Ledgers '!$G:$G,'P&L'!O$6) -> 0 | P52: =SUMIFS('List of Ledgers '!$Q:$Q,'List of Ledgers '!$F:$F,'P&L'!$A52,'List of Ledgers '!$G:$G,'P&L'!P$6) -> 0 | Q52: =SUMIFS('List of Ledgers '!$Q:$Q,'List of Ledgers '!$F:$F,'P&L'!$A52,'List of Ledgers '!$G:$G,'P&L'!Q$6) -> 0 | R52: =SUMIFS('List of Ledgers '!$Q:$Q,'List of Ledgers '!$F:$F,'P&L'!$A52,'List of Ledgers '!$G:$G,'P&L'!R$6) -> 0 | S52: =SUMIFS('List of Ledgers '!$Q:$Q,'List of Ledgers '!$F:$F,'P&L'!$A52,'List of Ledgers '!$G:$G,'P&L'!S$6) -> 0 | T52: =SUMIFS('List of Ledgers '!$Q:$Q,'List of Ledgers '!$F:$F,'P&L'!$A52,'List of Ledgers '!$G:$G,'P&L'!T$6) -> 0 | U52: =SUMIFS('List of Ledgers '!$Q:$Q,'List of Ledgers '!$F:$F,'P&L'!$A52,'List of Ledgers '!$G:$G,'P&L'!U$6) -> 260500 | V52: =SUM(N52:U52) -> 273760 | W52: =SUMIFS('List of Ledgers '!$Q:$Q,'List of Ledgers '!$F:$F,'P&L'!$A52,'List of Ledgers '!$G:$G,'P&L'!W$6) -> 0 | X52: =V52+W52 -> 273760 | Y52: =V52-X52 -> 0
A53: Misc Expenses | B53: =SUMIFS('List of Ledgers '!$L:$L,'List of Ledgers '!$F:$F,'P&L'!$A53,'List of Ledgers '!$G:$G,'P&L'!B$6) -> 0 | C53: =SUMIFS('List of Ledgers '!$L:$L,'List of Ledgers '!$F:$F,'P&L'!$A53,'List of Ledgers '!$G:$G,'P&L'!C$6) -> 0 | D53: =SUMIFS('List of Ledgers '!$L:$L,'List of Ledgers '!$F:$F,'P&L'!$A53,'List of Ledgers '!$G:$G,'P&L'!D$6) -> 0 | E53: =SUMIFS('List of Ledgers '!$L:$L,'List of Ledgers '!$F:$F,'P&L'!$A53,'List of Ledgers '!$G:$G,'P&L'!E$6) -> 0 | F53: =SUMIFS('List of Ledgers '!$L:$L,'List of Ledgers '!$F:$F,'P&L'!$A53,'List of Ledgers '!$G:$G,'P&L'!F$6) -> 0 | G53: =SUMIFS('List of Ledgers '!$L:$L,'List of Ledgers '!$F:$F,'P&L'!$A53,'List of Ledgers '!$G:$G,'P&L'!G$6) -> 4440.55 | H53: =SUMIFS('List of Ledgers '!$L:$L,'List of Ledgers '!$F:$F,'P&L'!$A53,'List of Ledgers '!$G:$G,'P&L'!H$6) -> 10000 | I53: =SUMIFS('List of Ledgers '!$L:$L,'List of Ledgers '!$F:$F,'P&L'!$A53,'List of Ledgers '!$G:$G,'P&L'!I$6) -> 9300 | J53: =SUM(B53:I53) -> 23740.55 | K53: =SUMIFS('List of Ledgers '!$L:$L,'List of Ledgers '!$F:$F,'P&L'!$A53,'List of Ledgers '!$G:$G,'P&L'!$K$6) -> 0 | L53: =J53+K53 -> 23740.55 | N53: =SUMIFS('List of Ledgers '!$Q:$Q,'List of Ledgers '!$F:$F,'P&L'!$A53,'List of Ledgers '!$G:$G,'P&L'!N$6) -> 0 | O53: =SUMIFS('List of Ledgers '!$Q:$Q,'List of Ledgers '!$F:$F,'P&L'!$A53,'List of Ledgers '!$G:$G,'P&L'!O$6) -> 0 | P53: =SUMIFS('List of Ledgers '!$Q:$Q,'List of Ledgers '!$F:$F,'P&L'!$A53,'List of Ledgers '!$G:$G,'P&L'!P$6) -> 93223 | Q53: =SUMIFS('List of Ledgers '!$Q:$Q,'List of Ledgers '!$F:$F,'P&L'!$A53,'List of Ledgers '!$G:$G,'P&L'!Q$6) -> 0 | R53: =SUMIFS('List of Ledgers '!$Q:$Q,'List of Ledgers '!$F:$F,'P&L'!$A53,'List of Ledgers '!$G:$G,'P&L'!R$6) -> 0 | S53: =SUMIFS('List of Ledgers '!$Q:$Q,'List of Ledgers '!$F:$F,'P&L'!$A53,'List of Ledgers '!$G:$G,'P&L'!S$6) -> 187300.19 | T53: =SUMIFS('List of Ledgers '!$Q:$Q,'List of Ledgers '!$F:$F,'P&L'!$A53,'List of Ledgers '!$G:$G,'P&L'!T$6) -> 38100 | U53: =SUMIFS('List of Ledgers '!$Q:$Q,'List of Ledgers '!$F:$F,'P&L'!$A53,'List of Ledgers '!$G:$G,'P&L'!U$6) -> 39429 | V53: =SUM(N53:U53) -> 358052.19 | W53: =SUMIFS('List of Ledgers '!$Q:$Q,'List of Ledgers '!$F:$F,'P&L'!$A53,'List of Ledgers '!$G:$G,'P&L'!W$6) -> 0 | X53: =V53+W53 -> 358052.19 | Y53: =V53-X53 -> 0
A54: Membership Expenses | B54: =SUMIFS('List of Ledgers '!$L:$L,'List of Ledgers '!$F:$F,'P&L'!$A54,'List of Ledgers '!$G:$G,'P&L'!B$6) -> 0 | C54: =SUMIFS('List of Ledgers '!$L:$L,'List of Ledgers '!$F:$F,'P&L'!$A54,'List of Ledgers '!$G:$G,'P&L'!C$6) -> 0 | D54: =SUMIFS('List of Ledgers '!$L:$L,'List of Ledgers '!$F:$F,'P&L'!$A54,'List of Ledgers '!$G:$G,'P&L'!D$6) -> 0 | E54: =SUMIFS('List of Ledgers '!$L:$L,'List of Ledgers '!$F:$F,'P&L'!$A54,'List of Ledgers '!$G:$G,'P&L'!E$6) -> 0 | F54: =SUMIFS('List of Ledgers '!$L:$L,'List of Ledgers '!$F:$F,'P&L'!$A54,'List of Ledgers '!$G:$G,'P&L'!F$6) -> 0 | G54: =SUMIFS('List of Ledgers '!$L:$L,'List of Ledgers '!$F:$F,'P&L'!$A54,'List of Ledgers '!$G:$G,'P&L'!G$6) -> 0 | H54: =SUMIFS('List of Ledgers '!$L:$L,'List of Ledgers '!$F:$F,'P&L'!$A54,'List of Ledgers '!$G:$G,'P&L'!H$6) -> 9810 | I54: =SUMIFS('List of Ledgers '!$L:$L,'List of Ledgers '!$F:$F,'P&L'!$A54,'List of Ledgers '!$G:$G,'P&L'!I$6) -> 0 | J54: =SUM(B54:I54) -> 9810 | K54: =SUMIFS('List of Ledgers '!$L:$L,'List of Ledgers '!$F:$F,'P&L'!$A54,'List of Ledgers '!$G:$G,'P&L'!$K$6) -> 0 | L54: =J54+K54 -> 9810 | T54: =SUMIFS('List of Ledgers '!$Q:$Q,'List of Ledgers '!$F:$F,'P&L'!$A54,'List of Ledgers '!$G:$G,'P&L'!T$6) -> 2043284.5 | U54: =SUMIFS('List of Ledgers '!$Q:$Q,'List of Ledgers '!$F:$F,'P&L'!$A54,'List of Ledgers '!$G:$G,'P&L'!U$6) -> 0 | V54: =SUM(N54:U54) -> 2043284.5 | X54: =V54+W54 -> 2043284.5 | Y54: =V54-X54 -> 0
A55: Printing & Stationery | B55: =SUMIFS('List of Ledgers '!$L:$L,'List of Ledgers '!$F:$F,'P&L'!$A55,'List of Ledgers '!$G:$G,'P&L'!B$6) -> 0 | C55: =SUMIFS('List of Ledgers '!$L:$L,'List of Ledgers '!$F:$F,'P&L'!$A55,'List of Ledgers '!$G:$G,'P&L'!C$6) -> 0 | D55: =SUMIFS('List of Ledgers '!$L:$L,'List of Ledgers '!$F:$F,'P&L'!$A55,'List of Ledgers '!$G:$G,'P&L'!D$6) -> 0 | E55: =SUMIFS('List of Ledgers '!$L:$L,'List of Ledgers '!$F:$F,'P&L'!$A55,'List of Ledgers '!$G:$G,'P&L'!E$6) -> 0 | F55: =SUMIFS('List of Ledgers '!$L:$L,'List of Ledgers '!$F:$F,'P&L'!$A55,'List of Ledgers '!$G:$G,'P&L'!F$6) -> 0 | G55: =SUMIFS('List of Ledgers '!$L:$L,'List of Ledgers '!$F:$F,'P&L'!$A55,'List of Ledgers '!$G:$G,'P&L'!G$6) -> 13225 | H55: =SUMIFS('List of Ledgers '!$L:$L,'List of Ledgers '!$F:$F,'P&L'!$A55,'List of Ledgers '!$G:$G,'P&L'!H$6) -> 0 | I55: =SUMIFS('List of Ledgers '!$L:$L,'List of Ledgers '!$F:$F,'P&L'!$A55,'List of Ledgers '!$G:$G,'P&L'!I$6) -> 25257 | J55: =SUM(B55:I55) -> 38482 | K55: =SUMIFS('List of Ledgers '!$L:$L,'List of Ledgers '!$F:$F,'P&L'!$A55,'List of Ledgers '!$G:$G,'P&L'!$K$6) -> 0 | L55: =J55+K55 -> 38482 | N55: =SUMIFS('List of Ledgers '!$Q:$Q,'List of Ledgers '!$F:$F,'P&L'!$A55,'List of Ledgers '!$G:$G,'P&L'!N$6) -> 0 | O55: =SUMIFS('List of Ledgers '!$Q:$Q,'List of Ledgers '!$F:$F,'P&L'!$A55,'List of Ledgers '!$G:$G,'P&L'!O$6) -> 0 | P55: =SUMIFS('List of Ledgers '!$Q:$Q,'List of Ledgers '!$F:$F,'P&L'!$A55,'List of Ledgers '!$G:$G,'P&L'!P$6) -> 0 | Q55: =SUMIFS('List of Ledgers '!$Q:$Q,'List of Ledgers '!$F:$F,'P&L'!$A55,'List of Ledgers '!$G:$G,'P&L'!Q$6) -> 0 | R55: =SUMIFS('List of Ledgers '!$Q:$Q,'List of Ledgers '!$F:$F,'P&L'!$A55,'List of Ledgers '!$G:$G,'P&L'!R$6) -> 0 | S55: =SUMIFS('List of Ledgers '!$Q:$Q,'List of Ledgers '!$F:$F,'P&L'!$A55,'List of Ledgers '!$G:$G,'P&L'!S$6) -> 117469 | T55: =SUMIFS('List of Ledgers '!$Q:$Q,'List of Ledgers '!$F:$F,'P&L'!$A55,'List of Ledgers '!$G:$G,'P&L'!T$6) -> 0 | U55: =SUMIFS('List of Ledgers '!$Q:$Q,'List of Ledgers '!$F:$F,'P&L'!$A55,'List of Ledgers '!$G:$G,'P&L'!U$6) -> 39472 | V55: =SUM(N55:U55) -> 156941 | W55: =SUMIFS('List of Ledgers '!$Q:$Q,'List of Ledgers '!$F:$F,'P&L'!$A55,'List of Ledgers '!$G:$G,'P&L'!W$6) -> 0 | X55: =V55+W55 -> 156941 | Y55: =V55-X55 -> 0
A56: Professional charges | B56: =SUMIFS('List of Ledgers '!$L:$L,'List of Ledgers '!$F:$F,'P&L'!$A56,'List of Ledgers '!$G:$G,'P&L'!B$6) -> 0 | C56: =SUMIFS('List of Ledgers '!$L:$L,'List of Ledgers '!$F:$F,'P&L'!$A56,'List of Ledgers '!$G:$G,'P&L'!C$6) -> 0 | D56: =SUMIFS('List of Ledgers '!$L:$L,'List of Ledgers '!$F:$F,'P&L'!$A56,'List of Ledgers '!$G:$G,'P&L'!D$6) -> 0 | E56: =SUMIFS('List of Ledgers '!$L:$L,'List of Ledgers '!$F:$F,'P&L'!$A56,'List of Ledgers '!$G:$G,'P&L'!E$6) -> 0 | F56: =SUMIFS('List of Ledgers '!$L:$L,'List of Ledgers '!$F:$F,'P&L'!$A56,'List of Ledgers '!$G:$G,'P&L'!F$6) -> 0 | G56: =SUMIFS('List of Ledgers '!$L:$L,'List of Ledgers '!$F:$F,'P&L'!$A56,'List of Ledgers '!$G:$G,'P&L'!G$6) -> 22000 | H56: =SUMIFS('List of Ledgers '!$L:$L,'List of Ledgers '!$F:$F,'P&L'!$A56,'List of Ledgers '!$G:$G,'P&L'!H$6) -> 0 | I56: =SUMIFS('List of Ledgers '!$L:$L,'List of Ledgers '!$F:$F,'P&L'!$A56,'List of Ledgers '!$G:$G,'P&L'!I$6) -> 0 | J56: =SUM(B56:I56) -> 22000 | K56: =SUMIFS('List of Ledgers '!$L:$L,'List of Ledgers '!$F:$F,'P&L'!$A56,'List of Ledgers '!$G:$G,'P&L'!$K$6) -> 0 | L56: =J56+K56 -> 22000 | N56: =SUMIFS('List of Ledgers '!$Q:$Q,'List of Ledgers '!$F:$F,'P&L'!$A56,'List of Ledgers '!$G:$G,'P&L'!N$6) -> 0 | O56: =SUMIFS('List of Ledgers '!$Q:$Q,'List of Ledgers '!$F:$F,'P&L'!$A56,'List of Ledgers '!$G:$G,'P&L'!O$6) -> 0 | P56: =SUMIFS('List of Ledgers '!$Q:$Q,'List of Ledgers '!$F:$F,'P&L'!$A56,'List of Ledgers '!$G:$G,'P&L'!P$6) -> 0 | Q56: =SUMIFS('List of Ledgers '!$Q:$Q,'List of Ledgers '!$F:$F,'P&L'!$A56,'List of Ledgers '!$G:$G,'P&L'!Q$6) -> 0 | R56: =SUMIFS('List of Ledgers '!$Q:$Q,'List of Ledgers '!$F:$F,'P&L'!$A56,'List of Ledgers '!$G:$G,'P&L'!R$6) -> 0 | S56: =SUMIFS('List of Ledgers '!$Q:$Q,'List of Ledgers '!$F:$F,'P&L'!$A56,'List of Ledgers '!$G:$G,'P&L'!S$6) -> 257723 | T56: =SUMIFS('List of Ledgers '!$Q:$Q,'List of Ledgers '!$F:$F,'P&L'!$A56,'List of Ledgers '!$G:$G,'P&L'!T$6) -> 48365 | U56: =SUMIFS('List of Ledgers '!$Q:$Q,'List of Ledgers '!$F:$F,'P&L'!$A56,'List of Ledgers '!$G:$G,'P&L'!U$6) -> 0 | V56: =SUM(N56:U56) -> 306088 | W56: =SUMIFS('List of Ledgers '!$Q:$Q,'List of Ledgers '!$F:$F,'P&L'!$A56,'List of Ledgers '!$G:$G,'P&L'!W$6) -> 0 | X56: =V56+W56 -> 306088 | Y56: =V56-X56 -> 0
A57: Rates & Taxes | B57: =SUMIFS('List of Ledgers '!$L:$L,'List of Ledgers '!$F:$F,'P&L'!$A57,'List of Ledgers '!$G:$G,'P&L'!B$6) -> 0 | C57: =SUMIFS('List of Ledgers '!$L:$L,'List of Ledgers '!$F:$F,'P&L'!$A57,'List of Ledgers '!$G:$G,'P&L'!C$6) -> 0 | D57: =SUMIFS('List of Ledgers '!$L:$L,'List of Ledgers '!$F:$F,'P&L'!$A57,'List of Ledgers '!$G:$G,'P&L'!D$6) -> 0 | E57: =SUMIFS('List of Ledgers '!$L:$L,'List of Ledgers '!$F:$F,'P&L'!$A57,'List of Ledgers '!$G:$G,'P&L'!E$6) -> 0 | F57: =SUMIFS('List of Ledgers '!$L:$L,'List of Ledgers '!$F:$F,'P&L'!$A57,'List of Ledgers '!$G:$G,'P&L'!F$6) -> 0 | G57: =SUMIFS('List of Ledgers '!$L:$L,'List of Ledgers '!$F:$F,'P&L'!$A57,'List of Ledgers '!$G:$G,'P&L'!G$6) -> 2925 | H57: =SUMIFS('List of Ledgers '!$L:$L,'List of Ledgers '!$F:$F,'P&L'!$A57,'List of Ledgers '!$G:$G,'P&L'!H$6) -> 0 | I57: =SUMIFS('List of Ledgers '!$L:$L,'List of Ledgers '!$F:$F,'P&L'!$A57,'List of Ledgers '!$G:$G,'P&L'!I$6) -> 0 | J57: =SUM(B57:I57) -> 2925 | K57: =SUMIFS('List of Ledgers '!$L:$L,'List of Ledgers '!$F:$F,'P&L'!$A57,'List of Ledgers '!$G:$G,'P&L'!$K$6) -> 0 | L57: =J57+K57 -> 2925 | N57: =SUMIFS('List of Ledgers '!$Q:$Q,'List of Ledgers '!$F:$F,'P&L'!$A57,'List of Ledgers '!$G:$G,'P&L'!N$6) -> 0 | O57: =SUMIFS('List of Ledgers '!$Q:$Q,'List of Ledgers '!$F:$F,'P&L'!$A57,'List of Ledgers '!$G:$G,'P&L'!O$6) -> 0 | P57: =SUMIFS('List of Ledgers '!$Q:$Q,'List of Ledgers '!$F:$F,'P&L'!$A57,'List of Ledgers '!$G:$G,'P&L'!P$6) -> 0 | Q57: =SUMIFS('List of Ledgers '!$Q:$Q,'List of Ledgers '!$F:$F,'P&L'!$A57,'List of Ledgers '!$G:$G,'P&L'!Q$6) -> 0 | R57: =SUMIFS('List of Ledgers '!$Q:$Q,'List of Ledgers '!$F:$F,'P&L'!$A57,'List of Ledgers '!$G:$G,'P&L'!R$6) -> 0 | S57: =SUMIFS('List of Ledgers '!$Q:$Q,'List of Ledgers '!$F:$F,'P&L'!$A57,'List of Ledgers '!$G:$G,'P&L'!S$6) -> 43751 | T57: =SUMIFS('List of Ledgers '!$Q:$Q,'List of Ledgers '!$F:$F,'P&L'!$A57,'List of Ledgers '!$G:$G,'P&L'!T$6) -> 0 | U57: =SUMIFS('List of Ledgers '!$Q:$Q,'List of Ledgers '!$F:$F,'P&L'!$A57,'List of Ledgers '!$G:$G,'P&L'!U$6) -> 0 | V57: =SUM(N57:U57) -> 43751 | W57: =SUMIFS('List of Ledgers '!$Q:$Q,'List of Ledgers '!$F:$F,'P&L'!$A57,'List of Ledgers '!$G:$G,'P&L'!W$6) -> 0 | X57: =V57+W57 -> 43751 | Y57: =V57-X57 -> 0
A58: Rent expenses | B58: =SUMIFS('List of Ledgers '!$L:$L,'List of Ledgers '!$F:$F,'P&L'!$A58,'List of Ledgers '!$G:$G,'P&L'!B$6) -> 0 | C58: =SUMIFS('List of Ledgers '!$L:$L,'List of Ledgers '!$F:$F,'P&L'!$A58,'List of Ledgers '!$G:$G,'P&L'!C$6) -> 0 | D58: =SUMIFS('List of Ledgers '!$L:$L,'List of Ledgers '!$F:$F,'P&L'!$A58,'List of Ledgers '!$G:$G,'P&L'!D$6) -> 0 | E58: =SUMIFS('List of Ledgers '!$L:$L,'List of Ledgers '!$F:$F,'P&L'!$A58,'List of Ledgers '!$G:$G,'P&L'!E$6) -> 0 | F58: =SUMIFS('List of Ledgers '!$L:$L,'List of Ledgers '!$F:$F,'P&L'!$A58,'List of Ledgers '!$G:$G,'P&L'!F$6) -> 0 | G58: =SUMIFS('List of Ledgers '!$L:$L,'List of Ledgers '!$F:$F,'P&L'!$A58,'List of Ledgers '!$G:$G,'P&L'!G$6) -> 225855 | H58: =SUMIFS('List of Ledgers '!$L:$L,'List of Ledgers '!$F:$F,'P&L'!$A58,'List of Ledgers '!$G:$G,'P&L'!H$6) -> 0 | I58: =SUMIFS('List of Ledgers '!$L:$L,'List of Ledgers '!$F:$F,'P&L'!$A58,'List of Ledgers '!$G:$G,'P&L'!I$6) -> 28000 | J58: =SUM(B58:I58) -> 253855 | K58: =SUMIFS('List of Ledgers '!$L:$L,'List of Ledgers '!$F:$F,'P&L'!$A58,'List of Ledgers '!$G:$G,'P&L'!$K$6) -> 0 | L58: =J58+K58 -> 253855 | N58: =SUMIFS('List of Ledgers '!$Q:$Q,'List of Ledgers '!$F:$F,'P&L'!$A58,'List of Ledgers '!$G:$G,'P&L'!N$6) -> 6000 | O58: =SUMIFS('List of Ledgers '!$Q:$Q,'List of Ledgers '!$F:$F,'P&L'!$A58,'List of Ledgers '!$G:$G,'P&L'!O$6) -> 0 | P58: =SUMIFS('List of Ledgers '!$Q:$Q,'List of Ledgers '!$F:$F,'P&L'!$A58,'List of Ledgers '!$G:$G,'P&L'!P$6) -> 0 | Q58: =SUMIFS('List of Ledgers '!$Q:$Q,'List of Ledgers '!$F:$F,'P&L'!$A58,'List of Ledgers '!$G:$G,'P&L'!Q$6) -> 0 | R58: =SUMIFS('List of Ledgers '!$Q:$Q,'List of Ledgers '!$F:$F,'P&L'!$A58,'List of Ledgers '!$G:$G,'P&L'!R$6) -> 0 | S58: =SUMIFS('List of Ledgers '!$Q:$Q,'List of Ledgers '!$F:$F,'P&L'!$A58,'List of Ledgers '!$G:$G,'P&L'!S$6) -> 2612720 | T58: =SUMIFS('List of Ledgers '!$Q:$Q,'List of Ledgers '!$F:$F,'P&L'!$A58,'List of Ledgers '!$G:$G,'P&L'!T$6) -> 0 | U58: =SUMIFS('List of Ledgers '!$Q:$Q,'List of Ledgers '!$F:$F,'P&L'!$A58,'List of Ledgers '!$G:$G,'P&L'!U$6) -> 112000 | V58: =SUM(N58:U58) -> 2730720 | W58: =SUMIFS('List of Ledgers '!$Q:$Q,'List of Ledgers '!$F:$F,'P&L'!$A58,'List of Ledgers '!$G:$G,'P&L'!W$6) -> 0 | X58: =V58+W58 -> 2730720 | Y58: =V58-X58 -> 0
A59: Repairs & maintenance expenses | B59: =SUMIFS('List of Ledgers '!$L:$L,'List of Ledgers '!$F:$F,'P&L'!$A59,'List of Ledgers '!$G:$G,'P&L'!B$6) -> 0 | C59: =SUMIFS('List of Ledgers '!$L:$L,'List of Ledgers '!$F:$F,'P&L'!$A59,'List of Ledgers '!$G:$G,'P&L'!C$6) -> 18401.57 | D59: =SUMIFS('List of Ledgers '!$L:$L,'List of Ledgers '!$F:$F,'P&L'!$A59,'List of Ledgers '!$G:$G,'P&L'!D$6) -> 0 | E59: =SUMIFS('List of Ledgers '!$L:$L,'List of Ledgers '!$F:$F,'P&L'!$A59,'List of Ledgers '!$G:$G,'P&L'!E$6) -> 0 | F59: =SUMIFS('List of Ledgers '!$L:$L,'List of Ledgers '!$F:$F,'P&L'!$A59,'List of Ledgers '!$G:$G,'P&L'!F$6) -> 0 | G59: =SUMIFS('List of Ledgers '!$L:$L,'List of Ledgers '!$F:$F,'P&L'!$A59,'List of Ledgers '!$G:$G,'P&L'!G$6) -> 0 | H59: =SUMIFS('List of Ledgers '!$L:$L,'List of Ledgers '!$F:$F,'P&L'!$A59,'List of Ledgers '!$G:$G,'P&L'!H$6) -> 0 | I59: =SUMIFS('List of Ledgers '!$L:$L,'List of Ledgers '!$F:$F,'P&L'!$A59,'List of Ledgers '!$G:$G,'P&L'!I$6) -> 500 | J59: =SUM(B59:I59) -> 18901.57 | K59: =SUMIFS('List of Ledgers '!$L:$L,'List of Ledgers '!$F:$F,'P&L'!$A59,'List of Ledgers '!$G:$G,'P&L'!$K$6) -> 0 | L59: =J59+K59 -> 18901.57 | N59: =SUMIFS('List of Ledgers '!$Q:$Q,'List of Ledgers '!$F:$F,'P&L'!$A59,'List of Ledgers '!$G:$G,'P&L'!N$6) -> 0 | O59: =SUMIFS('List of Ledgers '!$Q:$Q,'List of Ledgers '!$F:$F,'P&L'!$A59,'List of Ledgers '!$G:$G,'P&L'!O$6) -> 18401.57 | P59: =SUMIFS('List of Ledgers '!$Q:$Q,'List of Ledgers '!$F:$F,'P&L'!$A59,'List of Ledgers '!$G:$G,'P&L'!P$6) -> 0 | Q59: =SUMIFS('List of Ledgers '!$Q:$Q,'List of Ledgers '!$F:$F,'P&L'!$A59,'List of Ledgers '!$G:$G,'P&L'!Q$6) -> 0 | R59: =SUMIFS('List of Ledgers '!$Q:$Q,'List of Ledgers '!$F:$F,'P&L'!$A59,'List of Ledgers '!$G:$G,'P&L'!R$6) -> 0 | S59: =SUMIFS('List of Ledgers '!$Q:$Q,'List of Ledgers '!$F:$F,'P&L'!$A59,'List of Ledgers '!$G:$G,'P&L'!S$6) -> 193318 | T59: =SUMIFS('List of Ledgers '!$Q:$Q,'List of Ledgers '!$F:$F,'P&L'!$A59,'List of Ledgers '!$G:$G,'P&L'!T$6) -> 0 | U59: =SUMIFS('List of Ledgers '!$Q:$Q,'List of Ledgers '!$F:$F,'P&L'!$A59,'List of Ledgers '!$G:$G,'P&L'!U$6) -> 4180 | V59: =SUM(N59:U59) -> 215899.57 | W59: =SUMIFS('List of Ledgers '!$Q:$Q,'List of Ledgers '!$F:$F,'P&L'!$A59,'List of Ledgers '!$G:$G,'P&L'!W$6) -> 0 | X59: =V59+W59 -> 215899.57 | Y59: =V59-X59 -> 0
A60: Salary & wages | B60: =SUMIFS('List of Ledgers '!$L:$L,'List of Ledgers '!$F:$F,'P&L'!$A60,'List of Ledgers '!$G:$G,'P&L'!B$6) -> 0 | C60: =SUMIFS('List of Ledgers '!$L:$L,'List of Ledgers '!$F:$F,'P&L'!$A60,'List of Ledgers '!$G:$G,'P&L'!C$6) -> 0 | D60: =SUMIFS('List of Ledgers '!$L:$L,'List of Ledgers '!$F:$F,'P&L'!$A60,'List of Ledgers '!$G:$G,'P&L'!D$6) -> 0 | E60: =SUMIFS('List of Ledgers '!$L:$L,'List of Ledgers '!$F:$F,'P&L'!$A60,'List of Ledgers '!$G:$G,'P&L'!E$6) -> 0 | F60: =SUMIFS('List of Ledgers '!$L:$L,'List of Ledgers '!$F:$F,'P&L'!$A60,'List of Ledgers '!$G:$G,'P&L'!F$6) -> 0 | G60: =SUMIFS('List of Ledgers '!$L:$L,'List of Ledgers '!$F:$F,'P&L'!$A60,'List of Ledgers '!$G:$G,'P&L'!G$6) -> 148231 | H60: =SUMIFS('List of Ledgers '!$L:$L,'List of Ledgers '!$F:$F,'P&L'!$A60,'List of Ledgers '!$G:$G,'P&L'!H$6) -> 0 | I60: =SUMIFS('List of Ledgers '!$L:$L,'List of Ledgers '!$F:$F,'P&L'!$A60,'List of Ledgers '!$G:$G,'P&L'!I$6) -> 499417 | J60: =SUM(B60:I60) -> 647648 | K60: =SUMIFS('List of Ledgers '!$L:$L,'List of Ledgers '!$F:$F,'P&L'!$A60,'List of Ledgers '!$G:$G,'P&L'!$K$6) -> 0 | L60: =J60+K60 -> 647648 | N60: =SUMIFS('List of Ledgers '!$Q:$Q,'List of Ledgers '!$F:$F,'P&L'!$A60,'List of Ledgers '!$G:$G,'P&L'!N$6) -> 0 | O60: =SUMIFS('List of Ledgers '!$Q:$Q,'List of Ledgers '!$F:$F,'P&L'!$A60,'List of Ledgers '!$G:$G,'P&L'!O$6) -> 79825 | P60: =SUMIFS('List of Ledgers '!$Q:$Q,'List of Ledgers '!$F:$F,'P&L'!$A60,'List of Ledgers '!$G:$G,'P&L'!P$6) -> 0 | Q60: =SUMIFS('List of Ledgers '!$Q:$Q,'List of Ledgers '!$F:$F,'P&L'!$A60,'List of Ledgers '!$G:$G,'P&L'!Q$6) -> 0 | R60: =SUMIFS('List of Ledgers '!$Q:$Q,'List of Ledgers '!$F:$F,'P&L'!$A60,'List of Ledgers '!$G:$G,'P&L'!R$6) -> 0 | S60: =SUMIFS('List of Ledgers '!$Q:$Q,'List of Ledgers '!$F:$F,'P&L'!$A60,'List of Ledgers '!$G:$G,'P&L'!S$6) -> 1640391 | T60: =SUMIFS('List of Ledgers '!$Q:$Q,'List of Ledgers '!$F:$F,'P&L'!$A60,'List of Ledgers '!$G:$G,'P&L'!T$6) -> 0 | U60: =SUMIFS('List of Ledgers '!$Q:$Q,'List of Ledgers '!$F:$F,'P&L'!$A60,'List of Ledgers '!$G:$G,'P&L'!U$6) -> 1835500 | V60: =SUM(N60:U60) -> 3555716 | W60: =SUMIFS('List of Ledgers '!$Q:$Q,'List of Ledgers '!$F:$F,'P&L'!$A60,'List of Ledgers '!$G:$G,'P&L'!W$6) -> 0 | X60: =V60+W60 -> 3555716 | Y60: =V60-X60 -> 0
A61: Share trading expenses | B61: =SUMIFS('List of Ledgers '!$L:$L,'List of Ledgers '!$F:$F,'P&L'!$A61,'List of Ledgers '!$G:$G,'P&L'!B$6) -> 0 | C61: =SUMIFS('List of Ledgers '!$L:$L,'List of Ledgers '!$F:$F,'P&L'!$A61,'List of Ledgers '!$G:$G,'P&L'!C$6) -> 0 | D61: =SUMIFS('List of Ledgers '!$L:$L,'List of Ledgers '!$F:$F,'P&L'!$A61,'List of Ledgers '!$G:$G,'P&L'!D$6) -> 0 | E61: =SUMIFS('List of Ledgers '!$L:$L,'List of Ledgers '!$F:$F,'P&L'!$A61,'List of Ledgers '!$G:$G,'P&L'!E$6) -> 0 | F61: =SUMIFS('List of Ledgers '!$L:$L,'List of Ledgers '!$F:$F,'P&L'!$A61,'List of Ledgers '!$G:$G,'P&L'!F$6) -> 0 | G61: =SUMIFS('List of Ledgers '!$L:$L,'List of Ledgers '!$F:$F,'P&L'!$A61,'List of Ledgers '!$G:$G,'P&L'!G$6) -> 0 | H61: =SUMIFS('List of Ledgers '!$L:$L,'List of Ledgers '!$F:$F,'P&L'!$A61,'List of Ledgers '!$G:$G,'P&L'!H$6) -> 0 | I61: =SUMIFS('List of Ledgers '!$L:$L,'List of Ledgers '!$F:$F,'P&L'!$A61,'List of Ledgers '!$G:$G,'P&L'!I$6) -> 0 | J61: =SUM(B61:I61) -> 0 | K61: =SUMIFS('List of Ledgers '!$L:$L,'List of Ledgers '!$F:$F,'P&L'!$A61,'List of Ledgers '!$G:$G,'P&L'!$K$6) -> 0 | L61: =J61+K61 -> 0 | N61: =SUMIFS('List of Ledgers '!$Q:$Q,'List of Ledgers '!$F:$F,'P&L'!$A61,'List of Ledgers '!$G:$G,'P&L'!N$6) -> 0 | O61: =SUMIFS('List of Ledgers '!$Q:$Q,'List of Ledgers '!$F:$F,'P&L'!$A61,'List of Ledgers '!$G:$G,'P&L'!O$6) -> 0 | P61: =SUMIFS('List of Ledgers '!$Q:$Q,'List of Ledgers '!$F:$F,'P&L'!$A61,'List of Ledgers '!$G:$G,'P&L'!P$6) -> 0 | Q61: =SUMIFS('List of Ledgers '!$Q:$Q,'List of Ledgers '!$F:$F,'P&L'!$A61,'List of Ledgers '!$G:$G,'P&L'!Q$6) -> 0 | R61: =SUMIFS('List of Ledgers '!$Q:$Q,'List of Ledgers '!$F:$F,'P&L'!$A61,'List of Ledgers '!$G:$G,'P&L'!R$6) -> 0 | S61: =SUMIFS('List of Ledgers '!$Q:$Q,'List of Ledgers '!$F:$F,'P&L'!$A61,'List of Ledgers '!$G:$G,'P&L'!S$6) -> 8282.84 | T61: =SUMIFS('List of Ledgers '!$Q:$Q,'List of Ledgers '!$F:$F,'P&L'!$A61,'List of Ledgers '!$G:$G,'P&L'!T$6) -> 0 | U61: =SUMIFS('List of Ledgers '!$Q:$Q,'List of Ledgers '!$F:$F,'P&L'!$A61,'List of Ledgers '!$G:$G,'P&L'!U$6) -> 0 | V61: =SUM(N61:U61) -> 8282.84 | W61: =SUMIFS('List of Ledgers '!$Q:$Q,'List of Ledgers '!$F:$F,'P&L'!$A61,'List of Ledgers '!$G:$G,'P&L'!W$6) -> 460.59 | X61: =V61+W61 -> 8743.43 | Y61: =V61-X61 -> -460.59
A62: Staff welfare expenses | B62: =SUMIFS('List of Ledgers '!$L:$L,'List of Ledgers '!$F:$F,'P&L'!$A62,'List of Ledgers '!$G:$G,'P&L'!B$6) -> 0 | C62: =SUMIFS('List of Ledgers '!$L:$L,'List of Ledgers '!$F:$F,'P&L'!$A62,'List of Ledgers '!$G:$G,'P&L'!C$6) -> 0 | D62: =SUMIFS('List of Ledgers '!$L:$L,'List of Ledgers '!$F:$F,'P&L'!$A62,'List of Ledgers '!$G:$G,'P&L'!D$6) -> 0 | E62: =SUMIFS('List of Ledgers '!$L:$L,'List of Ledgers '!$F:$F,'P&L'!$A62,'List of Ledgers '!$G:$G,'P&L'!E$6) -> 0 | F62: =SUMIFS('List of Ledgers '!$L:$L,'List of Ledgers '!$F:$F,'P&L'!$A62,'List of Ledgers '!$G:$G,'P&L'!F$6) -> 0 | G62: =SUMIFS('List of Ledgers '!$L:$L,'List of Ledgers '!$F:$F,'P&L'!$A62,'List of Ledgers '!$G:$G,'P&L'!G$6) -> 15042 | H62: =SUMIFS('List of Ledgers '!$L:$L,'List of Ledgers '!$F:$F,'P&L'!$A62,'List of Ledgers '!$G:$G,'P&L'!H$6) -> 0 | I62: =SUMIFS('List of Ledgers '!$L:$L,'List of Ledgers '!$F:$F,'P&L'!$A62,'List of Ledgers '!$G:$G,'P&L'!I$6) -> 2290 | J62: =SUM(B62:I62) -> 17332 | K62: =SUMIFS('List of Ledgers '!$L:$L,'List of Ledgers '!$F:$F,'P&L'!$A62,'List of Ledgers '!$G:$G,'P&L'!$K$6) -> 0 | L62: =J62+K62 -> 17332 | N62: =SUMIFS('List of Ledgers '!$Q:$Q,'List of Ledgers '!$F:$F,'P&L'!$A62,'List of Ledgers '!$G:$G,'P&L'!N$6) -> 0 | O62: =SUMIFS('List of Ledgers '!$Q:$Q,'List of Ledgers '!$F:$F,'P&L'!$A62,'List of Ledgers '!$G:$G,'P&L'!O$6) -> 0 | P62: =SUMIFS('List of Ledgers '!$Q:$Q,'List of Ledgers '!$F:$F,'P&L'!$A62,'List of Ledgers '!$G:$G,'P&L'!P$6) -> 0 | Q62: =SUMIFS('List of Ledgers '!$Q:$Q,'List of Ledgers '!$F:$F,'P&L'!$A62,'List of Ledgers '!$G:$G,'P&L'!Q$6) -> 0 | R62: =SUMIFS('List of Ledgers '!$Q:$Q,'List of Ledgers '!$F:$F,'P&L'!$A62,'List of Ledgers '!$G:$G,'P&L'!R$6) -> 0 | S62: =SUMIFS('List of Ledgers '!$Q:$Q,'List of Ledgers '!$F:$F,'P&L'!$A62,'List of Ledgers '!$G:$G,'P&L'!S$6) -> 104822.37 | T62: =SUMIFS('List of Ledgers '!$Q:$Q,'List of Ledgers '!$F:$F,'P&L'!$A62,'List of Ledgers '!$G:$G,'P&L'!T$6) -> 0 | U62: =SUMIFS('List of Ledgers '!$Q:$Q,'List of Ledgers '!$F:$F,'P&L'!$A62,'List of Ledgers '!$G:$G,'P&L'!U$6) -> 9671 | V62: =SUM(N62:U62) -> 114493.37 | W62: =SUMIFS('List of Ledgers '!$Q:$Q,'List of Ledgers '!$F:$F,'P&L'!$A62,'List of Ledgers '!$G:$G,'P&L'!W$6) -> 0 | X62: =V62+W62 -> 114493.37 | Y62: =V62-X62 -> 0
A63: Subscription fees | B63: =SUMIFS('List of Ledgers '!$L:$L,'List of Ledgers '!$F:$F,'P&L'!$A63,'List of Ledgers '!$G:$G,'P&L'!B$6) -> 0 | C63: =SUMIFS('List of Ledgers '!$L:$L,'List of Ledgers '!$F:$F,'P&L'!$A63,'List of Ledgers '!$G:$G,'P&L'!C$6) -> 0 | D63: =SUMIFS('List of Ledgers '!$L:$L,'List of Ledgers '!$F:$F,'P&L'!$A63,'List of Ledgers '!$G:$G,'P&L'!D$6) -> 0 | E63: =SUMIFS('List of Ledgers '!$L:$L,'List of Ledgers '!$F:$F,'P&L'!$A63,'List of Ledgers '!$G:$G,'P&L'!E$6) -> 0 | F63: =SUMIFS('List of Ledgers '!$L:$L,'List of Ledgers '!$F:$F,'P&L'!$A63,'List of Ledgers '!$G:$G,'P&L'!F$6) -> 0 | G63: =SUMIFS('List of Ledgers '!$L:$L,'List of Ledgers '!$F:$F,'P&L'!$A63,'List of Ledgers '!$G:$G,'P&L'!G$6) -> 0 | H63: =SUMIFS('List of Ledgers '!$L:$L,'List of Ledgers '!$F:$F,'P&L'!$A63,'List of Ledgers '!$G:$G,'P&L'!H$6) -> 0 | I63: =SUMIFS('List of Ledgers '!$L:$L,'List of Ledgers '!$F:$F,'P&L'!$A63,'List of Ledgers '!$G:$G,'P&L'!I$6) -> 0 | J63: =SUM(B63:I63) -> 0 | K63: =SUMIFS('List of Ledgers '!$L:$L,'List of Ledgers '!$F:$F,'P&L'!$A63,'List of Ledgers '!$G:$G,'P&L'!$K$6) -> 0 | L63: =J63+K63 -> 0 | N63: =SUMIFS('List of Ledgers '!$Q:$Q,'List of Ledgers '!$F:$F,'P&L'!$A63,'List of Ledgers '!$G:$G,'P&L'!N$6) -> 0 | O63: =SUMIFS('List of Ledgers '!$Q:$Q,'List of Ledgers '!$F:$F,'P&L'!$A63,'List of Ledgers '!$G:$G,'P&L'!O$6) -> 0 | P63: =SUMIFS('List of Ledgers '!$Q:$Q,'List of Ledgers '!$F:$F,'P&L'!$A63,'List of Ledgers '!$G:$G,'P&L'!P$6) -> 0 | Q63: =SUMIFS('List of Ledgers '!$Q:$Q,'List of Ledgers '!$F:$F,'P&L'!$A63,'List of Ledgers '!$G:$G,'P&L'!Q$6) -> 0 | R63: =SUMIFS('List of Ledgers '!$Q:$Q,'List of Ledgers '!$F:$F,'P&L'!$A63,'List of Ledgers '!$G:$G,'P&L'!R$6) -> 0 | S63: =SUMIFS('List of Ledgers '!$Q:$Q,'List of Ledgers '!$F:$F,'P&L'!$A63,'List of Ledgers '!$G:$G,'P&L'!S$6) -> 12194.92 | T63: =SUMIFS('List of Ledgers '!$Q:$Q,'List of Ledgers '!$F:$F,'P&L'!$A63,'List of Ledgers '!$G:$G,'P&L'!T$6) -> 0 | U63: =SUMIFS('List of Ledgers '!$Q:$Q,'List of Ledgers '!$F:$F,'P&L'!$A63,'List of Ledgers '!$G:$G,'P&L'!U$6) -> 0 | V63: =SUM(N63:U63) -> 12194.92 | X63: =V63+W63 -> 12194.92 | Y63: =V63-X63 -> 0
A64: Telephone & Internet charges | B64: =SUMIFS('List of Ledgers '!$L:$L,'List of Ledgers '!$F:$F,'P&L'!$A64,'List of Ledgers '!$G:$G,'P&L'!B$6) -> 0 | C64: =SUMIFS('List of Ledgers '!$L:$L,'List of Ledgers '!$F:$F,'P&L'!$A64,'List of Ledgers '!$G:$G,'P&L'!C$6) -> 0 | D64: =SUMIFS('List of Ledgers '!$L:$L,'List of Ledgers '!$F:$F,'P&L'!$A64,'List of Ledgers '!$G:$G,'P&L'!D$6) -> 4473.46 | E64: =SUMIFS('List of Ledgers '!$L:$L,'List of Ledgers '!$F:$F,'P&L'!$A64,'List of Ledgers '!$G:$G,'P&L'!E$6) -> 0 | F64: =SUMIFS('List of Ledgers '!$L:$L,'List of Ledgers '!$F:$F,'P&L'!$A64,'List of Ledgers '!$G:$G,'P&L'!F$6) -> 0 | G64: =SUMIFS('List of Ledgers '!$L:$L,'List of Ledgers '!$F:$F,'P&L'!$A64,'List of Ledgers '!$G:$G,'P&L'!G$6) -> 2758.18 | H64: =SUMIFS('List of Ledgers '!$L:$L,'List of Ledgers '!$F:$F,'P&L'!$A64,'List of Ledgers '!$G:$G,'P&L'!H$6) -> 0 | I64: =SUMIFS('List of Ledgers '!$L:$L,'List of Ledgers '!$F:$F,'P&L'!$A64,'List of Ledgers '!$G:$G,'P&L'!I$6) -> 499 | J64: =SUM(B64:I64) -> 7730.64 | K64: =SUMIFS('List of Ledgers '!$L:$L,'List of Ledgers '!$F:$F,'P&L'!$A64,'List of Ledgers '!$G:$G,'P&L'!$K$6) -> 0 | L64: =J64+K64 -> 7730.64 | N64: =SUMIFS('List of Ledgers '!$Q:$Q,'List of Ledgers '!$F:$F,'P&L'!$A64,'List of Ledgers '!$G:$G,'P&L'!N$6) -> 0 | O64: =SUMIFS('List of Ledgers '!$Q:$Q,'List of Ledgers '!$F:$F,'P&L'!$A64,'List of Ledgers '!$G:$G,'P&L'!O$6) -> 0 | P64: =SUMIFS('List of Ledgers '!$Q:$Q,'List of Ledgers '!$F:$F,'P&L'!$A64,'List of Ledgers '!$G:$G,'P&L'!P$6) -> 91086.49 | Q64: =SUMIFS('List of Ledgers '!$Q:$Q,'List of Ledgers '!$F:$F,'P&L'!$A64,'List of Ledgers '!$G:$G,'P&L'!Q$6) -> 0 | R64: =SUMIFS('List of Ledgers '!$Q:$Q,'List of Ledgers '!$F:$F,'P&L'!$A64,'List of Ledgers '!$G:$G,'P&L'!R$6) -> 0 | S64: =SUMIFS('List of Ledgers '!$Q:$Q,'List of Ledgers '!$F:$F,'P&L'!$A64,'List of Ledgers '!$G:$G,'P&L'!S$6) -> 10741.73 | T64: =SUMIFS('List of Ledgers '!$Q:$Q,'List of Ledgers '!$F:$F,'P&L'!$A64,'List of Ledgers '!$G:$G,'P&L'!T$6) -> 0 | U64: =SUMIFS('List of Ledgers '!$Q:$Q,'List of Ledgers '!$F:$F,'P&L'!$A64,'List of Ledgers '!$G:$G,'P&L'!U$6) -> 1384.32 | V64: =SUM(N64:U64) -> 103212.54 | W64: =SUMIFS('List of Ledgers '!$Q:$Q,'List of Ledgers '!$F:$F,'P&L'!$A64,'List of Ledgers '!$G:$G,'P&L'!W$6) -> 0 | X64: =V64+W64 -> 103212.54 | Y64: =V64-X64 -> 0
A65: Transportation | B65: =SUMIFS('List of Ledgers '!$L:$L,'List of Ledgers '!$F:$F,'P&L'!$A65,'List of Ledgers '!$G:$G,'P&L'!B$6) -> 0 | C65: =SUMIFS('List of Ledgers '!$L:$L,'List of Ledgers '!$F:$F,'P&L'!$A65,'List of Ledgers '!$G:$G,'P&L'!C$6) -> 0 | D65: =SUMIFS('List of Ledgers '!$L:$L,'List of Ledgers '!$F:$F,'P&L'!$A65,'List of Ledgers '!$G:$G,'P&L'!D$6) -> 0 | E65: =SUMIFS('List of Ledgers '!$L:$L,'List of Ledgers '!$F:$F,'P&L'!$A65,'List of Ledgers '!$G:$G,'P&L'!E$6) -> 0 | F65: =SUMIFS('List of Ledgers '!$L:$L,'List of Ledgers '!$F:$F,'P&L'!$A65,'List of Ledgers '!$G:$G,'P&L'!F$6) -> 0 | G65: =SUMIFS('List of Ledgers '!$L:$L,'List of Ledgers '!$F:$F,'P&L'!$A65,'List of Ledgers '!$G:$G,'P&L'!G$6) -> 0 | H65: =SUMIFS('List of Ledgers '!$L:$L,'List of Ledgers '!$F:$F,'P&L'!$A65,'List of Ledgers '!$G:$G,'P&L'!H$6) -> 0 | I65: =SUMIFS('List of Ledgers '!$L:$L,'List of Ledgers '!$F:$F,'P&L'!$A65,'List of Ledgers '!$G:$G,'P&L'!I$6) -> 126600 | J65: =SUM(B65:I65) -> 126600 | K65: =SUMIFS('List of Ledgers '!$L:$L,'List of Ledgers '!$F:$F,'P&L'!$A65,'List of Ledgers '!$G:$G,'P&L'!$K$6) -> 0 | L65: =J65+K65 -> 126600 | N65: =SUMIFS('List of Ledgers '!$Q:$Q,'List of Ledgers '!$F:$F,'P&L'!$A65,'List of Ledgers '!$G:$G,'P&L'!N$6) -> 0 | O65: =SUMIFS('List of Ledgers '!$Q:$Q,'List of Ledgers '!$F:$F,'P&L'!$A65,'List of Ledgers '!$G:$G,'P&L'!O$6) -> 0 | P65: =SUMIFS('List of Ledgers '!$Q:$Q,'List of Ledgers '!$F:$F,'P&L'!$A65,'List of Ledgers '!$G:$G,'P&L'!P$6) -> 735787 | Q65: =SUMIFS('List of Ledgers '!$Q:$Q,'List of Ledgers '!$F:$F,'P&L'!$A65,'List of Ledgers '!$G:$G,'P&L'!Q$6) -> 0 | R65: =SUMIFS('List of Ledgers '!$Q:$Q,'List of Ledgers '!$F:$F,'P&L'!$A65,'List of Ledgers '!$G:$G,'P&L'!R$6) -> 0 | S65: =SUMIFS('List of Ledgers '!$Q:$Q,'List of Ledgers '!$F:$F,'P&L'!$A65,'List of Ledgers '!$G:$G,'P&L'!S$6) -> 0 | T65: =SUMIFS('List of Ledgers '!$Q:$Q,'List of Ledgers '!$F:$F,'P&L'!$A65,'List of Ledgers '!$G:$G,'P&L'!T$6) -> 0 | U65: =SUMIFS('List of Ledgers '!$Q:$Q,'List of Ledgers '!$F:$F,'P&L'!$A65,'List of Ledgers '!$G:$G,'P&L'!U$6) -> 409050 | V65: =SUM(N65:U65) -> 1144837 | W65: =SUMIFS('List of Ledgers '!$Q:$Q,'List of Ledgers '!$F:$F,'P&L'!$A65,'List of Ledgers '!$G:$G,'P&L'!W$6) -> 0 | X65: =V65+W65 -> 1144837 | Y65: =V65-X65 -> 0
A66: Travelling expenses | B66: =SUMIFS('List of Ledgers '!$L:$L,'List of Ledgers '!$F:$F,'P&L'!$A66,'List of Ledgers '!$G:$G,'P&L'!B$6) -> 0 | C66: =SUMIFS('List of Ledgers '!$L:$L,'List of Ledgers '!$F:$F,'P&L'!$A66,'List of Ledgers '!$G:$G,'P&L'!C$6) -> 0 | D66: =SUMIFS('List of Ledgers '!$L:$L,'List of Ledgers '!$F:$F,'P&L'!$A66,'List of Ledgers '!$G:$G,'P&L'!D$6) -> 0 | E66: =SUMIFS('List of Ledgers '!$L:$L,'List of Ledgers '!$F:$F,'P&L'!$A66,'List of Ledgers '!$G:$G,'P&L'!E$6) -> 0 | F66: =SUMIFS('List of Ledgers '!$L:$L,'List of Ledgers '!$F:$F,'P&L'!$A66,'List of Ledgers '!$G:$G,'P&L'!F$6) -> 0 | G66: =SUMIFS('List of Ledgers '!$L:$L,'List of Ledgers '!$F:$F,'P&L'!$A66,'List of Ledgers '!$G:$G,'P&L'!G$6) -> 42651 | H66: =SUMIFS('List of Ledgers '!$L:$L,'List of Ledgers '!$F:$F,'P&L'!$A66,'List of Ledgers '!$G:$G,'P&L'!H$6) -> 1013313 | I66: =SUMIFS('List of Ledgers '!$L:$L,'List of Ledgers '!$F:$F,'P&L'!$A66,'List of Ledgers '!$G:$G,'P&L'!I$6) -> 5395.95 | J66: =SUM(B66:I66) -> 1061359.9 | K66: =SUMIFS('List of Ledgers '!$L:$L,'List of Ledgers '!$F:$F,'P&L'!$A66,'List of Ledgers '!$G:$G,'P&L'!$K$6) -> 0 | L66: =J66+K66 -> 1061359.9 | N66: =SUMIFS('List of Ledgers '!$Q:$Q,'List of Ledgers '!$F:$F,'P&L'!$A66,'List of Ledgers '!$G:$G,'P&L'!N$6) -> 0 | O66: =SUMIFS('List of Ledgers '!$Q:$Q,'List of Ledgers '!$F:$F,'P&L'!$A66,'List of Ledgers '!$G:$G,'P&L'!O$6) -> 0 | P66: =SUMIFS('List of Ledgers '!$Q:$Q,'List of Ledgers '!$F:$F,'P&L'!$A66,'List of Ledgers '!$G:$G,'P&L'!P$6) -> 1443967.5 | Q66: =SUMIFS('List of Ledgers '!$Q:$Q,'List of Ledgers '!$F:$F,'P&L'!$A66,'List of Ledgers '!$G:$G,'P&L'!Q$6) -> 0 | R66: =SUMIFS('List of Ledgers '!$Q:$Q,'List of Ledgers '!$F:$F,'P&L'!$A66,'List of Ledgers '!$G:$G,'P&L'!R$6) -> 0 | S66: =SUMIFS('List of Ledgers '!$Q:$Q,'List of Ledgers '!$F:$F,'P&L'!$A66,'List of Ledgers '!$G:$G,'P&L'!S$6) -> 741479.9 | T66: =SUMIFS('List of Ledgers '!$Q:$Q,'List of Ledgers '!$F:$F,'P&L'!$A66,'List of Ledgers '!$G:$G,'P&L'!T$6) -> 3912911.9 | U66: =SUMIFS('List of Ledgers '!$Q:$Q,'List of Ledgers '!$F:$F,'P&L'!$A66,'List of Ledgers '!$G:$G,'P&L'!U$6) -> 24171.95 | V66: =SUM(N66:U66) -> 6122531.2 | W66: =SUMIFS('List of Ledgers '!$Q:$Q,'List of Ledgers '!$F:$F,'P&L'!$A66,'List of Ledgers '!$G:$G,'P&L'!W$6) -> 0 | X66: =V66+W66 -> 6122531.2 | Y66: =V66-X66 -> 0
A67: Packing Charges | B67: =SUMIFS('List of Ledgers '!$L:$L,'List of Ledgers '!$F:$F,'P&L'!$A67,'List of Ledgers '!$G:$G,'P&L'!B$6) -> 0 | C67: =SUMIFS('List of Ledgers '!$L:$L,'List of Ledgers '!$F:$F,'P&L'!$A67,'List of Ledgers '!$G:$G,'P&L'!C$6) -> 0 | D67: =SUMIFS('List of Ledgers '!$L:$L,'List of Ledgers '!$F:$F,'P&L'!$A67,'List of Ledgers '!$G:$G,'P&L'!D$6) -> 0 | E67: =SUMIFS('List of Ledgers '!$L:$L,'List of Ledgers '!$F:$F,'P&L'!$A67,'List of Ledgers '!$G:$G,'P&L'!E$6) -> 0 | F67: =SUMIFS('List of Ledgers '!$L:$L,'List of Ledgers '!$F:$F,'P&L'!$A67,'List of Ledgers '!$G:$G,'P&L'!F$6) -> 0 | G67: =SUMIFS('List of Ledgers '!$L:$L,'List of Ledgers '!$F:$F,'P&L'!$A67,'List of Ledgers '!$G:$G,'P&L'!G$6) -> 0 | H67: =SUMIFS('List of Ledgers '!$L:$L,'List of Ledgers '!$F:$F,'P&L'!$A67,'List of Ledgers '!$G:$G,'P&L'!H$6) -> 0 | I67: =SUMIFS('List of Ledgers '!$L:$L,'List of Ledgers '!$F:$F,'P&L'!$A67,'List of Ledgers '!$G:$G,'P&L'!I$6) -> 0 | J67: =SUM(B67:I67) -> 0 | K67: =SUMIFS('List of Ledgers '!$L:$L,'List of Ledgers '!$F:$F,'P&L'!$A67,'List of Ledgers '!$G:$G,'P&L'!$K$6) -> 0 | L67: =J67+K67 -> 0 | N67: =SUMIFS('List of Ledgers '!$Q:$Q,'List of Ledgers '!$F:$F,'P&L'!$A67,'List of Ledgers '!$G:$G,'P&L'!N$6) -> 0 | O67: =SUMIFS('List of Ledgers '!$Q:$Q,'List of Ledgers '!$F:$F,'P&L'!$A67,'List of Ledgers '!$G:$G,'P&L'!O$6) -> 0 | P67: =SUMIFS('List of Ledgers '!$Q:$Q,'List of Ledgers '!$F:$F,'P&L'!$A67,'List of Ledgers '!$G:$G,'P&L'!P$6) -> 0 | Q67: =SUMIFS('List of Ledgers '!$Q:$Q,'List of Ledgers '!$F:$F,'P&L'!$A67,'List of Ledgers '!$G:$G,'P&L'!Q$6) -> 0 | R67: =SUMIFS('List of Ledgers '!$Q:$Q,'List of Ledgers '!$F:$F,'P&L'!$A67,'List of Ledgers '!$G:$G,'P&L'!R$6) -> 0 | S67: =SUMIFS('List of Ledgers '!$Q:$Q,'List of Ledgers '!$F:$F,'P&L'!$A67,'List of Ledgers '!$G:$G,'P&L'!S$6) -> 0 | T67: =SUMIFS('List of Ledgers '!$Q:$Q,'List of Ledgers '!$F:$F,'P&L'!$A67,'List of Ledgers '!$G:$G,'P&L'!T$6) -> 0 | U67: =SUMIFS('List of Ledgers '!$Q:$Q,'List of Ledgers '!$F:$F,'P&L'!$A67,'List of Ledgers '!$G:$G,'P&L'!U$6) -> 0 | V67: =SUM(N67:U67) -> 0 | W67: =SUMIFS('List of Ledgers '!$Q:$Q,'List of Ledgers '!$F:$F,'P&L'!$A67,'List of Ledgers '!$G:$G,'P&L'!W$6) -> 0 | X67: =V67+W67 -> 0 | Y67: =V67-X67 -> 0
Y68: =V68-X68 -> 0
A69: Indirect costs | B69: =SUM(B36:B68) -> 0 | C69: =SUM(C36:C68) -> 18401.57 | D69: =SUM(D36:D68) -> 123899.4 | E69: =SUM(E36:E68) -> 0 | F69: =SUM(F36:F68) -> 0 | G69: =SUM(G36:G68) -> 3160813.6 | H69: =SUM(H36:H68) -> 1037123 | I69: =SUM(I36:I68) -> 968168.74 | ... L69: =SUM(L36:L68) -> 5308406.3 | N69: =SUM(N36:N68) -> 20850 | O69: =SUM(O36:O68) -> 98226.57 | P69: =SUM(P36:P68) -> 3051552.7 | Q69: =SUM(Q36:Q68) -> 0 | R69: =SUM(R36:R68) -> 0 | S69: =SUM(S36:S68) -> 9641656.3 | T69: =SUM(T36:T68) -> 6733716.4 | U69: =SUM(U36:U68) -> 3364458.3 | ... X69: =SUM(X36:X68) -> 22910921 | Y69: =V69-X69 -> -460.59
A71: Allocation of expenses:
A72: Factory | B72: =($E69+$E8)/3 -> 0 | C72: =($E69+$E8)/3 -> 0 | D72: =($E69+$E8)/3 -> 0 | J72: =SUM(B72:G72) -> 0 | L72: =J72+K72 -> 0 | N72: =($Q$69+$Q$8)/3 -> 0 | O72: =($Q$69+$Q$8)/3 -> 0 | P72: =($Q$69+$Q$8)/3 -> 0 | V72: =SUM(N72:S72) -> 0 | X72: =V72+W72 -> 0
A73: Office | B73: =($F69+$F8)/3 -> 0 | C73: =($F69+$F8)/3 -> 0 | D73: =($F69+$F8)/3 -> 0 | J73: =SUM(B73:G73) -> 0 | L73: =J73+K73 -> 0 | N73: =($R$69+$R$8)/3 -> 0 | O73: =($R$69+$R$8)/3 -> 0 | P73: =($R$69+$R$8)/3 -> 0 | V73: =SUM(N73:S73) -> 0 | X73: =V73+W73 -> 0
A74: Common | B74: 0 | C74: =G69*C7/J7 -> 1197.7023 | G74: =-G69 -> -3160813.6 | I74: =G69*I7/J7 -> 3159615.9 | J74: =SUM(B74:I74) -> 0 | L74: =J74+K74 -> 0 | N74: =$S$69*N$7/$V$7 -> 74777.922 | O74: =$S$69*O$7/$V$7 -> 35377.352 | P74: =$S$69*P$7/$V$7 -> 4468529.7 | Q74: =$S$69*Q$7/$V$7 -> 0 | R74: =$S$69*R$7/$V$7 -> 0 | S74: =-S69 -> -9641656.3 | T74: =$S$69*T$7/$V$7 -> 0 | U74: =$S$69*U$7/$V$7 -> 5062971.3 | V74: =SUM(N74:U74) -> 0 | X74: =V74+W74 -> 0
A75: Total indirect costs | B75: =B74+B69 -> 0 | C75: =C74+C69 -> 19599.272 | D75: =D74+D69 -> 123899.4 | E75: =E74+E69 -> 0 | F75: =F74+F69 -> 0 | G75: =G74+G69 -> 0 | H75: =H74+H69 -> 1037123 | I75: =I74+I69 -> 4127784.6 | J75: =J74+J69 -> 5308406.3 | L75: =J75+K75 -> 5308406.3 | N75: =N74+N69 -> 95627.922 | O75: =O74+O69 -> 133603.92 | P75: =P74+P69 -> 7520082.4 | Q75: =Q74+Q69 -> 0 | R75: =R74+R69 -> 0 | S75: =S74+S69 -> 0 | T75: =T74+T69 -> 6733716.4 | U75: =U74+U69 -> 8427429.6 | ... X75: =X74+X69 -> 22910921
A78: Profit/ (loss) before tax | B78: =B16+B20-B69 -> 0 | C78: =C16+C20-C69 -> -18401.57 | D78: =D16+D20-D69 -> 16779680 | E78: =E16+E20-E69 -> 0 | F78: =F16+F20-F69 -> 0 | G78: =G16+G20-G69 -> -3195863.6 | H78: =H16+H20-H69 -> -837123 | I78: =I16+I20-I69 -> 2368011 | J78: =J16+J20-J69 -> 15096303 | L78: =L16+L20-L69 -> 15096303 | N78: =N16+N20-N69 -> -81903.05 | O78: =O16+O20-O69 -> 230157.98 | P78: =P16+P20-P69 -> 17378194 | Q78: =Q16+Q20-Q69 -> 0 | R78: =R16+R20-R69 -> 0 | S78: =S16+S20-S69 -> -9028298.8 | T78: =T16+T20-T69 -> -6533716.4 | U78: =U16+U20-U69 -> 2275897.1 | ... X78: =X16+X20-X69 -> 4028515.9
A79: Net margin % | B79: =IFERROR(B78/B7,0) -> 0 | C79: =IFERROR(C78/C7,0) -> -0.64715144 | D79: =IFERROR(D78/D7,0) -> 0 | E79: =IFERROR(E78/E7,0) -> 0 | F79: =IFERROR(F78/F7,0) -> 0 | G79: =IFERROR(G78/G7,0) -> 0 | H79: =IFERROR(H78/H7,0) -> 0 | I79: =IFERROR(I78/I7,0) -> 0.031568166 | ... L79: =IFERROR(L78/L7,0) -> 0.2011739 | N79: =IFERROR(N78/N7,0) -> -0.046253302 | O79: =IFERROR(O78/O7,0) -> 0.27473676 | P79: =IFERROR(P78/P7,0) -> 0.16423134 | Q79: =IFERROR(Q78/Q7,0) -> 0 | R79: =IFERROR(R78/R7,0) -> 0 | S79: =IFERROR(S78/S7,0) -> 0 | T79: =IFERROR(T78/T7,0) -> 0 | U79: =IFERROR(U78/U7,0) -> 0.018982929 | ... X79: =IFERROR(X78/X7,0) -> 0.017644506
A80: Net margin % (previous month) | B80: 0 | C80: -3.20414 | D80: 0 | E80: 0 | F80: 0 | G80: 0 | H80: 0 | I80: 0.055087088 | J80: 0.0096455956 | K80: 0 | L80: 0 | N80: -0.046253302 | O80: 0.34334619 | P80: -0.021525231 | Q80: 0 | R80: 0 | S80: 0 | T80: 0 | U80: 0.061729204 | V80: -0.09436545 | W80: 0 | X80: -0.096288745
J82: =J78-K82 -> 15096303 | K82: =K69-K31 -> 0 | V82: =V78-W82 -> 4028515.9 | W82: 211814.79
J83: 15096303 | V83: 4028515.9
I84: Difference | J84: =J82-J83 -> 1.4901161e-08 | V84: =V82-V83 -> 3.2130629e-08
A85: Business Vertical | C85: =L5 -> Mar'26 | D85: YTD
A86: Bluestreak | C86: =B69 -> 0 | D86: =N69 -> 20850
A87: Clarus | C87: =C69 -> 18401.57 | D87: =O69 -> 98226.57
A88: IT | C88: =D69 -> 123899.4 | D88: =P69 -> 3051552.7
A89: Factory | C89: =E69 -> 0 | D89: =Q69 -> 0
A90: Office | C90: =F69 -> 0 | D90: =R69 -> 0
A91: Common | C91: =G69 -> 3160813.6 | D91: =S69 -> 9641656.3
A92: Spices - A to Z | C92: =H69 -> 1037123 | D92: =T69 -> 6733716.4
A93: Spices - Vashi | C93: =I69 -> 968168.74 | D93: =U69 -> 3364458.3
A94: Total Operating Expenses | C94: =SUM(C86:C93) -> 5308406.3 | D94: =SUM(D86:D93) -> 22910460

Sheet Marketing Expenses
L1: ='P&L'!L5 -> Mar'26 | N1: ='P&L'!N5 -> (April to Mar) | X1: YTD'26
A2: Expenses Type | B2: Bluestreak | C2: Clarus | D2: IT | E2: Factory | F2: Office | G2: Common | H2: Spices - A to Z | I2: Spices - Vashi | J2: Total (without share trading) | K2: Share Trading | L2: Total (including share trading) | N2: Bluestreak | O2: Clarus | P2: IT | Q2: Factory | R2: Office | S2: Common | T2: Spices - A to Z | U2: Spices - Vashi | V2: Total (without share trading) | W2: Share Trading | X2: Total (including share trading)
A3: Creative agency charges | B3: =SUMIFS('List of Ledgers '!$L:$L,'List of Ledgers '!$F:$F,'Marketing Expenses'!$A3,'List of Ledgers '!$G:$G,'Marketing Expenses'!B$2) -> 0 | C3: =SUMIFS('List of Ledgers '!$L:$L,'List of Ledgers '!$F:$F,'Marketing Expenses'!$A3,'List of Ledgers '!$G:$G,'Marketing Expenses'!C$2) -> 0 | D3: =SUMIFS('List of Ledgers '!$L:$L,'List of Ledgers '!$F:$F,'Marketing Expenses'!$A3,'List of Ledgers '!$G:$G,'Marketing Expenses'!D$2) -> 0 | E3: =SUMIFS('List of Ledgers '!$L:$L,'List of Ledgers '!$F:$F,'Marketing Expenses'!$A3,'List of Ledgers '!$G:$G,'Marketing Expenses'!E$2) -> 0 | F3: =SUMIFS('List of Ledgers '!$L:$L,'List of Ledgers '!$F:$F,'Marketing Expenses'!$A3,'List of Ledgers '!$G:$G,'Marketing Expenses'!F$2) -> 0 | G3: =SUMIFS('List of Ledgers '!$L:$L,'List of Ledgers '!$F:$F,'Marketing Expenses'!$A3,'List of Ledgers '!$G:$G,'Marketing Expenses'!G$2) -> 0 | H3: =SUMIFS('List of Ledgers '!$L:$L,'List of Ledgers '!$F:$F,'Marketing Expenses'!$A3,'List of Ledgers '!$G:$G,'Marketing Expenses'!H$2) -> 0 | I3: =SUMIFS('List of Ledgers '!$L:$L,'List of Ledgers '!$F:$F,'Marketing Expenses'!$A3,'List of Ledgers '!$G:$G,'Marketing Expenses'!I$2) -> 0 | J3: =SUM(B3:I3) -> 0 | K3: =SUMIFS('List of Ledgers '!$L:$L,'List of Ledgers '!$F:$F,'Marketing Expenses'!$A3,'List of Ledgers '!$G:$G,'Marketing Expenses'!K$2) -> 0 | L3: =J3+K3 -> 0 | N3: =SUMIFS('List of Ledgers '!$Q:$Q,'List of Ledgers '!$F:$F,'Marketing Expenses'!$A3,'List of Ledgers '!$G:$G,'Marketing Expenses'!N$2) -> 0 | O3: =SUMIFS('List of Ledgers '!$Q:$Q,'List of Ledgers '!$F:$F,'Marketing Expenses'!$A3,'List of Ledgers '!$G:$G,'Marketing Expenses'!O$2) -> 0 | P3: =SUMIFS('List of Ledgers '!$Q:$Q,'List of Ledgers '!$F:$F,'Marketing Expenses'!$A3,'List of Ledgers '!$G:$G,'Marketing Expenses'!P$2) -> 0 | Q3: =SUMIFS('List of Ledgers '!$Q:$Q,'List of Ledgers '!$F:$F,'Marketing Expenses'!$A3,'List of Ledgers '!$G:$G,'Marketing Expenses'!Q$2) -> 0 | R3: =SUMIFS('List of Ledgers '!$Q:$Q,'List of Ledgers '!$F:$F,'Marketing Expenses'!$A3,'List of Ledgers '!$G:$G,'Marketing Expenses'!R$2) -> 0 | S3: =SUMIFS('List of Ledgers '!$Q:$Q,'List of Ledgers '!$F:$F,'Marketing Expenses'!$A3,'List of Ledgers '!$G:$G,'Marketing Expenses'!S$2) -> 0 | T3: =SUMIFS('List of Ledgers '!$Q:$Q,'List of Ledgers '!$F:$F,'Marketing Expenses'!$A3,'List of Ledgers '!$G:$G,'Marketing Expenses'!T$2) -> 418005 | U3: =SUMIFS('List of Ledgers '!$Q:$Q,'List of Ledgers '!$F:$F,'Marketing Expenses'!$A3,'List of Ledgers '!$G:$G,'Marketing Expenses'!U$2) -> 0 | V3: =SUM(N3:U3) -> 418005 | W3: =SUMIFS('List of Ledgers '!$Q:$Q,'List of Ledgers '!$F:$F,'Marketing Expenses'!$A3,'List of Ledgers '!$G:$G,'Marketing Expenses'!W$2) -> 0 | X3: =W3+V3 -> 418005
A4: Website charges | B4: =SUMIFS('List of Ledgers '!$L:$L,'List of Ledgers '!$F:$F,'Marketing Expenses'!$A4,'List of Ledgers '!$G:$G,'Marketing Expenses'!B$2) -> 0 | C4: =SUMIFS('List of Ledgers '!$L:$L,'List of Ledgers '!$F:$F,'Marketing Expenses'!$A4,'List of Ledgers '!$G:$G,'Marketing Expenses'!C$2) -> 0 | D4: =SUMIFS('List of Ledgers '!$L:$L,'List of Ledgers '!$F:$F,'Marketing Expenses'!$A4,'List of Ledgers '!$G:$G,'Marketing Expenses'!D$2) -> 0 | E4: =SUMIFS('List of Ledgers '!$L:$L,'List of Ledgers '!$F:$F,'Marketing Expenses'!$A4,'List of Ledgers '!$G:$G,'Marketing Expenses'!E$2) -> 0 | F4: =SUMIFS('List of Ledgers '!$L:$L,'List of Ledgers '!$F:$F,'Marketing Expenses'!$A4,'List of Ledgers '!$G:$G,'Marketing Expenses'!F$2) -> 0 | G4: =SUMIFS('List of Ledgers '!$L:$L,'List of Ledgers '!$F:$F,'Marketing Expenses'!$A4,'List of Ledgers '!$G:$G,'Marketing Expenses'!G$2) -> 0 | H4: =SUMIFS('List of Ledgers '!$L:$L,'List of Ledgers '!$F:$F,'Marketing Expenses'!$A4,'List of Ledgers '!$G:$G,'Marketing Expenses'!H$2) -> 0 | I4: =SUMIFS('List of Ledgers '!$L:$L,'List of Ledgers '!$F:$F,'Marketing Expenses'!$A4,'List of Ledgers '!$G:$G,'Marketing Expenses'!I$2) -> 0 | J4: =SUM(B4:I4) -> 0 | K4: =SUMIFS('List of Ledgers '!$L:$L,'List of Ledgers '!$F:$F,'Marketing Expenses'!$A4,'List of Ledgers '!$G:$G,'Marketing Expenses'!K$2) -> 0 | L4: =J4+K4 -> 0 | N4: =SUMIFS('List of Ledgers '!$Q:$Q,'List of Ledgers '!$F:$F,'Marketing Expenses'!$A4,'List of Ledgers '!$G:$G,'Marketing Expenses'!N$2) -> 0 | O4: =SUMIFS('List of Ledgers '!$Q:$Q,'List of Ledgers '!$F:$F,'Marketing Expenses'!$A4,'List of Ledgers '!$G:$G,'Marketing Expenses'!O$2) -> 0 | P4: =SUMIFS('List of Ledgers '!$Q:$Q,'List of Ledgers '!$F:$F,'Marketing Expenses'!$A4,'List of Ledgers '!$G:$G,'Marketing Expenses'!P$2) -> 0 | Q4: =SUMIFS('List of Ledgers '!$Q:$Q,'List of Ledgers '!$F:$F,'Marketing Expenses'!$A4,'List of Ledgers '!$G:$G,'Marketing Expenses'!Q$2) -> 0 | R4: =SUMIFS('List of Ledgers '!$Q:$Q,'List of Ledgers '!$F:$F,'Marketing Expenses'!$A4,'List of Ledgers '!$G:$G,'Marketing Expenses'!R$2) -> 0 | S4: =SUMIFS('List of Ledgers '!$Q:$Q,'List of Ledgers '!$F:$F,'Marketing Expenses'!$A4,'List of Ledgers '!$G:$G,'Marketing Expenses'!S$2) -> 10711 | T4: =SUMIFS('List of Ledgers '!$Q:$Q,'List of Ledgers '!$F:$F,'Marketing Expenses'!$A4,'List of Ledgers '!$G:$G,'Marketing Expenses'!T$2) -> 0 | U4: =SUMIFS('List of Ledgers '!$Q:$Q,'List of Ledgers '!$F:$F,'Marketing Expenses'!$A4,'List of Ledgers '!$G:$G,'Marketing Expenses'!U$2) -> 0 | V4: =SUM(N4:U4) -> 10711 | W4: =SUMIFS('List of Ledgers '!$Q:$Q,'List of Ledgers '!$F:$F,'Marketing Expenses'!$A4,'List of Ledgers '!$G:$G,'Marketing Expenses'!W$2) -> 0 | X4: =W4+V4 -> 10711
A5: SEO charges | B5: =SUMIFS('List of Ledgers '!$L:$L,'List of Ledgers '!$F:$F,'Marketing Expenses'!$A5,'List of Ledgers '!$G:$G,'Marketing Expenses'!B$2) -> 0 | C5: =SUMIFS('List of Ledgers '!$L:$L,'List of Ledgers '!$F:$F,'Marketing Expenses'!$A5,'List of Ledgers '!$G:$G,'Marketing Expenses'!C$2) -> 0 | D5: =SUMIFS('List of Ledgers '!$L:$L,'List of Ledgers '!$F:$F,'Marketing Expenses'!$A5,'List of Ledgers '!$G:$G,'Marketing Expenses'!D$2) -> 0 | E5: =SUMIFS('List of Ledgers '!$L:$L,'List of Ledgers '!$F:$F,'Marketing Expenses'!$A5,'List of Ledgers '!$G:$G,'Marketing Expenses'!E$2) -> 0 | F5: =SUMIFS('List of Ledgers '!$L:$L,'List of Ledgers '!$F:$F,'Marketing Expenses'!$A5,'List of Ledgers '!$G:$G,'Marketing Expenses'!F$2) -> 0 | G5: =SUMIFS('List of Ledgers '!$L:$L,'List of Ledgers '!$F:$F,'Marketing Expenses'!$A5,'List of Ledgers '!$G:$G,'Marketing Expenses'!G$2) -> 0 | H5: =SUMIFS('List of Ledgers '!$L:$L,'List of Ledgers '!$F:$F,'Marketing Expenses'!$A5,'List of Ledgers '!$G:$G,'Marketing Expenses'!H$2) -> 0 | I5: =SUMIFS('List of Ledgers '!$L:$L,'List of Ledgers '!$F:$F,'Marketing Expenses'!$A5,'List of Ledgers '!$G:$G,'Marketing Expenses'!I$2) -> 0 | J5: =SUM(B5:I5) -> 0 | K5: =SUMIFS('List of Ledgers '!$L:$L,'List of Ledgers '!$F:$F,'Marketing Expenses'!$A5,'List of Ledgers '!$G:$G,'Marketing Expenses'!K$2) -> 0 | L5: =J5+K5 -> 0 | N5: =SUMIFS('List of Ledgers '!$Q:$Q,'List of Ledgers '!$F:$F,'Marketing Expenses'!$A5,'List of Ledgers '!$G:$G,'Marketing Expenses'!N$2) -> 0 | O5: =SUMIFS('List of Ledgers '!$Q:$Q,'List of Ledgers '!$F:$F,'Marketing Expenses'!$A5,'List of Ledgers '!$G:$G,'Marketing Expenses'!O$2) -> 0 | P5: =SUMIFS('List of Ledgers '!$Q:$Q,'List of Ledgers '!$F:$F,'Marketing Expenses'!$A5,'List of Ledgers '!$G:$G,'Marketing Expenses'!P$2) -> 0 | Q5: =SUMIFS('List of Ledgers '!$Q:$Q,'List of Ledgers '!$F:$F,'Marketing Expenses'!$A5,'List of Ledgers '!$G:$G,'Marketing Expenses'!Q$2) -> 0 | R5: =SUMIFS('List of Ledgers '!$Q:$Q,'List of Ledgers '!$F:$F,'Marketing Expenses'!$A5,'List of Ledgers '!$G:$G,'Marketing Expenses'!R$2) -> 0 | S5: =SUMIFS('List of Ledgers '!$Q:$Q,'List of Ledgers '!$F:$F,'Marketing Expenses'!$A5,'List of Ledgers '!$G:$G,'Marketing Expenses'!S$2) -> 0 | T5: =SUMIFS('List of Ledgers '!$Q:$Q,'List of Ledgers '!$F:$F,'Marketing Expenses'!$A5,'List of Ledgers '!$G:$G,'Marketing Expenses'!T$2) -> 0 | U5: =SUMIFS('List of Ledgers '!$Q:$Q,'List of Ledgers '!$F:$F,'Marketing Expenses'!$A5,'List of Ledgers '!$G:$G,'Marketing Expenses'!U$2) -> 0 | V5: =SUM(N5:U5) -> 0 | W5: =SUMIFS('List of Ledgers '!$Q:$Q,'List of Ledgers '!$F:$F,'Marketing Expenses'!$A5,'List of Ledgers '!$G:$G,'Marketing Expenses'!W$2) -> 0 | X5: =W5+V5 -> 0
A6: Advertisements costs | B6: =SUMIFS('List of Ledgers '!$L:$L,'List of Ledgers '!$F:$F,'Marketing Expenses'!$A6,'List of Ledgers '!$G:$G,'Marketing Expenses'!B$2) -> 0 | C6: =SUMIFS('List of Ledgers '!$L:$L,'List of Ledgers '!$F:$F,'Marketing Expenses'!$A6,'List of Ledgers '!$G:$G,'Marketing Expenses'!C$2) -> 0 | D6: =SUMIFS('List of Ledgers '!$L:$L,'List of Ledgers '!$F:$F,'Marketing Expenses'!$A6,'List of Ledgers '!$G:$G,'Marketing Expenses'!D$2) -> 30000 | E6: =SUMIFS('List of Ledgers '!$L:$L,'List of Ledgers '!$F:$F,'Marketing Expenses'!$A6,'List of Ledgers '!$G:$G,'Marketing Expenses'!E$2) -> 0 | F6: =SUMIFS('List of Ledgers '!$L:$L,'List of Ledgers '!$F:$F,'Marketing Expenses'!$A6,'List of Ledgers '!$G:$G,'Marketing Expenses'!F$2) -> 0 | G6: =SUMIFS('List of Ledgers '!$L:$L,'List of Ledgers '!$F:$F,'Marketing Expenses'!$A6,'List of Ledgers '!$G:$G,'Marketing Expenses'!G$2) -> 0 | H6: =SUMIFS('List of Ledgers '!$L:$L,'List of Ledgers '!$F:$F,'Marketing Expenses'!$A6,'List of Ledgers '!$G:$G,'Marketing Expenses'!H$2) -> 4000 | I6: =SUMIFS('List of Ledgers '!$L:$L,'List of Ledgers '!$F:$F,'Marketing Expenses'!$A6,'List of Ledgers '!$G:$G,'Marketing Expenses'!I$2) -> 0 | J6: =SUM(B6:I6) -> 34000 | K6: =SUMIFS('List of Ledgers '!$L:$L,'List of Ledgers '!$F:$F,'Marketing Expenses'!$A6,'List of Ledgers '!$G:$G,'Marketing Expenses'!K$2) -> 0 | L6: =J6+K6 -> 34000 | N6: =SUMIFS('List of Ledgers '!$Q:$Q,'List of Ledgers '!$F:$F,'Marketing Expenses'!$A6,'List of Ledgers '!$G:$G,'Marketing Expenses'!N$2) -> 0 | O6: =SUMIFS('List of Ledgers '!$Q:$Q,'List of Ledgers '!$F:$F,'Marketing Expenses'!$A6,'List of Ledgers '!$G:$G,'Marketing Expenses'!O$2) -> 0 | P6: =SUMIFS('List of Ledgers '!$Q:$Q,'List of Ledgers '!$F:$F,'Marketing Expenses'!$A6,'List of Ledgers '!$G:$G,'Marketing Expenses'!P$2) -> 30000 | Q6: =SUMIFS('List of Ledgers '!$Q:$Q,'List of Ledgers '!$F:$F,'Marketing Expenses'!$A6,'List of Ledgers '!$G:$G,'Marketing Expenses'!Q$2) -> 0 | R6: =SUMIFS('List of Ledgers '!$Q:$Q,'List of Ledgers '!$F:$F,'Marketing Expenses'!$A6,'List of Ledgers '!$G:$G,'Marketing Expenses'!R$2) -> 0 | S6: =SUMIFS('List of Ledgers '!$Q:$Q,'List of Ledgers '!$F:$F,'Marketing Expenses'!$A6,'List of Ledgers '!$G:$G,'Marketing Expenses'!S$2) -> 0 | T6: =SUMIFS('List of Ledgers '!$Q:$Q,'List of Ledgers '!$F:$F,'Marketing Expenses'!$A6,'List of Ledgers '!$G:$G,'Marketing Expenses'!T$2) -> 273050 | U6: =SUMIFS('List of Ledgers '!$Q:$Q,'List of Ledgers '!$F:$F,'Marketing Expenses'!$A6,'List of Ledgers '!$G:$G,'Marketing Expenses'!U$2) -> 0 | V6: =SUM(N6:U6) -> 303050 | W6: =SUMIFS('List of Ledgers '!$Q:$Q,'List of Ledgers '!$F:$F,'Marketing Expenses'!$A6,'List of Ledgers '!$G:$G,'Marketing Expenses'!W$2) -> 0 | X6: =W6+V6 -> 303050
A7: Exhibitions costs | B7: =SUMIFS('List of Ledgers '!$L:$L,'List of Ledgers '!$F:$F,'Marketing Expenses'!$A7,'List of Ledgers '!$G:$G,'Marketing Expenses'!B$2) -> 0 | C7: =SUMIFS('List of Ledgers '!$L:$L,'List of Ledgers '!$F:$F,'Marketing Expenses'!$A7,'List of Ledgers '!$G:$G,'Marketing Expenses'!C$2) -> 0 | D7: =SUMIFS('List of Ledgers '!$L:$L,'List of Ledgers '!$F:$F,'Marketing Expenses'!$A7,'List of Ledgers '!$G:$G,'Marketing Expenses'!D$2) -> 0 | E7: =SUMIFS('List of Ledgers '!$L:$L,'List of Ledgers '!$F:$F,'Marketing Expenses'!$A7,'List of Ledgers '!$G:$G,'Marketing Expenses'!E$2) -> 0 | F7: =SUMIFS('List of Ledgers '!$L:$L,'List of Ledgers '!$F:$F,'Marketing Expenses'!$A7,'List of Ledgers '!$G:$G,'Marketing Expenses'!F$2) -> 0 | G7: =SUMIFS('List of Ledgers '!$L:$L,'List of Ledgers '!$F:$F,'Marketing Expenses'!$A7,'List of Ledgers '!$G:$G,'Marketing Expenses'!G$2) -> 0 | H7: =SUMIFS('List of Ledgers '!$L:$L,'List of Ledgers '!$F:$F,'Marketing Expenses'!$A7,'List of Ledgers '!$G:$G,'Marketing Expenses'!H$2) -> 0 | I7: =SUMIFS('List of Ledgers '!$L:$L,'List of Ledgers '!$F:$F,'Marketing Expenses'!$A7,'List of Ledgers '!$G:$G,'Marketing Expenses'!I$2) -> 0 | J7: =SUM(B7:I7) -> 0 | K7: =SUMIFS('List of Ledgers '!$L:$L,'List of Ledgers '!$F:$F,'Marketing Expenses'!$A7,'List of Ledgers '!$G:$G,'Marketing Expenses'!K$2) -> 0 | L7: =J7+K7 -> 0 | N7: =SUMIFS('List of Ledgers '!$Q:$Q,'List of Ledgers '!$F:$F,'Marketing Expenses'!$A7,'List of Ledgers '!$G:$G,'Marketing Expenses'!N$2) -> 0 | O7: =SUMIFS('List of Ledgers '!$Q:$Q,'List of Ledgers '!$F:$F,'Marketing Expenses'!$A7,'List of Ledgers '!$G:$G,'Marketing Expenses'!O$2) -> 0 | P7: =SUMIFS('List of Ledgers '!$Q:$Q,'List of Ledgers '!$F:$F,'Marketing Expenses'!$A7,'List of Ledgers '!$G:$G,'Marketing Expenses'!P$2) -> 0 | Q7: =SUMIFS('List of Ledgers '!$Q:$Q,'List of Ledgers '!$F:$F,'Marketing Expenses'!$A7,'List of Ledgers '!$G:$G,'Marketing Expenses'!Q$2) -> 0 | R7: =SUMIFS('List of Ledgers '!$Q:$Q,'List of Ledgers '!$F:$F,'Marketing Expenses'!$A7,'List of Ledgers '!$G:$G,'Marketing Expenses'!R$2) -> 0 | S7: =SUMIFS('List of Ledgers '!$Q:$Q,'List of Ledgers '!$F:$F,'Marketing Expenses'!$A7,'List of Ledgers '!$G:$G,'Marketing Expenses'!S$2) -> 0 | T7: =SUMIFS('List of Ledgers '!$Q:$Q,'List of Ledgers '!$F:$F,'Marketing Expenses'!$A7,'List of Ledgers '!$G:$G,'Marketing Expenses'!T$2) -> 0 | U7: =SUMIFS('List of Ledgers '!$Q:$Q,'List of Ledgers '!$F:$F,'Marketing Expenses'!$A7,'List of Ledgers '!$G:$G,'Marketing Expenses'!U$2) -> 130800 | V7: =SUM(N7:U7) -> 130800 | W7: =SUMIFS('List of Ledgers '!$Q:$Q,'List of Ledgers '!$F:$F,'Marketing Expenses'!$A7,'List of Ledgers '!$G:$G,'Marketing Expenses'!W$2) -> 0 | X7: =W7+V7 -> 130800
A8: Buyer Sellers Meets costs | B8: =SUMIFS('List of Ledgers '!$L:$L,'List of Ledgers '!$F:$F,'Marketing Expenses'!$A8,'List of Ledgers '!$G:$G,'Marketing Expenses'!B$2) -> 0 | C8: =SUMIFS('List of Ledgers '!$L:$L,'List of Ledgers '!$F:$F,'Marketing Expenses'!$A8,'List of Ledgers '!$G:$G,'Marketing Expenses'!C$2) -> 0 | D8: =SUMIFS('List of Ledgers '!$L:$L,'List of Ledgers '!$F:$F,'Marketing Expenses'!$A8,'List of Ledgers '!$G:$G,'Marketing Expenses'!D$2) -> 0 | E8: =SUMIFS('List of Ledgers '!$L:$L,'List of Ledgers '!$F:$F,'Marketing Expenses'!$A8,'List of Ledgers '!$G:$G,'Marketing Expenses'!E$2) -> 0 | F8: =SUMIFS('List of Ledgers '!$L:$L,'List of Ledgers '!$F:$F,'Marketing Expenses'!$A8,'List of Ledgers '!$G:$G,'Marketing Expenses'!F$2) -> 0 | G8: =SUMIFS('List of Ledgers '!$L:$L,'List of Ledgers '!$F:$F,'Marketing Expenses'!$A8,'List of Ledgers '!$G:$G,'Marketing Expenses'!G$2) -> 0 | H8: =SUMIFS('List of Ledgers '!$L:$L,'List of Ledgers '!$F:$F,'Marketing Expenses'!$A8,'List of Ledgers '!$G:$G,'Marketing Expenses'!H$2) -> 0 | I8: =SUMIFS('List of Ledgers '!$L:$L,'List of Ledgers '!$F:$F,'Marketing Expenses'!$A8,'List of Ledgers '!$G:$G,'Marketing Expenses'!I$2) -> 0 | J8: =SUM(B8:I8) -> 0 | K8: =SUMIFS('List of Ledgers '!$L:$L,'List of Ledgers '!$F:$F,'Marketing Expenses'!$A8,'List of Ledgers '!$G:$G,'Marketing Expenses'!K$2) -> 0 | L8: =J8+K8 -> 0 | N8: =SUMIFS('List of Ledgers '!$Q:$Q,'List of Ledgers '!$F:$F,'Marketing Expenses'!$A8,'List of Ledgers '!$G:$G,'Marketing Expenses'!N$2) -> 0 | O8: =SUMIFS('List of Ledgers '!$Q:$Q,'List of Ledgers '!$F:$F,'Marketing Expenses'!$A8,'List of Ledgers '!$G:$G,'Marketing Expenses'!O$2) -> 0 | P8: =SUMIFS('List of Ledgers '!$Q:$Q,'List of Ledgers '!$F:$F,'Marketing Expenses'!$A8,'List of Ledgers '!$G:$G,'Marketing Expenses'!P$2) -> 0 | Q8: =SUMIFS('List of Ledgers '!$Q:$Q,'List of Ledgers '!$F:$F,'Marketing Expenses'!$A8,'List of Ledgers '!$G:$G,'Marketing Expenses'!Q$2) -> 0 | R8: =SUMIFS('List of Ledgers '!$Q:$Q,'List of Ledgers '!$F:$F,'Marketing Expenses'!$A8,'List of Ledgers '!$G:$G,'Marketing Expenses'!R$2) -> 0 | S8: =SUMIFS('List of Ledgers '!$Q:$Q,'List of Ledgers '!$F:$F,'Marketing Expenses'!$A8,'List of Ledgers '!$G:$G,'Marketing Expenses'!S$2) -> 0 | T8: =SUMIFS('List of Ledgers '!$Q:$Q,'List of Ledgers '!$F:$F,'Marketing Expenses'!$A8,'List of Ledgers '!$G:$G,'Marketing Expenses'!T$2) -> 0 | U8: =SUMIFS('List of Ledgers '!$Q:$Q,'List of Ledgers '!$F:$F,'Marketing Expenses'!$A8,'List of Ledgers '!$G:$G,'Marketing Expenses'!U$2) -> 0 | V8: =SUM(N8:U8) -> 0 | W8: =SUMIFS('List of Ledgers '!$Q:$Q,'List of Ledgers '!$F:$F,'Marketing Expenses'!$A8,'List of Ledgers '!$G:$G,'Marketing Expenses'!W$2) -> 0 | X8: =W8+V8 -> 0
A9: Brochures | B9: =SUMIFS('List of Ledgers '!$L:$L,'List of Ledgers '!$F:$F,'Marketing Expenses'!$A9,'List of Ledgers '!$G:$G,'Marketing Expenses'!B$2) -> 0 | C9: =SUMIFS('List of Ledgers '!$L:$L,'List of Ledgers '!$F:$F,'Marketing Expenses'!$A9,'List of Ledgers '!$G:$G,'Marketing Expenses'!C$2) -> 0 | D9: =SUMIFS('List of Ledgers '!$L:$L,'List of Ledgers '!$F:$F,'Marketing Expenses'!$A9,'List of Ledgers '!$G:$G,'Marketing Expenses'!D$2) -> 0 | E9: =SUMIFS('List of Ledgers '!$L:$L,'List of Ledgers '!$F:$F,'Marketing Expenses'!$A9,'List of Ledgers '!$G:$G,'Marketing Expenses'!E$2) -> 0 | F9: =SUMIFS('List of Ledgers '!$L:$L,'List of Ledgers '!$F:$F,'Marketing Expenses'!$A9,'List of Ledgers '!$G:$G,'Marketing Expenses'!F$2) -> 0 | G9: =SUMIFS('List of Ledgers '!$L:$L,'List of Ledgers '!$F:$F,'Marketing Expenses'!$A9,'List of Ledgers '!$G:$G,'Marketing Expenses'!G$2) -> 0 | H9: =SUMIFS('List of Ledgers '!$L:$L,'List of Ledgers '!$F:$F,'Marketing Expenses'!$A9,'List of Ledgers '!$G:$G,'Marketing Expenses'!H$2) -> 0 | I9: =SUMIFS('List of Ledgers '!$L:$L,'List of Ledgers '!$F:$F,'Marketing Expenses'!$A9,'List of Ledgers '!$G:$G,'Marketing Expenses'!I$2) -> 0 | J9: =SUM(B9:I9) -> 0 | K9: =SUMIFS('List of Ledgers '!$L:$L,'List of Ledgers '!$F:$F,'Marketing Expenses'!$A9,'List of Ledgers '!$G:$G,'Marketing Expenses'!K$2) -> 0 | L9: =J9+K9 -> 0 | N9: =SUMIFS('List of Ledgers '!$Q:$Q,'List of Ledgers '!$F:$F,'Marketing Expenses'!$A9,'List of Ledgers '!$G:$G,'Marketing Expenses'!N$2) -> 0 | O9: =SUMIFS('List of Ledgers '!$Q:$Q,'List of Ledgers '!$F:$F,'Marketing Expenses'!$A9,'List of Ledgers '!$G:$G,'Marketing Expenses'!O$2) -> 0 | P9: =SUMIFS('List of Ledgers '!$Q:$Q,'List of Ledgers '!$F:$F,'Marketing Expenses'!$A9,'List of Ledgers '!$G:$G,'Marketing Expenses'!P$2) -> 0 | Q9: =SUMIFS('List of Ledgers '!$Q:$Q,'List of Ledgers '!$F:$F,'Marketing Expenses'!$A9,'List of Ledgers '!$G:$G,'Marketing Expenses'!Q$2) -> 0 | R9: =SUMIFS('List of Ledgers '!$Q:$Q,'List of Ledgers '!$F:$F,'Marketing Expenses'!$A9,'List of Ledgers '!$G:$G,'Marketing Expenses'!R$2) -> 0 | S9: =SUMIFS('List of Ledgers '!$Q:$Q,'List of Ledgers '!$F:$F,'Marketing Expenses'!$A9,'List of Ledgers '!$G:$G,'Marketing Expenses'!S$2) -> 0 | T9: =SUMIFS('List of Ledgers '!$Q:$Q,'List of Ledgers '!$F:$F,'Marketing Expenses'!$A9,'List of Ledgers '!$G:$G,'Marketing Expenses'!T$2) -> 0 | U9: =SUMIFS('List of Ledgers '!$Q:$Q,'List of Ledgers '!$F:$F,'Marketing Expenses'!$A9,'List of Ledgers '!$G:$G,'Marketing Expenses'!U$2) -> 0 | V9: =SUM(N9:U9) -> 0 | W9: =SUMIFS('List of Ledgers '!$Q:$Q,'List of Ledgers '!$F:$F,'Marketing Expenses'!$A9,'List of Ledgers '!$G:$G,'Marketing Expenses'!W$2) -> 0 | X9: =W9+V9 -> 0
A10: Display material | B10: =SUMIFS('List of Ledgers '!$L:$L,'List of Ledgers '!$F:$F,'Marketing Expenses'!$A10,'List of Ledgers '!$G:$G,'Marketing Expenses'!B$2) -> 0 | C10: =SUMIFS('List of Ledgers '!$L:$L,'List of Ledgers '!$F:$F,'Marketing Expenses'!$A10,'List of Ledgers '!$G:$G,'Marketing Expenses'!C$2) -> 0 | D10: =SUMIFS('List of Ledgers '!$L:$L,'List of Ledgers '!$F:$F,'Marketing Expenses'!$A10,'List of Ledgers '!$G:$G,'Marketing Expenses'!D$2) -> 0 | E10: =SUMIFS('List of Ledgers '!$L:$L,'List of Ledgers '!$F:$F,'Marketing Expenses'!$A10,'List of Ledgers '!$G:$G,'Marketing Expenses'!E$2) -> 0 | F10: =SUMIFS('List of Ledgers '!$L:$L,'List of Ledgers '!$F:$F,'Marketing Expenses'!$A10,'List of Ledgers '!$G:$G,'Marketing Expenses'!F$2) -> 0 | G10: =SUMIFS('List of Ledgers '!$L:$L,'List of Ledgers '!$F:$F,'Marketing Expenses'!$A10,'List of Ledgers '!$G:$G,'Marketing Expenses'!G$2) -> 0 | H10: =SUMIFS('List of Ledgers '!$L:$L,'List of Ledgers '!$F:$F,'Marketing Expenses'!$A10,'List of Ledgers '!$G:$G,'Marketing Expenses'!H$2) -> 0 | I10: =SUMIFS('List of Ledgers '!$L:$L,'List of Ledgers '!$F:$F,'Marketing Expenses'!$A10,'List of Ledgers '!$G:$G,'Marketing Expenses'!I$2) -> 0 | J10: =SUM(B10:I10) -> 0 | K10: =SUMIFS('List of Ledgers '!$L:$L,'List of Ledgers '!$F:$F,'Marketing Expenses'!$A10,'List of Ledgers '!$G:$G,'Marketing Expenses'!K$2) -> 0 | L10: =J10+K10 -> 0 | N10: =SUMIFS('List of Ledgers '!$Q:$Q,'List of Ledgers '!$F:$F,'Marketing Expenses'!$A10,'List of Ledgers '!$G:$G,'Marketing Expenses'!N$2) -> 0 | O10: =SUMIFS('List of Ledgers '!$Q:$Q,'List of Ledgers '!$F:$F,'Marketing Expenses'!$A10,'List of Ledgers '!$G:$G,'Marketing Expenses'!O$2) -> 0 | P10: =SUMIFS('List of Ledgers '!$Q:$Q,'List of Ledgers '!$F:$F,'Marketing Expenses'!$A10,'List of Ledgers '!$G:$G,'Marketing Expenses'!P$2) -> 0 | Q10: =SUMIFS('List of Ledgers '!$Q:$Q,'List of Ledgers '!$F:$F,'Marketing Expenses'!$A10,'List of Ledgers '!$G:$G,'Marketing Expenses'!Q$2) -> 0 | R10: =SUMIFS('List of Ledgers '!$Q:$Q,'List of Ledgers '!$F:$F,'Marketing Expenses'!$A10,'List of Ledgers '!$G:$G,'Marketing Expenses'!R$2) -> 0 | S10: =SUMIFS('List of Ledgers '!$Q:$Q,'List of Ledgers '!$F:$F,'Marketing Expenses'!$A10,'List of Ledgers '!$G:$G,'Marketing Expenses'!S$2) -> 0 | T10: =SUMIFS('List of Ledgers '!$Q:$Q,'List of Ledgers '!$F:$F,'Marketing Expenses'!$A10,'List of Ledgers '!$G:$G,'Marketing Expenses'!T$2) -> 0 | U10: =SUMIFS('List of Ledgers '!$Q:$Q,'List of Ledgers '!$F:$F,'Marketing Expenses'!$A10,'List of Ledgers '!$G:$G,'Marketing Expenses'!U$2) -> 0 | V10: =SUM(N10:U10) -> 0 | W10: =SUMIFS('List of Ledgers '!$Q:$Q,'List of Ledgers '!$F:$F,'Marketing Expenses'!$A10,'List of Ledgers '!$G:$G,'Marketing Expenses'!W$2) -> 0 | X10: =W10+V10 -> 0
A11: Bussiness Development costs | B11: =SUMIFS('List of Ledgers '!$L:$L,'List of Ledgers '!$F:$F,'Marketing Expenses'!$A11,'List of Ledgers '!$G:$G,'Marketing Expenses'!B$2) -> 0 | C11: =SUMIFS('List of Ledgers '!$L:$L,'List of Ledgers '!$F:$F,'Marketing Expenses'!$A11,'List of Ledgers '!$G:$G,'Marketing Expenses'!C$2) -> 0 | D11: =SUMIFS('List of Ledgers '!$L:$L,'List of Ledgers '!$F:$F,'Marketing Expenses'!$A11,'List of Ledgers '!$G:$G,'Marketing Expenses'!D$2) -> 0 | E11: =SUMIFS('List of Ledgers '!$L:$L,'List of Ledgers '!$F:$F,'Marketing Expenses'!$A11,'List of Ledgers '!$G:$G,'Marketing Expenses'!E$2) -> 0 | F11: =SUMIFS('List of Ledgers '!$L:$L,'List of Ledgers '!$F:$F,'Marketing Expenses'!$A11,'List of Ledgers '!$G:$G,'Marketing Expenses'!F$2) -> 0 | G11: =SUMIFS('List of Ledgers '!$L:$L,'List of Ledgers '!$F:$F,'Marketing Expenses'!$A11,'List of Ledgers '!$G:$G,'Marketing Expenses'!G$2) -> 0 | H11: =SUMIFS('List of Ledgers '!$L:$L,'List of Ledgers '!$F:$F,'Marketing Expenses'!$A11,'List of Ledgers '!$G:$G,'Marketing Expenses'!H$2) -> 0 | I11: =SUMIFS('List of Ledgers '!$L:$L,'List of Ledgers '!$F:$F,'Marketing Expenses'!$A11,'List of Ledgers '!$G:$G,'Marketing Expenses'!I$2) -> 0 | J11: =SUM(B11:I11) -> 0 | K11: =SUMIFS('List of Ledgers '!$L:$L,'List of Ledgers '!$F:$F,'Marketing Expenses'!$A11,'List of Ledgers '!$G:$G,'Marketing Expenses'!K$2) -> 0 | L11: =J11+K11 -> 0 | N11: =SUMIFS('List of Ledgers '!$Q:$Q,'List of Ledgers '!$F:$F,'Marketing Expenses'!$A11,'List of Ledgers '!$G:$G,'Marketing Expenses'!N$2) -> 0 | O11: =SUMIFS('List of Ledgers '!$Q:$Q,'List of Ledgers '!$F:$F,'Marketing Expenses'!$A11,'List of Ledgers '!$G:$G,'Marketing Expenses'!O$2) -> 0 | P11: =SUMIFS('List of Ledgers '!$Q:$Q,'List of Ledgers '!$F:$F,'Marketing Expenses'!$A11,'List of Ledgers '!$G:$G,'Marketing Expenses'!P$2) -> 164200.82 | Q11: =SUMIFS('List of Ledgers '!$Q:$Q,'List of Ledgers '!$F:$F,'Marketing Expenses'!$A11,'List of Ledgers '!$G:$G,'Marketing Expenses'!Q$2) -> 0 | R11: =SUMIFS('List of Ledgers '!$Q:$Q,'List of Ledgers '!$F:$F,'Marketing Expenses'!$A11,'List of Ledgers '!$G:$G,'Marketing Expenses'!R$2) -> 0 | S11: =SUMIFS('List of Ledgers '!$Q:$Q,'List of Ledgers '!$F:$F,'Marketing Expenses'!$A11,'List of Ledgers '!$G:$G,'Marketing Expenses'!S$2) -> 861 | T11: =SUMIFS('List of Ledgers '!$Q:$Q,'List of Ledgers '!$F:$F,'Marketing Expenses'!$A11,'List of Ledgers '!$G:$G,'Marketing Expenses'!T$2) -> 0 | U11: =SUMIFS('List of Ledgers '!$Q:$Q,'List of Ledgers '!$F:$F,'Marketing Expenses'!$A11,'List of Ledgers '!$G:$G,'Marketing Expenses'!U$2) -> 421904 | V11: =SUM(N11:U11) -> 586965.82 | W11: =SUMIFS('List of Ledgers '!$Q:$Q,'List of Ledgers '!$F:$F,'Marketing Expenses'!$A11,'List of Ledgers '!$G:$G,'Marketing Expenses'!W$2) -> 0 | X11: =W11+V11 -> 586965.82
A12: Grand Total | B12: =SUM(B3:B11) -> 0 | C12: =SUM(C3:C11) -> 0 | D12: =SUM(D3:D11) -> 30000 | E12: =SUM(E3:E11) -> 0 | F12: =SUM(F3:F11) -> 0 | G12: =SUM(G3:G11) -> 0 | H12: =SUM(H3:H11) -> 4000 | I12: =SUM(I3:I11) -> 0 | ... L12: =SUM(L3:L11) -> 34000 | N12: =SUM(N3:N11) -> 0 | O12: =SUM(O3:O11) -> 0 | P12: =SUM(P3:P11) -> 194200.82 | Q12: =SUM(Q3:Q11) -> 0 | R12: =SUM(R3:R11) -> 0 | S12: =SUM(S3:S11) -> 11572 | T12: =SUM(T3:T11) -> 691055 | U12: =SUM(U3:U11) -> 552704 | ... X12: =SUM(X3:X11) -> 1449531.8

Sheet Stock
A1: M J P T & Co LLP
A2: Pristine Worldwide Private Limited
A3: Stock Summary
F4: ='P&L'!N5 -> (April to Mar)
A5: Sr. No | B5: Business Verticle | C5: Opening Balance | D5: Inward | E5: Outward | F5: Closing Balance
A6: 1 | B6: Bluestreak | C6: =SUMIF('Stk YTD'!$A:$A,Stock!$B6,'Stk YTD'!C:C) -> 4273691 | D6: =SUMIF('Stk YTD'!$A:$A,Stock!$B6,'Stk YTD'!D:D) -> 1345437.9 | E6: =SUMIF('Stk YTD'!$A:$A,Stock!$B6,'Stk YTD'!E:E) -> 2530990.7 | F6: =SUMIF('Stk YTD'!$A:$A,Stock!$B6,'Stk YTD'!F:F) -> 2768029.6
A7: 2 | B7: Clarus | C7: =SUMIF('Stk YTD'!$A:$A,Stock!$B7,'Stk YTD'!C:C) -> 2101860.3 | D7: =SUMIF('Stk YTD'!$A:$A,Stock!$B7,'Stk YTD'!D:D) -> 802219.82 | E7: =SUMIF('Stk YTD'!$A:$A,Stock!$B7,'Stk YTD'!E:E) -> 988667.41 | F7: =SUMIF('Stk YTD'!$A:$A,Stock!$B7,'Stk YTD'!F:F) -> 1867562.3
A8: 3 | B8: IT | C8: =SUMIF('Stk YTD'!$A:$A,Stock!$B8,'Stk YTD'!C:C) -> 14777043 | D8: =SUMIF('Stk YTD'!$A:$A,Stock!$B8,'Stk YTD'!D:D) -> 87437600 | E8: =SUMIF('Stk YTD'!$A:$A,Stock!$B8,'Stk YTD'!E:E) -> 1.0581533e+08 | F8: =SUMIF('Stk YTD'!$A:$A,Stock!$B8,'Stk YTD'!F:F) -> 0
A9: 4 | B9: Spices - Vashi | C9: =SUMIF('Stk YTD'!$A:$A,Stock!$B9,'Stk YTD'!C:C) -> 0 | D9: =SUMIF('Stk YTD'!$A:$A,Stock!$B9,'Stk YTD'!D:D) -> 1.1692874e+08 | E9: =SUMIF('Stk YTD'!$A:$A,Stock!$B9,'Stk YTD'!E:E) -> 1.1997986e+08 | F9: =SUMIF('Stk YTD'!$A:$A,Stock!$B9,'Stk YTD'!F:F) -> 5589254.9
B10: Total | C10: =SUM(C6:C9) -> 21152594 | D10: =SUM(D6:D9) -> 2.06514e+08 | E10: =SUM(E6:E9) -> 2.2931484e+08 | F10: =SUM(F6:F9) -> 10224847
F12: ='P&L'!L5 -> Mar'26
A13: Sr. No | B13: Business Verticle | C13: Opening Balance | D13: Inward | E13: Outward | F13: Closing Balance | G13: Remarks
A14: 1 | B14: Bluestreak | C14: =SUMIF('Stk '!$A:$A,Stock!$B14,'Stk '!C:C) -> 2768029.6 | D14: =SUMIF('Stk '!$A:$A,Stock!$B14,'Stk '!D:D) -> 0 | E14: =SUMIF('Stk '!$A:$A,Stock!$B14,'Stk '!E:E) -> 0 | F14: =SUMIF('Stk '!$A:$A,Stock!$B14,'Stk '!F:F) -> 2768029.6
A15: 2 | B15: Clarus | C15: =SUMIF('Stk '!$A:$A,Stock!$B15,'Stk '!C:C) -> 1234703.5 | D15: =SUMIF('Stk '!$A:$A,Stock!$B15,'Stk '!D:D) -> 0 | E15: =SUMIF('Stk '!$A:$A,Stock!$B15,'Stk '!E:E) -> 0 | F15: =SUMIF('Stk '!$A:$A,Stock!$B15,'Stk '!F:F) -> 1234703.5 | G15: Due to Vauation method (Weighted Avg Method) impact is there on Closing Balance of 42K
A16: 3 | B16: IT | C16: =SUMIF('Stk '!$A:$A,Stock!$B16,'Stk '!C:C) -> 649724.44 | D16: =SUMIF('Stk '!$A:$A,Stock!$B16,'Stk '!D:D) -> 28434.72 | E16: =SUMIF('Stk '!$A:$A,Stock!$B16,'Stk '!E:E) -> 28434.72 | F16: =SUMIF('Stk '!$A:$A,Stock!$B16,'Stk '!F:F) -> 632858.89
A17: 4 | B17: Spices - Vashi | C17: =SUMIF('Stk '!$A:$A,Stock!$B17,'Stk '!C:C) -> 27267339 | D17: =SUMIF('Stk '!$A:$A,Stock!$B17,'Stk '!D:D) -> 48210916 | E17: =SUMIF('Stk '!$A:$A,Stock!$B17,'Stk '!E:E) -> 75030497 | F17: =SUMIF('Stk '!$A:$A,Stock!$B17,'Stk '!F:F) -> 5589254.9
B18: Total | C18: =SUM(C14:C17) -> 31919797 | D18: =SUM(D14:D17) -> 48239350 | E18: =SUM(E14:E17) -> 75058932 | F18: =SUM(F14:F17) -> 10224847

Sheet Drs_Crs
A1: ='P&L'!A1 -> M J P T & Co LLP
A2: ='P&L'!A2 -> Pristine Worldwide Private Limited
A4: Summary of Sundry Debtors & Sundry Creditors
C5: ='P&L'!L5 -> Mar'26 | H5: ='P&L'!N5 -> (April to Mar)
B6: Sundry Debtor | C6: Opening | D6: Debit | E6: Credit | F6: Closing | H6: Opening | I6: Debit | J6: Credit | K6: Closing
B7: Bluestreak | C7: =SUMIFS('List of Ledgers '!I:I,'List of Ledgers '!$E:$E,Drs_Crs!$B$6,'List of Ledgers '!$G:$G,Drs_Crs!$B7) -> -76286.88 | D7: =SUMIFS('List of Ledgers '!J:J,'List of Ledgers '!$E:$E,Drs_Crs!$B$6,'List of Ledgers '!$G:$G,Drs_Crs!$B7) -> 0 | E7: =SUMIFS('List of Ledgers '!K:K,'List of Ledgers '!$E:$E,Drs_Crs!$B$6,'List of Ledgers '!$G:$G,Drs_Crs!$B7) -> 0 | F7: =SUMIFS('List of Ledgers '!L:L,'List of Ledgers '!$E:$E,Drs_Crs!$B$6,'List of Ledgers '!$G:$G,Drs_Crs!$B7) -> -76286.88 | H7: =SUMIFS('List of Ledgers '!N:N,'List of Ledgers '!$E:$E,Drs_Crs!$B$6,'List of Ledgers '!$G:$G,Drs_Crs!$B7) -> 5361378.8 | I7: =SUMIFS('List of Ledgers '!O:O,'List of Ledgers '!$E:$E,Drs_Crs!$B$6,'List of Ledgers '!$G:$G,Drs_Crs!$B7) -> 10726884 | J7: =SUMIFS('List of Ledgers '!P:P,'List of Ledgers '!$E:$E,Drs_Crs!$B$6,'List of Ledgers '!$G:$G,Drs_Crs!$B7) -> 16164550 | K7: =SUMIFS('List of Ledgers '!Q:Q,'List of Ledgers '!$E:$E,Drs_Crs!$B$6,'List of Ledgers '!$G:$G,Drs_Crs!$B7) -> -76286.88
B8: Clarus | C8: =SUMIFS('List of Ledgers '!I:I,'List of Ledgers '!$E:$E,Drs_Crs!$B$6,'List of Ledgers '!$G:$G,Drs_Crs!$B8) -> -123082.59 | D8: =SUMIFS('List of Ledgers '!J:J,'List of Ledgers '!$E:$E,Drs_Crs!$B$6,'List of Ledgers '!$G:$G,Drs_Crs!$B8) -> 38553 | E8: =SUMIFS('List of Ledgers '!K:K,'List of Ledgers '!$E:$E,Drs_Crs!$B$6,'List of Ledgers '!$G:$G,Drs_Crs!$B8) -> 64788 | F8: =SUMIFS('List of Ledgers '!L:L,'List of Ledgers '!$E:$E,Drs_Crs!$B$6,'List of Ledgers '!$G:$G,Drs_Crs!$B8) -> -149317.59 | H8: =SUMIFS('List of Ledgers '!N:N,'List of Ledgers '!$E:$E,Drs_Crs!$B$6,'List of Ledgers '!$G:$G,Drs_Crs!$B8) -> 132920.87 | I8: =SUMIFS('List of Ledgers '!O:O,'List of Ledgers '!$E:$E,Drs_Crs!$B$6,'List of Ledgers '!$G:$G,Drs_Crs!$B8) -> 1188550 | J8: =SUMIFS('List of Ledgers '!P:P,'List of Ledgers '!$E:$E,Drs_Crs!$B$6,'List of Ledgers '!$G:$G,Drs_Crs!$B8) -> 1470788.5 | K8: =SUMIFS('List of Ledgers '!Q:Q,'List of Ledgers '!$E:$E,Drs_Crs!$B$6,'List of Ledgers '!$G:$G,Drs_Crs!$B8) -> -149317.59
B9: Common | C9: =SUMIFS('List of Ledgers '!I:I,'List of Ledgers '!$E:$E,Drs_Crs!$B$6,'List of Ledgers '!$G:$G,Drs_Crs!$B9) -> 0 | D9: =SUMIFS('List of Ledgers '!J:J,'List of Ledgers '!$E:$E,Drs_Crs!$B$6,'List of Ledgers '!$G:$G,Drs_Crs!$B9) -> 24190000 | E9: =SUMIFS('List of Ledgers '!K:K,'List of Ledgers '!$E:$E,Drs_Crs!$B$6,'List of Ledgers '!$G:$G,Drs_Crs!$B9) -> 24190000 | F9: =SUMIFS('List of Ledgers '!L:L,'List of Ledgers '!$E:$E,Drs_Crs!$B$6,'List of Ledgers '!$G:$G,Drs_Crs!$B9) -> 0 | H9: =SUMIFS('List of Ledgers '!N:N,'List of Ledgers '!$E:$E,Drs_Crs!$B$6,'List of Ledgers '!$G:$G,Drs_Crs!$B9) -> 237010 | I9: =SUMIFS('List of Ledgers '!O:O,'List of Ledgers '!$E:$E,Drs_Crs!$B$6,'List of Ledgers '!$G:$G,Drs_Crs!$B9) -> 24845048 | J9: =SUMIFS('List of Ledgers '!P:P,'List of Ledgers '!$E:$E,Drs_Crs!$B$6,'List of Ledgers '!$G:$G,Drs_Crs!$B9) -> 25082058 | K9: =SUMIFS('List of Ledgers '!Q:Q,'List of Ledgers '!$E:$E,Drs_Crs!$B$6,'List of Ledgers '!$G:$G,Drs_Crs!$B9) -> 0
B10: IT | C10: =SUMIFS('List of Ledgers '!I:I,'List of Ledgers '!$E:$E,Drs_Crs!$B$6,'List of Ledgers '!$G:$G,Drs_Crs!$B10) -> 38958814 | D10: =SUMIFS('List of Ledgers '!J:J,'List of Ledgers '!$E:$E,Drs_Crs!$B$6,'List of Ledgers '!$G:$G,Drs_Crs!$B10) -> 18446903 | E10: =SUMIFS('List of Ledgers '!K:K,'List of Ledgers '!$E:$E,Drs_Crs!$B$6,'List of Ledgers '!$G:$G,Drs_Crs!$B10) -> 40861911 | F10: =SUMIFS('List of Ledgers '!L:L,'List of Ledgers '!$E:$E,Drs_Crs!$B$6,'List of Ledgers '!$G:$G,Drs_Crs!$B10) -> 16543806 | H10: =SUMIFS('List of Ledgers '!N:N,'List of Ledgers '!$E:$E,Drs_Crs!$B$6,'List of Ledgers '!$G:$G,Drs_Crs!$B10) -> 0 | I10: =SUMIFS('List of Ledgers '!O:O,'List of Ledgers '!$E:$E,Drs_Crs!$B$6,'List of Ledgers '!$G:$G,Drs_Crs!$B10) -> 1.301136e+08 | J10: =SUMIFS('List of Ledgers '!P:P,'List of Ledgers '!$E:$E,Drs_Crs!$B$6,'List of Ledgers '!$G:$G,Drs_Crs!$B10) -> 1.135698e+08 | K10: =SUMIFS('List of Ledgers '!Q:Q,'List of Ledgers '!$E:$E,Drs_Crs!$B$6,'List of Ledgers '!$G:$G,Drs_Crs!$B10) -> 16543806
B11: Spices - Vashi | C11: =SUMIFS('List of Ledgers '!I:I,'List of Ledgers '!$E:$E,Drs_Crs!$B$6,'List of Ledgers '!$G:$G,Drs_Crs!$B11) -> 17225917 | D11: =SUMIFS('List of Ledgers '!J:J,'List of Ledgers '!$E:$E,Drs_Crs!$B$6,'List of Ledgers '!$G:$G,Drs_Crs!$B11) -> 58878405 | E11: =SUMIFS('List of Ledgers '!K:K,'List of Ledgers '!$E:$E,Drs_Crs!$B$6,'List of Ledgers '!$G:$G,Drs_Crs!$B11) -> 20579816 | F11: =SUMIFS('List of Ledgers '!L:L,'List of Ledgers '!$E:$E,Drs_Crs!$B$6,'List of Ledgers '!$G:$G,Drs_Crs!$B11) -> 55524506 | H11: =SUMIFS('List of Ledgers '!N:N,'List of Ledgers '!$E:$E,Drs_Crs!$B$6,'List of Ledgers '!$G:$G,Drs_Crs!$B11) -> 0 | I11: =SUMIFS('List of Ledgers '!O:O,'List of Ledgers '!$E:$E,Drs_Crs!$B$6,'List of Ledgers '!$G:$G,Drs_Crs!$B11) -> 1.0736807e+08 | J11: =SUMIFS('List of Ledgers '!P:P,'List of Ledgers '!$E:$E,Drs_Crs!$B$6,'List of Ledgers '!$G:$G,Drs_Crs!$B11) -> 51843559 | K11: =SUMIFS('List of Ledgers '!Q:Q,'List of Ledgers '!$E:$E,Drs_Crs!$B$6,'List of Ledgers '!$G:$G,Drs_Crs!$B11) -> 55524506
B12: Share Trading | C12: =SUMIFS('List of Ledgers '!I:I,'List of Ledgers '!$E:$E,Drs_Crs!$B$6,'List of Ledgers '!$G:$G,Drs_Crs!$B12) -> 0 | D12: =SUMIFS('List of Ledgers '!J:J,'List of Ledgers '!$E:$E,Drs_Crs!$B$6,'List of Ledgers '!$G:$G,Drs_Crs!$B12) -> 0 | E12: =SUMIFS('List of Ledgers '!K:K,'List of Ledgers '!$E:$E,Drs_Crs!$B$6,'List of Ledgers '!$G:$G,Drs_Crs!$B12) -> 0 | F12: =SUMIFS('List of Ledgers '!L:L,'List of Ledgers '!$E:$E,Drs_Crs!$B$6,'List of Ledgers '!$G:$G,Drs_Crs!$B12) -> 0 | H12: =SUMIFS('List of Ledgers '!N:N,'List of Ledgers '!$E:$E,Drs_Crs!$B$6,'List of Ledgers '!$G:$G,Drs_Crs!$B12) -> 0 | I12: =SUMIFS('List of Ledgers '!O:O,'List of Ledgers '!$E:$E,Drs_Crs!$B$6,'List of Ledgers '!$G:$G,Drs_Crs!$B12) -> 0 | J12: =SUMIFS('List of Ledgers '!P:P,'List of Ledgers '!$E:$E,Drs_Crs!$B$6,'List of Ledgers '!$G:$G,Drs_Crs!$B12) -> 0 | K12: =SUMIFS('List of Ledgers '!Q:Q,'List of Ledgers '!$E:$E,Drs_Crs!$B$6,'List of Ledgers '!$G:$G,Drs_Crs!$B12) -> 0
B13: Grand Total | C13: =SUM(C7:C12) -> 55985362 | D13: =SUM(D7:D12) -> 101553861 | E13: =SUM(E7:E12) -> 85696515 | F13: =SUM(F7:F12) -> 71842708 | H13: =SUM(H7:H12) -> 5731309.6 | I13: =SUM(I7:I12) -> 2.7424215e+08 | J13: =SUM(J7:J12) -> 2.0813075e+08 | K13: =SUM(K7:K12) -> 71842708
C15: =C5 -> Mar'26 | H15: =H5 -> (April to Mar)
B16: Sundry Creditor | C16: Opening | D16: Debit | E16: Credit | F16: Closing | H16: Opening | I16: Debit | J16: Credit | K16: Closing
B17: Bluestreak | C17: =SUMIFS('List of Ledgers '!I:I,'List of Ledgers '!$E:$E,Drs_Crs!$B$16,'List of Ledgers '!$G:$G,Drs_Crs!$B17) -> -23961 | D17: =SUMIFS('List of Ledgers '!J:J,'List of Ledgers '!$E:$E,Drs_Crs!$B$16,'List of Ledgers '!$G:$G,Drs_Crs!$B17) -> 0 | E17: =SUMIFS('List of Ledgers '!K:K,'List of Ledgers '!$E:$E,Drs_Crs!$B$16,'List of Ledgers '!$G:$G,Drs_Crs!$B17) -> 0 | F17: =SUMIFS('List of Ledgers '!L:L,'List of Ledgers '!$E:$E,Drs_Crs!$B$16,'List of Ledgers '!$G:$G,Drs_Crs!$B17) -> -23961 | H17: =SUMIFS('List of Ledgers '!N:N,'List of Ledgers '!$E:$E,Drs_Crs!$B$16,'List of Ledgers '!$G:$G,Drs_Crs!$B17) -> -591235.2 | I17: =SUMIFS('List of Ledgers '!O:O,'List of Ledgers '!$E:$E,Drs_Crs!$B$16,'List of Ledgers '!$G:$G,Drs_Crs!$B17) -> 1048133.2 | J17: =SUMIFS('List of Ledgers '!P:P,'List of Ledgers '!$E:$E,Drs_Crs!$B$16,'List of Ledgers '!$G:$G,Drs_Crs!$B17) -> 480859 | K17: =SUMIFS('List of Ledgers '!Q:Q,'List of Ledgers '!$E:$E,Drs_Crs!$B$16,'List of Ledgers '!$G:$G,Drs_Crs!$B17) -> -23961
B18: Clarus | C18: =SUMIFS('List of Ledgers '!I:I,'List of Ledgers '!$E:$E,Drs_Crs!$B$16,'List of Ledgers '!$G:$G,Drs_Crs!$B18) -> 90378 | D18: =SUMIFS('List of Ledgers '!J:J,'List of Ledgers '!$E:$E,Drs_Crs!$B$16,'List of Ledgers '!$G:$G,Drs_Crs!$B18) -> 0 | E18: =SUMIFS('List of Ledgers '!K:K,'List of Ledgers '!$E:$E,Drs_Crs!$B$16,'List of Ledgers '!$G:$G,Drs_Crs!$B18) -> 0 | F18: =SUMIFS('List of Ledgers '!L:L,'List of Ledgers '!$E:$E,Drs_Crs!$B$16,'List of Ledgers '!$G:$G,Drs_Crs!$B18) -> 90378 | H18: =SUMIFS('List of Ledgers '!N:N,'List of Ledgers '!$E:$E,Drs_Crs!$B$16,'List of Ledgers '!$G:$G,Drs_Crs!$B18) -> 88254 | I18: =SUMIFS('List of Ledgers '!O:O,'List of Ledgers '!$E:$E,Drs_Crs!$B$16,'List of Ledgers '!$G:$G,Drs_Crs!$B18) -> 31624 | J18: =SUMIFS('List of Ledgers '!P:P,'List of Ledgers '!$E:$E,Drs_Crs!$B$16,'List of Ledgers '!$G:$G,Drs_Crs!$B18) -> 29500 | K18: =SUMIFS('List of Ledgers '!Q:Q,'List of Ledgers '!$E:$E,Drs_Crs!$B$16,'List of Ledgers '!$G:$G,Drs_Crs!$B18) -> 90378
B19: Common | C19: =SUMIFS('List of Ledgers '!I:I,'List of Ledgers '!$E:$E,Drs_Crs!$B$16,'List of Ledgers '!$G:$G,Drs_Crs!$B19) -> 472714.2 | D19: =SUMIFS('List of Ledgers '!J:J,'List of Ledgers '!$E:$E,Drs_Crs!$B$16,'List of Ledgers '!$G:$G,Drs_Crs!$B19) -> 4742892.2 | E19: =SUMIFS('List of Ledgers '!K:K,'List of Ledgers '!$E:$E,Drs_Crs!$B$16,'List of Ledgers '!$G:$G,Drs_Crs!$B19) -> 4816619.2 | F19: =SUMIFS('List of Ledgers '!L:L,'List of Ledgers '!$E:$E,Drs_Crs!$B$16,'List of Ledgers '!$G:$G,Drs_Crs!$B19) -> 398987.17 | H19: =SUMIFS('List of Ledgers '!N:N,'List of Ledgers '!$E:$E,Drs_Crs!$B$16,'List of Ledgers '!$G:$G,Drs_Crs!$B19) -> -173305.92 | I19: =SUMIFS('List of Ledgers '!O:O,'List of Ledgers '!$E:$E,Drs_Crs!$B$16,'List of Ledgers '!$G:$G,Drs_Crs!$B19) -> 17455616 | J19: =SUMIFS('List of Ledgers '!P:P,'List of Ledgers '!$E:$E,Drs_Crs!$B$16,'List of Ledgers '!$G:$G,Drs_Crs!$B19) -> 16883323 | K19: =SUMIFS('List of Ledgers '!Q:Q,'List of Ledgers '!$E:$E,Drs_Crs!$B$16,'List of Ledgers '!$G:$G,Drs_Crs!$B19) -> 398987.17
B20: IT | C20: =SUMIFS('List of Ledgers '!I:I,'List of Ledgers '!$E:$E,Drs_Crs!$B$16,'List of Ledgers '!$G:$G,Drs_Crs!$B20) -> -285560 | D20: =SUMIFS('List of Ledgers '!J:J,'List of Ledgers '!$E:$E,Drs_Crs!$B$16,'List of Ledgers '!$G:$G,Drs_Crs!$B20) -> 1975347.9 | E20: =SUMIFS('List of Ledgers '!K:K,'List of Ledgers '!$E:$E,Drs_Crs!$B$16,'List of Ledgers '!$G:$G,Drs_Crs!$B20) -> 2260126.9 | F20: =SUMIFS('List of Ledgers '!L:L,'List of Ledgers '!$E:$E,Drs_Crs!$B$16,'List of Ledgers '!$G:$G,Drs_Crs!$B20) -> -570339 | H20: =SUMIFS('List of Ledgers '!N:N,'List of Ledgers '!$E:$E,Drs_Crs!$B$16,'List of Ledgers '!$G:$G,Drs_Crs!$B20) -> -32600 | I20: =SUMIFS('List of Ledgers '!O:O,'List of Ledgers '!$E:$E,Drs_Crs!$B$16,'List of Ledgers '!$G:$G,Drs_Crs!$B20) -> 1.2909711e+08 | J20: =SUMIFS('List of Ledgers '!P:P,'List of Ledgers '!$E:$E,Drs_Crs!$B$16,'List of Ledgers '!$G:$G,Drs_Crs!$B20) -> 1.2963485e+08 | K20: =SUMIFS('List of Ledgers '!Q:Q,'List of Ledgers '!$E:$E,Drs_Crs!$B$16,'List of Ledgers '!$G:$G,Drs_Crs!$B20) -> -570339
B21: Factory | C21: =SUMIFS('List of Ledgers '!I:I,'List of Ledgers '!$E:$E,Drs_Crs!$B$16,'List of Ledgers '!$G:$G,Drs_Crs!$B21) -> 0 | D21: =SUMIFS('List of Ledgers '!J:J,'List of Ledgers '!$E:$E,Drs_Crs!$B$16,'List of Ledgers '!$G:$G,Drs_Crs!$B21) -> 0 | E21: =SUMIFS('List of Ledgers '!K:K,'List of Ledgers '!$E:$E,Drs_Crs!$B$16,'List of Ledgers '!$G:$G,Drs_Crs!$B21) -> 0 | F21: =SUMIFS('List of Ledgers '!L:L,'List of Ledgers '!$E:$E,Drs_Crs!$B$16,'List of Ledgers '!$G:$G,Drs_Crs!$B21) -> 0 | H21: =SUMIFS('List of Ledgers '!N:N,'List of Ledgers '!$E:$E,Drs_Crs!$B$16,'List of Ledgers '!$G:$G,Drs_Crs!$B21) -> 0 | I21: =SUMIFS('List of Ledgers '!O:O,'List of Ledgers '!$E:$E,Drs_Crs!$B$16,'List of Ledgers '!$G:$G,Drs_Crs!$B21) -> 0 | J21: =SUMIFS('List of Ledgers '!P:P,'List of Ledgers '!$E:$E,Drs_Crs!$B$16,'List of Ledgers '!$G:$G,Drs_Crs!$B21) -> 0 | K21: =SUMIFS('List of Ledgers '!Q:Q,'List of Ledgers '!$E:$E,Drs_Crs!$B$16,'List of Ledgers '!$G:$G,Drs_Crs!$B21) -> 0
B22: Office | C22: =SUMIFS('List of Ledgers '!I:I,'List of Ledgers '!$E:$E,Drs_Crs!$B$16,'List of Ledgers '!$G:$G,Drs_Crs!$B22) -> 0 | D22: =SUMIFS('List of Ledgers '!J:J,'List of Ledgers '!$E:$E,Drs_Crs!$B$16,'List of Ledgers '!$G:$G,Drs_Crs!$B22) -> 0 | E22: =SUMIFS('List of Ledgers '!K:K,'List of Ledgers '!$E:$E,Drs_Crs!$B$16,'List of Ledgers '!$G:$G,Drs_Crs!$B22) -> 0 | F22: =SUMIFS('List of Ledgers '!L:L,'List of Ledgers '!$E:$E,Drs_Crs!$B$16,'List of Ledgers '!$G:$G,Drs_Crs!$B22) -> 0 | H22: =SUMIFS('List of Ledgers '!N:N,'List of Ledgers '!$E:$E,Drs_Crs!$B$16,'List of Ledgers '!$G:$G,Drs_Crs!$B22) -> 0 | I22: =SUMIFS('List of Ledgers '!O:O,'List of Ledgers '!$E:$E,Drs_Crs!$B$16,'List of Ledgers '!$G:$G,Drs_Crs!$B22) -> 0 | J22: =SUMIFS('List of Ledgers '!P:P,'List of Ledgers '!$E:$E,Drs_Crs!$B$16,'List of Ledgers '!$G:$G,Drs_Crs!$B22) -> 0 | K22: =SUMIFS('List of Ledgers '!Q:Q,'List of Ledgers '!$E:$E,Drs_Crs!$B$16,'List of Ledgers '!$G:$G,Drs_Crs!$B22) -> 0
B23: Share Trading | C23: =SUMIFS('List of Ledgers '!I:I,'List of Ledgers '!$E:$E,Drs_Crs!$B$16,'List of Ledgers '!$G:$G,Drs_Crs!$B23) -> 0 | D23: =SUMIFS('List of Ledgers '!J:J,'List of Ledgers '!$E:$E,Drs_Crs!$B$16,'List of Ledgers '!$G:$G,Drs_Crs!$B23) -> 0 | E23: =SUMIFS('List of Ledgers '!K:K,'List of Ledgers '!$E:$E,Drs_Crs!$B$16,'List of Ledgers '!$G:$G,Drs_Crs!$B23) -> 0 | F23: =SUMIFS('List of Ledgers '!L:L,'List of Ledgers '!$E:$E,Drs_Crs!$B$16,'List of Ledgers '!$G:$G,Drs_Crs!$B23) -> 0 | H23: =SUMIFS('List of Ledgers '!N:N,'List of Ledgers '!$E:$E,Drs_Crs!$B$16,'List of Ledgers '!$G:$G,Drs_Crs!$B23) -> 0 | I23: =SUMIFS('List of Ledgers '!O:O,'List of Ledgers '!$E:$E,Drs_Crs!$B$16,'List of Ledgers '!$G:$G,Drs_Crs!$B23) -> 0 | J23: =SUMIFS('List of Ledgers '!P:P,'List of Ledgers '!$E:$E,Drs_Crs!$B$16,'List of Ledgers '!$G:$G,Drs_Crs!$B23) -> 0 | K23: =SUMIFS('List of Ledgers '!Q:Q,'List of Ledgers '!$E:$E,Drs_Crs!$B$16,'List of Ledgers '!$G:$G,Drs_Crs!$B23) -> 0
B24: Spices - Vashi | C24: =SUMIFS('List of Ledgers '!I:I,'List of Ledgers '!$E:$E,Drs_Crs!$B$16,'List of Ledgers '!$G:$G,Drs_Crs!$B24) -> -7457070.7 | D24: =SUMIFS('List of Ledgers '!J:J,'List of Ledgers '!$E:$E,Drs_Crs!$B$16,'List of Ledgers '!$G:$G,Drs_Crs!$B24) -> 52239220 | E24: =SUMIFS('List of Ledgers '!K:K,'List of Ledgers '!$E:$E,Drs_Crs!$B$16,'List of Ledgers '!$G:$G,Drs_Crs!$B24) -> 49939871 | F24: =SUMIFS('List of Ledgers '!L:L,'List of Ledgers '!$E:$E,Drs_Crs!$B$16,'List of Ledgers '!$G:$G,Drs_Crs!$B24) -> -5157720.7 | H24: =SUMIFS('List of Ledgers '!N:N,'List of Ledgers '!$E:$E,Drs_Crs!$B$16,'List of Ledgers '!$G:$G,Drs_Crs!$B24) -> 0 | I24: =SUMIFS('List of Ledgers '!O:O,'List of Ledgers '!$E:$E,Drs_Crs!$B$16,'List of Ledgers '!$G:$G,Drs_Crs!$B24) -> 1.1849314e+08 | J24: =SUMIFS('List of Ledgers '!P:P,'List of Ledgers '!$E:$E,Drs_Crs!$B$16,'List of Ledgers '!$G:$G,Drs_Crs!$B24) -> 1.2365086e+08 | K24: =SUMIFS('List of Ledgers '!Q:Q,'List of Ledgers '!$E:$E,Drs_Crs!$B$16,'List of Ledgers '!$G:$G,Drs_Crs!$B24) -> -5157720.7
B25: Grand Total | C25: =SUM(C17:C24) -> -7203499.5 | D25: =SUM(D17:D24) -> 58957461 | E25: =SUM(E17:E24) -> 57016617 | F25: =SUM(F17:F24) -> -5262655.6 | H25: =SUM(H17:H24) -> -708887.12 | I25: =SUM(I17:I24) -> 2.6612563e+08 | J25: =SUM(J17:J24) -> 2.706794e+08 | K25: =SUM(K17:K24) -> -5262655.6
A27: List of Debtors | C27: =C5 -> Mar'26 | H27: =H5 -> (April to Mar)
A28: Sundry Debtor | B28: Business Verticle | C28: Opening | D28: Debit | E28: Credit | F28: Closing | G28: xxx | H28: Opening YTD | I28: Debit YTD | J28: Credit YTD | K28: Closing YTD
A29: ABHA PRINTERS & STATIONERS | B29: =VLOOKUP(A29,'List of Ledgers '!B:G,6,0) -> Bluestreak | C29: =SUMIFS('List of Ledgers '!I:I,'List of Ledgers '!$E:$E,Drs_Crs!$A$28,'List of Ledgers '!$B:$B,Drs_Crs!$A29) -> 0 | D29: =SUMIFS('List of Ledgers '!J:J,'List of Ledgers '!$E:$E,Drs_Crs!$A$28,'List of Ledgers '!$B:$B,Drs_Crs!$A29) -> 0 | E29: =SUMIFS('List of Ledgers '!K:K,'List of Ledgers '!$E:$E,Drs_Crs!$A$28,'List of Ledgers '!$B:$B,Drs_Crs!$A29) -> 0 | F29: =SUMIFS('List of Ledgers '!L:L,'List of Ledgers '!$E:$E,Drs_Crs!$A$28,'List of Ledgers '!$B:$B,Drs_Crs!$A29) -> 0 | H29: =SUMIFS('List of Ledgers '!N:N,'List of Ledgers '!$E:$E,Drs_Crs!$A$28,'List of Ledgers '!$B:$B,Drs_Crs!$A29) -> 0 | I29: =SUMIFS('List of Ledgers '!O:O,'List of Ledgers '!$E:$E,Drs_Crs!$A$28,'List of Ledgers '!$B:$B,Drs_Crs!$A29) -> 0 | J29: =SUMIFS('List of Ledgers '!P:P,'List of Ledgers '!$E:$E,Drs_Crs!$A$28,'List of Ledgers '!$B:$B,Drs_Crs!$A29) -> 0 | K29: =SUMIFS('List of Ledgers '!Q:Q,'List of Ledgers '!$E:$E,Drs_Crs!$A$28,'List of Ledgers '!$B:$B,Drs_Crs!$A29) -> 0
A30: Abhay Infotech | B30: =VLOOKUP(A30,'List of Ledgers '!B:G,6,0) -> Bluestreak | C30: =SUMIFS('List of Ledgers '!I:I,'List of Ledgers '!$E:$E,Drs_Crs!$A$28,'List of Ledgers '!$B:$B,Drs_Crs!$A30) -> 0 | D30: =SUMIFS('List of Ledgers '!J:J,'List of Ledgers '!$E:$E,Drs_Crs!$A$28,'List of Ledgers '!$B:$B,Drs_Crs!$A30) -> 0 | E30: =SUMIFS('List of Ledgers '!K:K,'List of Ledgers '!$E:$E,Drs_Crs!$A$28,'List of Ledgers '!$B:$B,Drs_Crs!$A30) -> 0 | F30: =SUMIFS('List of Ledgers '!L:L,'List of Ledgers '!$E:$E,Drs_Crs!$A$28,'List of Ledgers '!$B:$B,Drs_Crs!$A30) -> 0 | H30: =SUMIFS('List of Ledgers '!N:N,'List of Ledgers '!$E:$E,Drs_Crs!$A$28,'List of Ledgers '!$B:$B,Drs_Crs!$A30) -> 0 | I30: =SUMIFS('List of Ledgers '!O:O,'List of Ledgers '!$E:$E,Drs_Crs!$A$28,'List of Ledgers '!$B:$B,Drs_Crs!$A30) -> 0 | J30: =SUMIFS('List of Ledgers '!P:P,'List of Ledgers '!$E:$E,Drs_Crs!$A$28,'List of Ledgers '!$B:$B,Drs_Crs!$A30) -> 0 | K30: =SUMIFS('List of Ledgers '!Q:Q,'List of Ledgers '!$E:$E,Drs_Crs!$A$28,'List of Ledgers '!$B:$B,Drs_Crs!$A30) -> 0
A31: Add on Enterprises | B31: =VLOOKUP(A31,'List of Ledgers '!B:G,6,0) -> Bluestreak | C31: =SUMIFS('List of Ledgers '!I:I,'List of Ledgers '!$E:$E,Drs_Crs!$A$28,'List of Ledgers '!$B:$B,Drs_Crs!$A31) -> 79762.52 | D31: =SUMIFS('List of Ledgers '!J:J,'List of Ledgers '!$E:$E,Drs_Crs!$A$28,'List of Ledgers '!$B:$B,Drs_Crs!$A31) -> 0 | E31: =SUMIFS('List of Ledgers '!K:K,'List of Ledgers '!$E:$E,Drs_Crs!$A$28,'List of Ledgers '!$B:$B,Drs_Crs!$A31) -> 0 | F31: =SUMIFS('List of Ledgers '!L:L,'List of Ledgers '!$E:$E,Drs_Crs!$A$28,'List of Ledgers '!$B:$B,Drs_Crs!$A31) -> 79762.52 | G31: Op Bal | H31: =SUMIFS('List of Ledgers '!N:N,'List of Ledgers '!$E:$E,Drs_Crs!$A$28,'List of Ledgers '!$B:$B,Drs_Crs!$A31) -> 79762.52 | I31: =SUMIFS('List of Ledgers '!O:O,'List of Ledgers '!$E:$E,Drs_Crs!$A$28,'List of Ledgers '!$B:$B,Drs_Crs!$A31) -> 0 | J31: =SUMIFS('List of Ledgers '!P:P,'List of Ledgers '!$E:$E,Drs_Crs!$A$28,'List of Ledgers '!$B:$B,Drs_Crs!$A31) -> 0 | K31: =SUMIFS('List of Ledgers '!Q:Q,'List of Ledgers '!$E:$E,Drs_Crs!$A$28,'List of Ledgers '!$B:$B,Drs_Crs!$A31) -> 79762.52
A32: Advhika Enterprises | B32: =VLOOKUP(A32,'List of Ledgers '!B:G,6,0) -> Bluestreak | C32: =SUMIFS('List of Ledgers '!I:I,'List of Ledgers '!$E:$E,Drs_Crs!$A$28,'List of Ledgers '!$B:$B,Drs_Crs!$A32) -> 0 | D32: =SUMIFS('List of Ledgers '!J:J,'List of Ledgers '!$E:$E,Drs_Crs!$A$28,'List of Ledgers '!$B:$B,Drs_Crs!$A32) -> 0 | E32: =SUMIFS('List of Ledgers '!K:K,'List of Ledgers '!$E:$E,Drs_Crs!$A$28,'List of Ledgers '!$B:$B,Drs_Crs!$A32) -> 0 | F32: =SUMIFS('List of Ledgers '!L:L,'List of Ledgers '!$E:$E,Drs_Crs!$A$28,'List of Ledgers '!$B:$B,Drs_Crs!$A32) -> 0 | H32: =SUMIFS('List of Ledgers '!N:N,'List of Ledgers '!$E:$E,Drs_Crs!$A$28,'List of Ledgers '!$B:$B,Drs_Crs!$A32) -> 0 | I32: =SUMIFS('List of Ledgers '!O:O,'List of Ledgers '!$E:$E,Drs_Crs!$A$28,'List of Ledgers '!$B:$B,Drs_Crs!$A32) -> 15741 | J32: =SUMIFS('List of Ledgers '!P:P,'List of Ledgers '!$E:$E,Drs_Crs!$A$28,'List of Ledgers '!$B:$B,Drs_Crs!$A32) -> 15741 | K32: =SUMIFS('List of Ledgers '!Q:Q,'List of Ledgers '!$E:$E,Drs_Crs!$A$28,'List of Ledgers '!$B:$B,Drs_Crs!$A32) -> 0
A33: Always Marketing | B33: =VLOOKUP(A33,'List of Ledgers '!B:G,6,0) -> Bluestreak | C33: =SUMIFS('List of Ledgers '!I:I,'List of Ledgers '!$E:$E,Drs_Crs!$A$28,'List of Ledgers '!$B:$B,Drs_Crs!$A33) -> 0 | D33: =SUMIFS('List of Ledgers '!J:J,'List of Ledgers '!$E:$E,Drs_Crs!$A$28,'List of Ledgers '!$B:$B,Drs_Crs!$A33) -> 0 | E33: =SUMIFS('List of Ledgers '!K:K,'List of Ledgers '!$E:$E,Drs_Crs!$A$28,'List of Ledgers '!$B:$B,Drs_Crs!$A33) -> 0 | F33: =SUMIFS('List of Ledgers '!L:L,'List of Ledgers '!$E:$E,Drs_Crs!$A$28,'List of Ledgers '!$B:$B,Drs_Crs!$A33) -> 0 | H33: =SUMIFS('List of Ledgers '!N:N,'List of Ledgers '!$E:$E,Drs_Crs!$A$28,'List of Ledgers '!$B:$B,Drs_Crs!$A33) -> 0 | I33: =SUMIFS('List of Ledgers '!O:O,'List of Ledgers '!$E:$E,Drs_Crs!$A$28,'List of Ledgers '!$B:$B,Drs_Crs!$A33) -> 0 | J33: =SUMIFS('List of Ledgers '!P:P,'List of Ledgers '!$E:$E,Drs_Crs!$A$28,'List of Ledgers '!$B:$B,Drs_Crs!$A33) -> 0 | K33: =SUMIFS('List of Ledgers '!Q:Q,'List of Ledgers '!$E:$E,Drs_Crs!$A$28,'List of Ledgers '!$B:$B,Drs_Crs!$A33) -> 0
A34: Amba Agencies | B34: =VLOOKUP(A34,'List of Ledgers '!B:G,6,0) -> Clarus | C34: =SUMIFS('List of Ledgers '!I:I,'List of Ledgers '!$E:$E,Drs_Crs!$A$28,'List of Ledgers '!$B:$B,Drs_Crs!$A34) -> 0 | D34: =SUMIFS('List of Ledgers '!J:J,'List of Ledgers '!$E:$E,Drs_Crs!$A$28,'List of Ledgers '!$B:$B,Drs_Crs!$A34) -> 0 | E34: =SUMIFS('List of Ledgers '!K:K,'List of Ledgers '!$E:$E,Drs_Crs!$A$28,'List of Ledgers '!$B:$B,Drs_Crs!$A34) -> 0 | F34: =SUMIFS('List of Ledgers '!L:L,'List of Ledgers '!$E:$E,Drs_Crs!$A$28,'List of Ledgers '!$B:$B,Drs_Crs!$A34) -> 0 | H34: =SUMIFS('List of Ledgers '!N:N,'List of Ledgers '!$E:$E,Drs_Crs!$A$28,'List of Ledgers '!$B:$B,Drs_Crs!$A34) -> 0 | I34: =SUMIFS('List of Ledgers '!O:O,'List of Ledgers '!$E:$E,Drs_Crs!$A$28,'List of Ledgers '!$B:$B,Drs_Crs!$A34) -> 31288 | J34: =SUMIFS('List of Ledgers '!P:P,'List of Ledgers '!$E:$E,Drs_Crs!$A$28,'List of Ledgers '!$B:$B,Drs_Crs!$A34) -> 31288 | K34: =SUMIFS('List of Ledgers '!Q:Q,'List of Ledgers '!$E:$E,Drs_Crs!$A$28,'List of Ledgers '!$B:$B,Drs_Crs!$A34) -> 0
A35: Ambrish Typing Institute | B35: =VLOOKUP(A35,'List of Ledgers '!B:G,6,0) -> Bluestreak | C35: =SUMIFS('List of Ledgers '!I:I,'List of Ledgers '!$E:$E,Drs_Crs!$A$28,'List of Ledgers '!$B:$B,Drs_Crs!$A35) -> 0 | D35: =SUMIFS('List of Ledgers '!J:J,'List of Ledgers '!$E:$E,Drs_Crs!$A$28,'List of Ledgers '!$B:$B,Drs_Crs!$A35) -> 0 | E35: =SUMIFS('List of Ledgers '!K:K,'List of Ledgers '!$E:$E,Drs_Crs!$A$28,'List of Ledgers '!$B:$B,Drs_Crs!$A35) -> 0 | F35: =SUMIFS('List of Ledgers '!L:L,'List of Ledgers '!$E:$E,Drs_Crs!$A$28,'List of Ledgers '!$B:$B,Drs_Crs!$A35) -> 0 | H35: =SUMIFS('List of Ledgers '!N:N,'List of Ledgers '!$E:$E,Drs_Crs!$A$28,'List of Ledgers '!$B:$B,Drs_Crs!$A35) -> 0 | I35: =SUMIFS('List of Ledgers '!O:O,'List of Ledgers '!$E:$E,Drs_Crs!$A$28,'List of Ledgers '!$B:$B,Drs_Crs!$A35) -> 0 | J35: =SUMIFS('List of Ledgers '!P:P,'List of Ledgers '!$E:$E,Drs_Crs!$A$28,'List of Ledgers '!$B:$B,Drs_Crs!$A35) -> 0 | K35: =SUMIFS('List of Ledgers '!Q:Q,'List of Ledgers '!$E:$E,Drs_Crs!$A$28,'List of Ledgers '!$B:$B,Drs_Crs!$A35) -> 0
A36: Anjali Traders | B36: =VLOOKUP(A36,'List of Ledgers '!B:G,6,0) -> Bluestreak | C36: =SUMIFS('List of Ledgers '!I:I,'List of Ledgers '!$E:$E,Drs_Crs!$A$28,'List of Ledgers '!$B:$B,Drs_Crs!$A36) -> 0 | D36: =SUMIFS('List of Ledgers '!J:J,'List of Ledgers '!$E:$E,Drs_Crs!$A$28,'List of Ledgers '!$B:$B,Drs_Crs!$A36) -> 0 | E36: =SUMIFS('List of Ledgers '!K:K,'List of Ledgers '!$E:$E,Drs_Crs!$A$28,'List of Ledgers '!$B:$B,Drs_Crs!$A36) -> 0 | F36: =SUMIFS('List of Ledgers '!L:L,'List of Ledgers '!$E:$E,Drs_Crs!$A$28,'List of Ledgers '!$B:$B,Drs_Crs!$A36) -> 0 | H36: =SUMIFS('List of Ledgers '!N:N,'List of Ledgers '!$E:$E,Drs_Crs!$A$28,'List of Ledgers '!$B:$B,Drs_Crs!$A36) -> 0 | I36: =SUMIFS('List of Ledgers '!O:O,'List of Ledgers '!$E:$E,Drs_Crs!$A$28,'List of Ledgers '!$B:$B,Drs_Crs!$A36) -> 0 | J36: =SUMIFS('List of Ledgers '!P:P,'List of Ledgers '!$E:$E,Drs_Crs!$A$28,'List of Ledgers '!$B:$B,Drs_Crs!$A36) -> 0 | K36: =SUMIFS('List of Ledgers '!Q:Q,'List of Ledgers '!$E:$E,Drs_Crs!$A$28,'List of Ledgers '!$B:$B,Drs_Crs!$A36) -> 0
A37: Anshu Printer | B37: =VLOOKUP(A37,'List of Ledgers '!B:G,6,0) -> Bluestreak | C37: =SUMIFS('List of Ledgers '!I:I,'List of Ledgers '!$E:$E,Drs_Crs!$A$28,'List of Ledgers '!$B:$B,Drs_Crs!$A37) -> 0 | D37: =SUMIFS('List of Ledgers '!J:J,'List of Ledgers '!$E:$E,Drs_Crs!$A$28,'List of Ledgers '!$B:$B,Drs_Crs!$A37) -> 0 | E37: =SUMIFS('List of Ledgers '!K:K,'List of Ledgers '!$E:$E,Drs_Crs!$A$28,'List of Ledgers '!$B:$B,Drs_Crs!$A37) -> 0 | F37: =SUMIFS('List of Ledgers '!L:L,'List of Ledgers '!$E:$E,Drs_Crs!$A$28,'List of Ledgers '!$B:$B,Drs_Crs!$A37) -> 0 | H37: =SUMIFS('List of Ledgers '!N:N,'List of Ledgers '!$E:$E,Drs_Crs!$A$28,'List of Ledgers '!$B:$B,Drs_Crs!$A37) -> 0 | I37: =SUMIFS('List of Ledgers '!O:O,'List of Ledgers '!$E:$E,Drs_Crs!$A$28,'List of Ledgers '!$B:$B,Drs_Crs!$A37) -> 0 | J37: =SUMIFS('List of Ledgers '!P:P,'List of Ledgers '!$E:$E,Drs_Crs!$A$28,'List of Ledgers '!$B:$B,Drs_Crs!$A37) -> 0 | K37: =SUMIFS('List of Ledgers '!Q:Q,'List of Ledgers '!$E:$E,Drs_Crs!$A$28,'List of Ledgers '!$B:$B,Drs_Crs!$A37) -> 0
A38: ARYAN ALLIANCE INDIA PVT. LTD | B38: =VLOOKUP(A38,'List of Ledgers '!B:G,6,0) -> Bluestreak | C38: =SUMIFS('List of Ledgers '!I:I,'List of Ledgers '!$E:$E,Drs_Crs!$A$28,'List of Ledgers '!$B:$B,Drs_Crs!$A38) -> 0 | D38: =SUMIFS('List of Ledgers '!J:J,'List of Ledgers '!$E:$E,Drs_Crs!$A$28,'List of Ledgers '!$B:$B,Drs_Crs!$A38) -> 0 | E38: =SUMIFS('List of Ledgers '!K:K,'List of Ledgers '!$E:$E,Drs_Crs!$A$28,'List of Ledgers '!$B:$B,Drs_Crs!$A38) -> 0 | F38: =SUMIFS('List of Ledgers '!L:L,'List of Ledgers '!$E:$E,Drs_Crs!$A$28,'List of Ledgers '!$B:$B,Drs_Crs!$A38) -> 0 | H38: =SUMIFS('List of Ledgers '!N:N,'List of Ledgers '!$E:$E,Drs_Crs!$A$28,'List of Ledgers '!$B:$B,Drs_Crs!$A38) -> 0 | I38: =SUMIFS('List of Ledgers '!O:O,'List of Ledgers '!$E:$E,Drs_Crs!$A$28,'List of Ledgers '!$B:$B,Drs_Crs!$A38) -> 0 | J38: =SUMIFS('List of Ledgers '!P:P,'List of Ledgers '!$E:$E,Drs_Crs!$A$28,'List of Ledgers '!$B:$B,Drs_Crs!$A38) -> 0 | K38: =SUMIFS('List of Ledgers '!Q:Q,'List of Ledgers '!$E:$E,Drs_Crs!$A$28,'List of Ledgers '!$B:$B,Drs_Crs!$A38) -> 0
A39: Aryan Facilities | B39: =VLOOKUP(A39,'List of Ledgers '!B:G,6,0) -> Bluestreak | C39: =SUMIFS('List of Ledgers '!I:I,'List of Ledgers '!$E:$E,Drs_Crs!$A$28,'List of Ledgers '!$B:$B,Drs_Crs!$A39) -> 0 | D39: =SUMIFS('List of Ledgers '!J:J,'List of Ledgers '!$E:$E,Drs_Crs!$A$28,'List of Ledgers '!$B:$B,Drs_Crs!$A39) -> 0 | E39: =SUMIFS('List of Ledgers '!K:K,'List of Ledgers '!$E:$E,Drs_Crs!$A$28,'List of Ledgers '!$B:$B,Drs_Crs!$A39) -> 0 | F39: =SUMIFS('List of Ledgers '!L:L,'List of Ledgers '!$E:$E,Drs_Crs!$A$28,'List of Ledgers '!$B:$B,Drs_Crs!$A39) -> 0 | H39: =SUMIFS('List of Ledgers '!N:N,'List of Ledgers '!$E:$E,Drs_Crs!$A$28,'List of Ledgers '!$B:$B,Drs_Crs!$A39) -> 0 | I39: =SUMIFS('List of Ledgers '!O:O,'List of Ledgers '!$E:$E,Drs_Crs!$A$28,'List of Ledgers '!$B:$B,Drs_Crs!$A39) -> 0 | J39: =SUMIFS('List of Ledgers '!P:P,'List of Ledgers '!$E:$E,Drs_Crs!$A$28,'List of Ledgers '!$B:$B,Drs_Crs!$A39) -> 0 | K39: =SUMIFS('List of Ledgers '!Q:Q,'List of Ledgers '!$E:$E,Drs_Crs!$A$28,'List of Ledgers '!$B:$B,Drs_Crs!$A39) -> 0
A40: Ashapura Agency | B40: =VLOOKUP(A40,'List of Ledgers '!B:G,6,0) -> Clarus | C40: =SUMIFS('List of Ledgers '!I:I,'List of Ledgers '!$E:$E,Drs_Crs!$A$28,'List of Ledgers '!$B:$B,Drs_Crs!$A40) -> 0 | D40: =SUMIFS('List of Ledgers '!J:J,'List of Ledgers '!$E:$E,Drs_Crs!$A$28,'List of Ledgers '!$B:$B,Drs_Crs!$A40) -> 0 | E40: =SUMIFS('List of Ledgers '!K:K,'List of Ledgers '!$E:$E,Drs_Crs!$A$28,'List of Ledgers '!$B:$B,Drs_Crs!$A40) -> 0 | F40: =SUMIFS('List of Ledgers '!L:L,'List of Ledgers '!$E:$E,Drs_Crs!$A$28,'List of Ledgers '!$B:$B,Drs_Crs!$A40) -> 0 | H40: =SUMIFS('List of Ledgers '!N:N,'List of Ledgers '!$E:$E,Drs_Crs!$A$28,'List of Ledgers '!$B:$B,Drs_Crs!$A40) -> 0 | I40: =SUMIFS('List of Ledgers '!O:O,'List of Ledgers '!$E:$E,Drs_Crs!$A$28,'List of Ledgers '!$B:$B,Drs_Crs!$A40) -> 21902 | J40: =SUMIFS('List of Ledgers '!P:P,'List of Ledgers '!$E:$E,Drs_Crs!$A$28,'List of Ledgers '!$B:$B,Drs_Crs!$A40) -> 21902 | K40: =SUMIFS('List of Ledgers '!Q:Q,'List of Ledgers '!$E:$E,Drs_Crs!$A$28,'List of Ledgers '!$B:$B,Drs_Crs!$A40) -> 0
A41: Aznelle Naturals Private Limited | B41: =VLOOKUP(A41,'List of Ledgers '!B:G,6,0) -> Clarus | C41: =SUMIFS('List of Ledgers '!I:I,'List of Ledgers '!$E:$E,Drs_Crs!$A$28,'List of Ledgers '!$B:$B,Drs_Crs!$A41) -> -229554.44 | D41: =SUMIFS('List of Ledgers '!J:J,'List of Ledgers '!$E:$E,Drs_Crs!$A$28,'List of Ledgers '!$B:$B,Drs_Crs!$A41) -> 5000 | E41: =SUMIFS('List of Ledgers '!K:K,'List of Ledgers '!$E:$E,Drs_Crs!$A$28,'List of Ledgers '!$B:$B,Drs_Crs!$A41) -> 38553 | F41: =SUMIFS('List of Ledgers '!L:L,'List of Ledgers '!$E:$E,Drs_Crs!$A$28,'List of Ledgers '!$B:$B,Drs_Crs!$A41) -> -263107.44 | H41: =SUMIFS('List of Ledgers '!N:N,'List of Ledgers '!$E:$E,Drs_Crs!$A$28,'List of Ledgers '!$B:$B,Drs_Crs!$A41) -> 0 | I41: =SUMIFS('List of Ledgers '!O:O,'List of Ledgers '!$E:$E,Drs_Crs!$A$28,'List of Ledgers '!$B:$B,Drs_Crs!$A41) -> 136962 | J41: =SUMIFS('List of Ledgers '!P:P,'List of Ledgers '!$E:$E,Drs_Crs!$A$28,'List of Ledgers '!$B:$B,Drs_Crs!$A41) -> 400069.44 | K41: =SUMIFS('List of Ledgers '!Q:Q,'List of Ledgers '!$E:$E,Drs_Crs!$A$28,'List of Ledgers '!$B:$B,Drs_Crs!$A41) -> -263107.44
A42: Beriwal Computers & Mobile | B42: =VLOOKUP(A42,'List of Ledgers '!B:G,6,0) -> Bluestreak | C42: =SUMIFS('List of Ledgers '!I:I,'List of Ledgers '!$E:$E,Drs_Crs!$A$28,'List of Ledgers '!$B:$B,Drs_Crs!$A42) -> 0 | D42: =SUMIFS('List of Ledgers '!J:J,'List of Ledgers '!$E:$E,Drs_Crs!$A$28,'List of Ledgers '!$B:$B,Drs_Crs!$A42) -> 0 | E42: =SUMIFS('List of Ledgers '!K:K,'List of Ledgers '!$E:$E,Drs_Crs!$A$28,'List of Ledgers '!$B:$B,Drs_Crs!$A42) -> 0 | F42: =SUMIFS('List of Ledgers '!L:L,'List of Ledgers '!$E:$E,Drs_Crs!$A$28,'List of Ledgers '!$B:$B,Drs_Crs!$A42) -> 0 | H42: =SUMIFS('List of Ledgers '!N:N,'List of Ledgers '!$E:$E,Drs_Crs!$A$28,'List of Ledgers '!$B:$B,Drs_Crs!$A42) -> 0 | I42: =SUMIFS('List of Ledgers '!O:O,'List of Ledgers '!$E:$E,Drs_Crs!$A$28,'List of Ledgers '!$B:$B,Drs_Crs!$A42) -> 0 | J42: =SUMIFS('List of Ledgers '!P:P,'List of Ledgers '!$E:$E,Drs_Crs!$A$28,'List of Ledgers '!$B:$B,Drs_Crs!$A42) -> 0 | K42: =SUMIFS('List of Ledgers '!Q:Q,'List of Ledgers '!$E:$E,Drs_Crs!$A$28,'List of Ledgers '!$B:$B,Drs_Crs!$A42) -> 0
A43: Bhagwandas Sons | B43: =VLOOKUP(A43,'List of Ledgers '!B:G,6,0) -> Clarus | C43: =SUMIFS('List of Ledgers '!I:I,'List of Ledgers '!$E:$E,Drs_Crs!$A$28,'List of Ledgers '!$B:$B,Drs_Crs!$A43) -> 0 | D43: =SUMIFS('List of Ledgers '!J:J,'List of Ledgers '!$E:$E,Drs_Crs!$A$28,'List of Ledgers '!$B:$B,Drs_Crs!$A43) -> 0 | E43: =SUMIFS('List of Ledgers '!K:K,'List of Ledgers '!$E:$E,Drs_Crs!$A$28,'List of Ledgers '!$B:$B,Drs_Crs!$A43) -> 0 | F43: =SUMIFS('List of Ledgers '!L:L,'List of Ledgers '!$E:$E,Drs_Crs!$A$28,'List of Ledgers '!$B:$B,Drs_Crs!$A43) -> 0 | H43: =SUMIFS('List of Ledgers '!N:N,'List of Ledgers '!$E:$E,Drs_Crs!$A$28,'List of Ledgers '!$B:$B,Drs_Crs!$A43) -> 0 | I43: =SUMIFS('List of Ledgers '!O:O,'List of Ledgers '!$E:$E,Drs_Crs!$A$28,'List of Ledgers '!$B:$B,Drs_Crs!$A43) -> 21902 | J43: =SUMIFS('List of Ledgers '!P:P,'List of Ledgers '!$E:$E,Drs_Crs!$A$28,'List of Ledgers '!$B:$B,Drs_Crs!$A43) -> 21902 | K43: =SUMIFS('List of Ledgers '!Q:Q,'List of Ledgers '!$E:$E,Drs_Crs!$A$28,'List of Ledgers '!$B:$B,Drs_Crs!$A43) -> 0
... A47: Cabletronics | B47: =VLOOKUP(A47,'List of Ledgers '!B:G,6,0) -> Bluestreak | C47: =SUMIFS('List of Ledgers '!I:I,'List of Ledgers '!$E:$E,Drs_Crs!$A$28,'List of Ledgers '!$B:$B,Drs_Crs!$A47) -> -1768 | D47: =SUMIFS('List of Ledgers '!J:J,'List of Ledgers '!$E:$E,Drs_Crs!$A$28,'List of Ledgers '!$B:$B,Drs_Crs!$A47) -> 0 | E47: =SUMIFS('List of Ledgers '!K:K,'List of Ledgers '!$E:$E,Drs_Crs!$A$28,'List of Ledgers '!$B:$B,Drs_Crs!$A47) -> 0 | F47: =SUMIFS('List of Ledgers '!L:L,'List of Ledgers '!$E:$E,Drs_Crs!$A$28,'List of Ledgers '!$B:$B,Drs_Crs!$A47) -> -1768 | H47: =SUMIFS('List of Ledgers '!N:N,'List of Ledgers '!$E:$E,Drs_Crs!$A$28,'List of Ledgers '!$B:$B,Drs_Crs!$A47) -> 164376 | I47: =SUMIFS('List of Ledgers '!O:O,'List of Ledgers '!$E:$E,Drs_Crs!$A$28,'List of Ledgers '!$B:$B,Drs_Crs!$A47) -> 247191 | J47: =SUMIFS('List of Ledgers '!P:P,'List of Ledgers '!$E:$E,Drs_Crs!$A$28,'List of Ledgers '!$B:$B,Drs_Crs!$A47) -> 413335 | K47: =SUMIFS('List of Ledgers '!Q:Q,'List of Ledgers '!$E:$E,Drs_Crs!$A$28,'List of Ledgers '!$B:$B,Drs_Crs!$A47) -> -1768
A48: Computer & Cartridge Point | B48: =VLOOKUP(A48,'List of Ledgers '!B:G,6,0) -> Bluestreak | C48: =SUMIFS('List of Ledgers '!I:I,'List of Ledgers '!$E:$E,Drs_Crs!$A$28,'List of Ledgers '!$B:$B,Drs_Crs!$A48) -> 26597 | D48: =SUMIFS('List of Ledgers '!J:J,'List of Ledgers '!$E:$E,Drs_Crs!$A$28,'List of Ledgers '!$B:$B,Drs_Crs!$A48) -> 0 | E48: =SUMIFS('List of Ledgers '!K:K,'List of Ledgers '!$E:$E,Drs_Crs!$A$28,'List of Ledgers '!$B:$B,Drs_Crs!$A48) -> 0 | F48: =SUMIFS('List of Ledgers '!L:L,'List of Ledgers '!$E:$E,Drs_Crs!$A$28,'List of Ledgers '!$B:$B,Drs_Crs!$A48) -> 26597 | G48: Op Bal | H48: =SUMIFS('List of Ledgers '!N:N,'List of Ledgers '!$E:$E,Drs_Crs!$A$28,'List of Ledgers '!$B:$B,Drs_Crs!$A48) -> 26597 | I48: =SUMIFS('List of Ledgers '!O:O,'List of Ledgers '!$E:$E,Drs_Crs!$A$28,'List of Ledgers '!$B:$B,Drs_Crs!$A48) -> 26597 | J48: =SUMIFS('List of Ledgers '!P:P,'List of Ledgers '!$E:$E,Drs_Crs!$A$28,'List of Ledgers '!$B:$B,Drs_Crs!$A48) -> 26597 | K48: =SUMIFS('List of Ledgers '!Q:Q,'List of Ledgers '!$E:$E,Drs_Crs!$A$28,'List of Ledgers '!$B:$B,Drs_Crs!$A48) -> 26597
A49: Computer World | B49: =VLOOKUP(A49,'List of Ledgers '!B:G,6,0) -> Bluestreak | C49: =SUMIFS('List of Ledgers '!I:I,'List of Ledgers '!$E:$E,Drs_Crs!$A$28,'List of Ledgers '!$B:$B,Drs_Crs!$A49) -> 0 | D49: =SUMIFS('List of Ledgers '!J:J,'List of Ledgers '!$E:$E,Drs_Crs!$A$28,'List of Ledgers '!$B:$B,Drs_Crs!$A49) -> 0 | E49: =SUMIFS('List of Ledgers '!K:K,'List of Ledgers '!$E:$E,Drs_Crs!$A$28,'List of Ledgers '!$B:$B,Drs_Crs!$A49) -> 0 | F49: =SUMIFS('List of Ledgers '!L:L,'List of Ledgers '!$E:$E,Drs_Crs!$A$28,'List of Ledgers '!$B:$B,Drs_Crs!$A49) -> 0 | H49: =SUMIFS('List of Ledgers '!N:N,'List of Ledgers '!$E:$E,Drs_Crs!$A$28,'List of Ledgers '!$B:$B,Drs_Crs!$A49) -> 0 | I49: =SUMIFS('List of Ledgers '!O:O,'List of Ledgers '!$E:$E,Drs_Crs!$A$28,'List of Ledgers '!$B:$B,Drs_Crs!$A49) -> 0 | J49: =SUMIFS('List of Ledgers '!P:P,'List of Ledgers '!$E:$E,Drs_Crs!$A$28,'List of Ledgers '!$B:$B,Drs_Crs!$A49) -> 0 | K49: =SUMIFS('List of Ledgers '!Q:Q,'List of Ledgers '!$E:$E,Drs_Crs!$A$28,'List of Ledgers '!$B:$B,Drs_Crs!$A49) -> 0
A50: Das Paper Enterprises | B50: =VLOOKUP(A50,'List of Ledgers '!B:G,6,0) -> Bluestreak | C50: =SUMIFS('List of Ledgers '!I:I,'List of Ledgers '!$E:$E,Drs_Crs!$A$28,'List of Ledgers '!$B:$B,Drs_Crs!$A50) -> 0 | D50: =SUMIFS('List of Ledgers '!J:J,'List of Ledgers '!$E:$E,Drs_Crs!$A$28,'List of Ledgers '!$B:$B,Drs_Crs!$A50) -> 0 | E50: =SUMIFS('List of Ledgers '!K:K,'List of Ledgers '!$E:$E,Drs_Crs!$A$28,'List of Ledgers '!$B:$B,Drs_Crs!$A50) -> 0 | F50: =SUMIFS('List of Ledgers '!L:L,'List of Ledgers '!$E:$E,Drs_Crs!$A$28,'List of Ledgers '!$B:$B,Drs_Crs!$A50) -> 0 | H50: =SUMIFS('List of Ledgers '!N:N,'List of Ledgers '!$E:$E,Drs_Crs!$A$28,'List of Ledgers '!$B:$B,Drs_Crs!$A50) -> 29198 | I50: =SUMIFS('List of Ledgers '!O:O,'List of Ledgers '!$E:$E,Drs_Crs!$A$28,'List of Ledgers '!$B:$B,Drs_Crs!$A50) -> 0 | J50: =SUMIFS('List of Ledgers '!P:P,'List of Ledgers '!$E:$E,Drs_Crs!$A$28,'List of Ledgers '!$B:$B,Drs_Crs!$A50) -> 29198 | K50: =SUMIFS('List of Ledgers '!Q:Q,'List of Ledgers '!$E:$E,Drs_Crs!$A$28,'List of Ledgers '!$B:$B,Drs_Crs!$A50) -> 0
A51: D.B.Enterprises | B51: =VLOOKUP(A51,'List of Ledgers '!B:G,6,0) -> Bluestreak | C51: =SUMIFS('List of Ledgers '!I:I,'List of Ledgers '!$E:$E,Drs_Crs!$A$28,'List of Ledgers '!$B:$B,Drs_Crs!$A51) -> 0 | D51: =SUMIFS('List of Ledgers '!J:J,'List of Ledgers '!$E:$E,Drs_Crs!$A$28,'List of Ledgers '!$B:$B,Drs_Crs!$A51) -> 0 | E51: =SUMIFS('List of Ledgers '!K:K,'List of Ledgers '!$E:$E,Drs_Crs!$A$28,'List of Ledgers '!$B:$B,Drs_Crs!$A51) -> 0 | F51: =SUMIFS('List of Ledgers '!L:L,'List of Ledgers '!$E:$E,Drs_Crs!$A$28,'List of Ledgers '!$B:$B,Drs_Crs!$A51) -> 0 | H51: =SUMIFS('List of Ledgers '!N:N,'List of Ledgers '!$E:$E,Drs_Crs!$A$28,'List of Ledgers '!$B:$B,Drs_Crs!$A51) -> 0 | I51: =SUMIFS('List of Ledgers '!O:O,'List of Ledgers '!$E:$E,Drs_Crs!$A$28,'List of Ledgers '!$B:$B,Drs_Crs!$A51) -> 0 | J51: =SUMIFS('List of Ledgers '!P:P,'List of Ledgers '!$E:$E,Drs_Crs!$A$28,'List of Ledgers '!$B:$B,Drs_Crs!$A51) -> 0 | K51: =SUMIFS('List of Ledgers '!Q:Q,'List of Ledgers '!$E:$E,Drs_Crs!$A$28,'List of Ledgers '!$B:$B,Drs_Crs!$A51) -> 0
A52: Deepanshu Enterprises | B52: =VLOOKUP(A52,'List of Ledgers '!B:G,6,0) -> Bluestreak | C52: =SUMIFS('List of Ledgers '!I:I,'List of Ledgers '!$E:$E,Drs_Crs!$A$28,'List of Ledgers '!$B:$B,Drs_Crs!$A52) -> 0 | D52: =SUMIFS('List of Ledgers '!J:J,'List of Ledgers '!$E:$E,Drs_Crs!$A$28,'List of Ledgers '!$B:$B,Drs_Crs!$A52) -> 0 | E52: =SUMIFS('List of Ledgers '!K:K,'List of Ledgers '!$E:$E,Drs_Crs!$A$28,'List of Ledgers '!$B:$B,Drs_Crs!$A52) -> 0 | F52: =SUMIFS('List of Ledgers '!L:L,'List of Ledgers '!$E:$E,Drs_Crs!$A$28,'List of Ledgers '!$B:$B,Drs_Crs!$A52) -> 0 | H52: =SUMIFS('List of Ledgers '!N:N,'List of Ledgers '!$E:$E,Drs_Crs!$A$28,'List of Ledgers '!$B:$B,Drs_Crs!$A52) -> 0 | I52: =SUMIFS('List of Ledgers '!O:O,'List of Ledgers '!$E:$E,Drs_Crs!$A$28,'List of Ledgers '!$B:$B,Drs_Crs!$A52) -> 78720 | J52: =SUMIFS('List of Ledgers '!P:P,'List of Ledgers '!$E:$E,Drs_Crs!$A$28,'List of Ledgers '!$B:$B,Drs_Crs!$A52) -> 78720 | K52: =SUMIFS('List of Ledgers '!Q:Q,'List of Ledgers '!$E:$E,Drs_Crs!$A$28,'List of Ledgers '!$B:$B,Drs_Crs!$A52) -> 0
A53: Device Technologies | B53: =VLOOKUP(A53,'List of Ledgers '!B:G,6,0) -> Bluestreak | C53: =SUMIFS('List of Ledgers '!I:I,'List of Ledgers '!$E:$E,Drs_Crs!$A$28,'List of Ledgers '!$B:$B,Drs_Crs!$A53) -> 0 | D53: =SUMIFS('List of Ledgers '!J:J,'List of Ledgers '!$E:$E,Drs_Crs!$A$28,'List of Ledgers '!$B:$B,Drs_Crs!$A53) -> 0 | E53: =SUMIFS('List of Ledgers '!K:K,'List of Ledgers '!$E:$E,Drs_Crs!$A$28,'List of Ledgers '!$B:$B,Drs_Crs!$A53) -> 0 | F53: =SUMIFS('List of Ledgers '!L:L,'List of Ledgers '!$E:$E,Drs_Crs!$A$28,'List of Ledgers '!$B:$B,Drs_Crs!$A53) -> 0 | H53: =SUMIFS('List of Ledgers '!N:N,'List of Ledgers '!$E:$E,Drs_Crs!$A$28,'List of Ledgers '!$B:$B,Drs_Crs!$A53) -> 0 | I53: =SUMIFS('List of Ledgers '!O:O,'List of Ledgers '!$E:$E,Drs_Crs!$A$28,'List of Ledgers '!$B:$B,Drs_Crs!$A53) -> 0 | J53: =SUMIFS('List of Ledgers '!P:P,'List of Ledgers '!$E:$E,Drs_Crs!$A$28,'List of Ledgers '!$B:$B,Drs_Crs!$A53) -> 0 | K53: =SUMIFS('List of Ledgers '!Q:Q,'List of Ledgers '!$E:$E,Drs_Crs!$A$28,'List of Ledgers '!$B:$B,Drs_Crs!$A53) -> 0
A54: Dhal Associates | B54: =VLOOKUP(A54,'List of Ledgers '!B:G,6,0) -> Clarus | C54: =SUMIFS('List of Ledgers '!I:I,'List of Ledgers '!$E:$E,Drs_Crs!$A$28,'List of Ledgers '!$B:$B,Drs_Crs!$A54) -> 0 | D54: =SUMIFS('List of Ledgers '!J:J,'List of Ledgers '!$E:$E,Drs_Crs!$A$28,'List of Ledgers '!$B:$B,Drs_Crs!$A54) -> 0 | E54: =SUMIFS('List of Ledgers '!K:K,'List of Ledgers '!$E:$E,Drs_Crs!$A$28,'List of Ledgers '!$B:$B,Drs_Crs!$A54) -> 0 | F54: =SUMIFS('List of Ledgers '!L:L,'List of Ledgers '!$E:$E,Drs_Crs!$A$28,'List of Ledgers '!$B:$B,Drs_Crs!$A54) -> 0 | H54: =SUMIFS('List of Ledgers '!N:N,'List of Ledgers '!$E:$E,Drs_Crs!$A$28,'List of Ledgers '!$B:$B,Drs_Crs!$A54) -> 0 | I54: =SUMIFS('List of Ledgers '!O:O,'List of Ledgers '!$E:$E,Drs_Crs!$A$28,'List of Ledgers '!$B:$B,Drs_Crs!$A54) -> 0 | J54: =SUMIFS('List of Ledgers '!P:P,'List of Ledgers '!$E:$E,Drs_Crs!$A$28,'List of Ledgers '!$B:$B,Drs_Crs!$A54) -> 0 | K54: =SUMIFS('List of Ledgers '!Q:Q,'List of Ledgers '!$E:$E,Drs_Crs!$A$28,'List of Ledgers '!$B:$B,Drs_Crs!$A54) -> 0
A55: Digital Mediation | B55: =VLOOKUP(A55,'List of Ledgers '!B:G,6,0) -> Bluestreak | C55: =SUMIFS('List of Ledgers '!I:I,'List of Ledgers '!$E:$E,Drs_Crs!$A$28,'List of Ledgers '!$B:$B,Drs_Crs!$A55) -> 0 | D55: =SUMIFS('List of Ledgers '!J:J,'List of Ledgers '!$E:$E,Drs_Crs!$A$28,'List of Ledgers '!$B:$B,Drs_Crs!$A55) -> 0 | E55: =SUMIFS('List of Ledgers '!K:K,'List of Ledgers '!$E:$E,Drs_Crs!$A$28,'List of Ledgers '!$B:$B,Drs_Crs!$A55) -> 0 | F55: =SUMIFS('List of Ledgers '!L:L,'List of Ledgers '!$E:$E,Drs_Crs!$A$28,'List of Ledgers '!$B:$B,Drs_Crs!$A55) -> 0 | H55: =SUMIFS('List of Ledgers '!N:N,'List of Ledgers '!$E:$E,Drs_Crs!$A$28,'List of Ledgers '!$B:$B,Drs_Crs!$A55) -> 0 | I55: =SUMIFS('List of Ledgers '!O:O,'List of Ledgers '!$E:$E,Drs_Crs!$A$28,'List of Ledgers '!$B:$B,Drs_Crs!$A55) -> 0 | J55: =SUMIFS('List of Ledgers '!P:P,'List of Ledgers '!$E:$E,Drs_Crs!$A$28,'List of Ledgers '!$B:$B,Drs_Crs!$A55) -> 0 | K55: =SUMIFS('List of Ledgers '!Q:Q,'List of Ledgers '!$E:$E,Drs_Crs!$A$28,'List of Ledgers '!$B:$B,Drs_Crs!$A55) -> 0
A56: DILIP AGENCY RK | B56: =VLOOKUP(A56,'List of Ledgers '!B:G,6,0) -> Clarus | C56: =SUMIFS('List of Ledgers '!I:I,'List of Ledgers '!$E:$E,Drs_Crs!$A$28,'List of Ledgers '!$B:$B,Drs_Crs!$A56) -> 0 | D56: =SUMIFS('List of Ledgers '!J:J,'List of Ledgers '!$E:$E,Drs_Crs!$A$28,'List of Ledgers '!$B:$B,Drs_Crs!$A56) -> 0 | E56: =SUMIFS('List of Ledgers '!K:K,'List of Ledgers '!$E:$E,Drs_Crs!$A$28,'List of Ledgers '!$B:$B,Drs_Crs!$A56) -> 0 | F56: =SUMIFS('List of Ledgers '!L:L,'List of Ledgers '!$E:$E,Drs_Crs!$A$28,'List of Ledgers '!$B:$B,Drs_Crs!$A56) -> 0 | H56: =SUMIFS('List of Ledgers '!N:N,'List of Ledgers '!$E:$E,Drs_Crs!$A$28,'List of Ledgers '!$B:$B,Drs_Crs!$A56) -> 0 | I56: =SUMIFS('List of Ledgers '!O:O,'List of Ledgers '!$E:$E,Drs_Crs!$A$28,'List of Ledgers '!$B:$B,Drs_Crs!$A56) -> 109511 | J56: =SUMIFS('List of Ledgers '!P:P,'List of Ledgers '!$E:$E,Drs_Crs!$A$28,'List of Ledgers '!$B:$B,Drs_Crs!$A56) -> 109511 | K56: =SUMIFS('List of Ledgers '!Q:Q,'List of Ledgers '!$E:$E,Drs_Crs!$A$28,'List of Ledgers '!$B:$B,Drs_Crs!$A56) -> 0
A57: Dilip Sales | B57: =VLOOKUP(A57,'List of Ledgers '!B:G,6,0) -> Clarus | C57: =SUMIFS('List of Ledgers '!I:I,'List of Ledgers '!$E:$E,Drs_Crs!$A$28,'List of Ledgers '!$B:$B,Drs_Crs!$A57) -> 0 | D57: =SUMIFS('List of Ledgers '!J:J,'List of Ledgers '!$E:$E,Drs_Crs!$A$28,'List of Ledgers '!$B:$B,Drs_Crs!$A57) -> 0 | E57: =SUMIFS('List of Ledgers '!K:K,'List of Ledgers '!$E:$E,Drs_Crs!$A$28,'List of Ledgers '!$B:$B,Drs_Crs!$A57) -> 0 | F57: =SUMIFS('List of Ledgers '!L:L,'List of Ledgers '!$E:$E,Drs_Crs!$A$28,'List of Ledgers '!$B:$B,Drs_Crs!$A57) -> 0 | H57: =SUMIFS('List of Ledgers '!N:N,'List of Ledgers '!$E:$E,Drs_Crs!$A$28,'List of Ledgers '!$B:$B,Drs_Crs!$A57) -> 0 | I57: =SUMIFS('List of Ledgers '!O:O,'List of Ledgers '!$E:$E,Drs_Crs!$A$28,'List of Ledgers '!$B:$B,Drs_Crs!$A57) -> 12516 | J57: =SUMIFS('List of Ledgers '!P:P,'List of Ledgers '!$E:$E,Drs_Crs!$A$28,'List of Ledgers '!$B:$B,Drs_Crs!$A57) -> 12516 | K57: =SUMIFS('List of Ledgers '!Q:Q,'List of Ledgers '!$E:$E,Drs_Crs!$A$28,'List of Ledgers '!$B:$B,Drs_Crs!$A57) -> 0
A58: D. S. Data Spec Pvt Ltd | B58: =VLOOKUP(A58,'List of Ledgers '!B:G,6,0) -> Bluestreak | C58: =SUMIFS('List of Ledgers '!I:I,'List of Ledgers '!$E:$E,Drs_Crs!$A$28,'List of Ledgers '!$B:$B,Drs_Crs!$A58) -> 0 | D58: =SUMIFS('List of Ledgers '!J:J,'List of Ledgers '!$E:$E,Drs_Crs!$A$28,'List of Ledgers '!$B:$B,Drs_Crs!$A58) -> 0 | E58: =SUMIFS('List of Ledgers '!K:K,'List of Ledgers '!$E:$E,Drs_Crs!$A$28,'List of Ledgers '!$B:$B,Drs_Crs!$A58) -> 0 | F58: =SUMIFS('List of Ledgers '!L:L,'List of Ledgers '!$E:$E,Drs_Crs!$A$28,'List of Ledgers '!$B:$B,Drs_Crs!$A58) -> 0 | H58: =SUMIFS('List of Ledgers '!N:N,'List of Ledgers '!$E:$E,Drs_Crs!$A$28,'List of Ledgers '!$B:$B,Drs_Crs!$A58) -> 57909 | I58: =SUMIFS('List of Ledgers '!O:O,'List of Ledgers '!$E:$E,Drs_Crs!$A$28,'List of Ledgers '!$B:$B,Drs_Crs!$A58) -> 0 | J58: =SUMIFS('List of Ledgers '!P:P,'List of Ledgers '!$E:$E,Drs_Crs!$A$28,'List of Ledgers '!$B:$B,Drs_Crs!$A58) -> 57909 | K58: =SUMIFS('List of Ledgers '!Q:Q,'List of Ledgers '!$E:$E,Drs_Crs!$A$28,'List of Ledgers '!$B:$B,Drs_Crs!$A58) -> 0
A59: EL Enterprises | B59: =VLOOKUP(A59,'List of Ledgers '!B:G,6,0) -> Bluestreak | C59: =SUMIFS('List of Ledgers '!I:I,'List of Ledgers '!$E:$E,Drs_Crs!$A$28,'List of Ledgers '!$B:$B,Drs_Crs!$A59) -> 0 | D59: =SUMIFS('List of Ledgers '!J:J,'List of Ledgers '!$E:$E,Drs_Crs!$A$28,'List of Ledgers '!$B:$B,Drs_Crs!$A59) -> 0 | E59: =SUMIFS('List of Ledgers '!K:K,'List of Ledgers '!$E:$E,Drs_Crs!$A$28,'List of Ledgers '!$B:$B,Drs_Crs!$A59) -> 0 | F59: =SUMIFS('List of Ledgers '!L:L,'List of Ledgers '!$E:$E,Drs_Crs!$A$28,'List of Ledgers '!$B:$B,Drs_Crs!$A59) -> 0 | H59: =SUMIFS('List of Ledgers '!N:N,'List of Ledgers '!$E:$E,Drs_Crs!$A$28,'List of Ledgers '!$B:$B,Drs_Crs!$A59) -> 0 | I59: =SUMIFS('List of Ledgers '!O:O,'List of Ledgers '!$E:$E,Drs_Crs!$A$28,'List of Ledgers '!$B:$B,Drs_Crs!$A59) -> 15644 | J59: =SUMIFS('List of Ledgers '!P:P,'List of Ledgers '!$E:$E,Drs_Crs!$A$28,'List of Ledgers '!$B:$B,Drs_Crs!$A59) -> 15644 | K59: =SUMIFS('List of Ledgers '!Q:Q,'List of Ledgers '!$E:$E,Drs_Crs!$A$28,'List of Ledgers '!$B:$B,Drs_Crs!$A59) -> 0
A60: Friends Computers | B60: =VLOOKUP(A60,'List of Ledgers '!B:G,6,0) -> Bluestreak | C60: =SUMIFS('List of Ledgers '!I:I,'List of Ledgers '!$E:$E,Drs_Crs!$A$28,'List of Ledgers '!$B:$B,Drs_Crs!$A60) -> 0 | D60: =SUMIFS('List of Ledgers '!J:J,'List of Ledgers '!$E:$E,Drs_Crs!$A$28,'List of Ledgers '!$B:$B,Drs_Crs!$A60) -> 0 | E60: =SUMIFS('List of Ledgers '!K:K,'List of Ledgers '!$E:$E,Drs_Crs!$A$28,'List of Ledgers '!$B:$B,Drs_Crs!$A60) -> 0 | F60: =SUMIFS('List of Ledgers '!L:L,'List of Ledgers '!$E:$E,Drs_Crs!$A$28,'List of Ledgers '!$B:$B,Drs_Crs!$A60) -> 0 | H60: =SUMIFS('List of Ledgers '!N:N,'List of Ledgers '!$E:$E,Drs_Crs!$A$28,'List of Ledgers '!$B:$B,Drs_Crs!$A60) -> 0 | I60: =SUMIFS('List of Ledgers '!O:O,'List of Ledgers '!$E:$E,Drs_Crs!$A$28,'List of Ledgers '!$B:$B,Drs_Crs!$A60) -> 0 | J60: =SUMIFS('List of Ledgers '!P:P,'List of Ledgers '!$E:$E,Drs_Crs!$A$28,'List of Ledgers '!$B:$B,Drs_Crs!$A60) -> 0 | K60: =SUMIFS('List of Ledgers '!Q:Q,'List of Ledgers '!$E:$E,Drs_Crs!$A$28,'List of Ledgers '!$B:$B,Drs_Crs!$A60) -> 0
... A63: G. T. Technologies | B63: =VLOOKUP(A63,'List of Ledgers '!B:G,6,0) -> Bluestreak | C63: =SUMIFS('List of Ledgers '!I:I,'List of Ledgers '!$E:$E,Drs_Crs!$A$28,'List of Ledgers '!$B:$B,Drs_Crs!$A63) -> 0 | D63: =SUMIFS('List of Ledgers '!J:J,'List of Ledgers '!$E:$E,Drs_Crs!$A$28,'List of Ledgers '!$B:$B,Drs_Crs!$A63) -> 0 | E63: =SUMIFS('List of Ledgers '!K:K,'List of Ledgers '!$E:$E,Drs_Crs!$A$28,'List of Ledgers '!$B:$B,Drs_Crs!$A63) -> 0 | F63: =SUMIFS('List of Ledgers '!L:L,'List of Ledgers '!$E:$E,Drs_Crs!$A$28,'List of Ledgers '!$B:$B,Drs_Crs!$A63) -> 0 | H63: =SUMIFS('List of Ledgers '!N:N,'List of Ledgers '!$E:$E,Drs_Crs!$A$28,'List of Ledgers '!$B:$B,Drs_Crs!$A63) -> 0 | I63: =SUMIFS('List of Ledgers '!O:O,'List of Ledgers '!$E:$E,Drs_Crs!$A$28,'List of Ledgers '!$B:$B,Drs_Crs!$A63) -> 0 | J63: =SUMIFS('List of Ledgers '!P:P,'List of Ledgers '!$E:$E,Drs_Crs!$A$28,'List of Ledgers '!$B:$B,Drs_Crs!$A63) -> 0 | K63: =SUMIFS('List of Ledgers '!Q:Q,'List of Ledgers '!$E:$E,Drs_Crs!$A$28,'List of Ledgers '!$B:$B,Drs_Crs!$A63) -> 0
A64: Indrayani Sales Pvt Ltd | B64: =VLOOKUP(A64,'List of Ledgers '!B:G,6,0) -> Bluestreak | C64: =SUMIFS('List of Ledgers '!I:I,'List of Ledgers '!$E:$E,Drs_Crs!$A$28,'List of Ledgers '!$B:$B,Drs_Crs!$A64) -> 90097 | D64: =SUMIFS('List of Ledgers '!J:J,'List of Ledgers '!$E:$E,Drs_Crs!$A$28,'List of Ledgers '!$B:$B,Drs_Crs!$A64) -> 0 | E64: =SUMIFS('List of Ledgers '!K:K,'List of Ledgers '!$E:$E,Drs_Crs!$A$28,'List of Ledgers '!$B:$B,Drs_Crs!$A64) -> 0 | F64: =SUMIFS('List of Ledgers '!L:L,'List of Ledgers '!$E:$E,Drs_Crs!$A$28,'List of Ledgers '!$B:$B,Drs_Crs!$A64) -> 90097 | G64: Op Bal | H64: =SUMIFS('List of Ledgers '!N:N,'List of Ledgers '!$E:$E,Drs_Crs!$A$28,'List of Ledgers '!$B:$B,Drs_Crs!$A64) -> 90097 | I64: =SUMIFS('List of Ledgers '!O:O,'List of Ledgers '!$E:$E,Drs_Crs!$A$28,'List of Ledgers '!$B:$B,Drs_Crs!$A64) -> 0 | J64: =SUMIFS('List of Ledgers '!P:P,'List of Ledgers '!$E:$E,Drs_Crs!$A$28,'List of Ledgers '!$B:$B,Drs_Crs!$A64) -> 0 | K64: =SUMIFS('List of Ledgers '!Q:Q,'List of Ledgers '!$E:$E,Drs_Crs!$A$28,'List of Ledgers '!$B:$B,Drs_Crs!$A64) -> 90097
A65: Infopower Systems | B65: =VLOOKUP(A65,'List of Ledgers '!B:G,6,0) -> Bluestreak | C65: =SUMIFS('List of Ledgers '!I:I,'List of Ledgers '!$E:$E,Drs_Crs!$A$28,'List of Ledgers '!$B:$B,Drs_Crs!$A65) -> -12803 | D65: =SUMIFS('List of Ledgers '!J:J,'List of Ledgers '!$E:$E,Drs_Crs!$A$28,'List of Ledgers '!$B:$B,Drs_Crs!$A65) -> 0 | E65: =SUMIFS('List of Ledgers '!K:K,'List of Ledgers '!$E:$E,Drs_Crs!$A$28,'List of Ledgers '!$B:$B,Drs_Crs!$A65) -> 0 | F65: =SUMIFS('List of Ledgers '!L:L,'List of Ledgers '!$E:$E,Drs_Crs!$A$28,'List of Ledgers '!$B:$B,Drs_Crs!$A65) -> -12803 | H65: =SUMIFS('List of Ledgers '!N:N,'List of Ledgers '!$E:$E,Drs_Crs!$A$28,'List of Ledgers '!$B:$B,Drs_Crs!$A65) -> -12803 | I65: =SUMIFS('List of Ledgers '!O:O,'List of Ledgers '!$E:$E,Drs_Crs!$A$28,'List of Ledgers '!$B:$B,Drs_Crs!$A65) -> 0 | J65: =SUMIFS('List of Ledgers '!P:P,'List of Ledgers '!$E:$E,Drs_Crs!$A$28,'List of Ledgers '!$B:$B,Drs_Crs!$A65) -> 0 | K65: =SUMIFS('List of Ledgers '!Q:Q,'List of Ledgers '!$E:$E,Drs_Crs!$A$28,'List of Ledgers '!$B:$B,Drs_Crs!$A65) -> -12803
A66: Infotech Solution | B66: =VLOOKUP(A66,'List of Ledgers '!B:G,6,0) -> Bluestreak | C66: =SUMIFS('List of Ledgers '!I:I,'List of Ledgers '!$E:$E,Drs_Crs!$A$28,'List of Ledgers '!$B:$B,Drs_Crs!$A66) -> 0 | D66: =SUMIFS('List of Ledgers '!J:J,'List of Ledgers '!$E:$E,Drs_Crs!$A$28,'List of Ledgers '!$B:$B,Drs_Crs!$A66) -> 0 | E66: =SUMIFS('List of Ledgers '!K:K,'List of Ledgers '!$E:$E,Drs_Crs!$A$28,'List of Ledgers '!$B:$B,Drs_Crs!$A66) -> 0 | F66: =SUMIFS('List of Ledgers '!L:L,'List of Ledgers '!$E:$E,Drs_Crs!$A$28,'List of Ledgers '!$B:$B,Drs_Crs!$A66) -> 0 | H66: =SUMIFS('List of Ledgers '!N:N,'List of Ledgers '!$E:$E,Drs_Crs!$A$28,'List of Ledgers '!$B:$B,Drs_Crs!$A66) -> 0 | I66: =SUMIFS('List of Ledgers '!O:O,'List of Ledgers '!$E:$E,Drs_Crs!$A$28,'List of Ledgers '!$B:$B,Drs_Crs!$A66) -> 42903 | J66: =SUMIFS('List of Ledgers '!P:P,'List of Ledgers '!$E:$E,Drs_Crs!$A$28,'List of Ledgers '!$B:$B,Drs_Crs!$A66) -> 42903 | K66: =SUMIFS('List of Ledgers '!Q:Q,'List of Ledgers '!$E:$E,Drs_Crs!$A$28,'List of Ledgers '!$B:$B,Drs_Crs!$A66) -> 0
A67: Iscon Distributors | B67: =VLOOKUP(A67,'List of Ledgers '!B:G,6,0) -> Bluestreak | C67: =SUMIFS('List of Ledgers '!I:I,'List of Ledgers '!$E:$E,Drs_Crs!$A$28,'List of Ledgers '!$B:$B,Drs_Crs!$A67) -> 10201.6 | D67: =SUMIFS('List of Ledgers '!J:J,'List of Ledgers '!$E:$E,Drs_Crs!$A$28,'List of Ledgers '!$B:$B,Drs_Crs!$A67) -> 0 | E67: =SUMIFS('List of Ledgers '!K:K,'List of Ledgers '!$E:$E,Drs_Crs!$A$28,'List of Ledgers '!$B:$B,Drs_Crs!$A67) -> 0 | F67: =SUMIFS('List of Ledgers '!L:L,'List of Ledgers '!$E:$E,Drs_Crs!$A$28,'List of Ledgers '!$B:$B,Drs_Crs!$A67) -> 10201.6 | G67: Op Bal | H67: =SUMIFS('List of Ledgers '!N:N,'List of Ledgers '!$E:$E,Drs_Crs!$A$28,'List of Ledgers '!$B:$B,Drs_Crs!$A67) -> 56221.6 | I67: =SUMIFS('List of Ledgers '!O:O,'List of Ledgers '!$E:$E,Drs_Crs!$A$28,'List of Ledgers '!$B:$B,Drs_Crs!$A67) -> 76877 | J67: =SUMIFS('List of Ledgers '!P:P,'List of Ledgers '!$E:$E,Drs_Crs!$A$28,'List of Ledgers '!$B:$B,Drs_Crs!$A67) -> 122897 | K67: =SUMIFS('List of Ledgers '!Q:Q,'List of Ledgers '!$E:$E,Drs_Crs!$A$28,'List of Ledgers '!$B:$B,Drs_Crs!$A67) -> 10201.6
A68: J Core | B68: =VLOOKUP(A68,'List of Ledgers '!B:G,6,0) -> Bluestreak | C68: =SUMIFS('List of Ledgers '!I:I,'List of Ledgers '!$E:$E,Drs_Crs!$A$28,'List of Ledgers '!$B:$B,Drs_Crs!$A68) -> 6254 | D68: =SUMIFS('List of Ledgers '!J:J,'List of Ledgers '!$E:$E,Drs_Crs!$A$28,'List of Ledgers '!$B:$B,Drs_Crs!$A68) -> 0 | E68: =SUMIFS('List of Ledgers '!K:K,'List of Ledgers '!$E:$E,Drs_Crs!$A$28,'List of Ledgers '!$B:$B,Drs_Crs!$A68) -> 0 | F68: =SUMIFS('List of Ledgers '!L:L,'List of Ledgers '!$E:$E,Drs_Crs!$A$28,'List of Ledgers '!$B:$B,Drs_Crs!$A68) -> 6254 | G68: Op Bal | H68: =SUMIFS('List of Ledgers '!N:N,'List of Ledgers '!$E:$E,Drs_Crs!$A$28,'List of Ledgers '!$B:$B,Drs_Crs!$A68) -> 6254 | I68: =SUMIFS('List of Ledgers '!O:O,'List of Ledgers '!$E:$E,Drs_Crs!$A$28,'List of Ledgers '!$B:$B,Drs_Crs!$A68) -> 0 | J68: =SUMIFS('List of Ledgers '!P:P,'List of Ledgers '!$E:$E,Drs_Crs!$A$28,'List of Ledgers '!$B:$B,Drs_Crs!$A68) -> 0 | K68: =SUMIFS('List of Ledgers '!Q:Q,'List of Ledgers '!$E:$E,Drs_Crs!$A$28,'List of Ledgers '!$B:$B,Drs_Crs!$A68) -> 6254
A69: Kaman Police Station | B69: =VLOOKUP(A69,'List of Ledgers '!B:G,6,0) -> Bluestreak | C69: =SUMIFS('List of Ledgers '!I:I,'List of Ledgers '!$E:$E,Drs_Crs!$A$28,'List of Ledgers '!$B:$B,Drs_Crs!$A69) -> 0 | D69: =SUMIFS('List of Ledgers '!J:J,'List of Ledgers '!$E:$E,Drs_Crs!$A$28,'List of Ledgers '!$B:$B,Drs_Crs!$A69) -> 0 | E69: =SUMIFS('List of Ledgers '!K:K,'List of Ledgers '!$E:$E,Drs_Crs!$A$28,'List of Ledgers '!$B:$B,Drs_Crs!$A69) -> 0 | F69: =SUMIFS('List of Ledgers '!L:L,'List of Ledgers '!$E:$E,Drs_Crs!$A$28,'List of Ledgers '!$B:$B,Drs_Crs!$A69) -> 0 | H69: =SUMIFS('List of Ledgers '!N:N,'List of Ledgers '!$E:$E,Drs_Crs!$A$28,'List of Ledgers '!$B:$B,Drs_Crs!$A69) -> 0 | I69: =SUMIFS('List of Ledgers '!O:O,'List of Ledgers '!$E:$E,Drs_Crs!$A$28,'List of Ledgers '!$B:$B,Drs_Crs!$A69) -> 500 | J69: =SUMIFS('List of Ledgers '!P:P,'List of Ledgers '!$E:$E,Drs_Crs!$A$28,'List of Ledgers '!$B:$B,Drs_Crs!$A69) -> 500 | K69: =SUMIFS('List of Ledgers '!Q:Q,'List of Ledgers '!$E:$E,Drs_Crs!$A$28,'List of Ledgers '!$B:$B,Drs_Crs!$A69) -> 0
A70: Kanaiyalal M. Vania | B70: =VLOOKUP(A70,'List of Ledgers '!B:G,6,0) -> Clarus | C70: =SUMIFS('List of Ledgers '!I:I,'List of Ledgers '!$E:$E,Drs_Crs!$A$28,'List of Ledgers '!$B:$B,Drs_Crs!$A70) -> 0 | D70: =SUMIFS('List of Ledgers '!J:J,'List of Ledgers '!$E:$E,Drs_Crs!$A$28,'List of Ledgers '!$B:$B,Drs_Crs!$A70) -> 0 | E70: =SUMIFS('List of Ledgers '!K:K,'List of Ledgers '!$E:$E,Drs_Crs!$A$28,'List of Ledgers '!$B:$B,Drs_Crs!$A70) -> 0 | F70: =SUMIFS('List of Ledgers '!L:L,'List of Ledgers '!$E:$E,Drs_Crs!$A$28,'List of Ledgers '!$B:$B,Drs_Crs!$A70) -> 0 | H70: =SUMIFS('List of Ledgers '!N:N,'List of Ledgers '!$E:$E,Drs_Crs!$A$28,'List of Ledgers '!$B:$B,Drs_Crs!$A70) -> 0 | I70: =SUMIFS('List of Ledgers '!O:O,'List of Ledgers '!$E:$E,Drs_Crs!$A$28,'List of Ledgers '!$B:$B,Drs_Crs!$A70) -> 0 | J70: =SUMIFS('List of Ledgers '!P:P,'List of Ledgers '!$E:$E,Drs_Crs!$A$28,'List of Ledgers '!$B:$B,Drs_Crs!$A70) -> 0 | K70: =SUMIFS('List of Ledgers '!Q:Q,'List of Ledgers '!$E:$E,Drs_Crs!$A$28,'List of Ledgers '!$B:$B,Drs_Crs!$A70) -> 0
A71: Karma Management Global Consulting Solutions Private Limited | B71: =VLOOKUP(A71,'List of Ledgers '!B:G,6,0) -> Common | C71: =SUMIFS('List of Ledgers '!I:I,'List of Ledgers '!$E:$E,Drs_Crs!$A$28,'List of Ledgers '!$B:$B,Drs_Crs!$A71) -> 0 | D71: =SUMIFS('List of Ledgers '!J:J,'List of Ledgers '!$E:$E,Drs_Crs!$A$28,'List of Ledgers '!$B:$B,Drs_Crs!$A71) -> 0 | E71: =SUMIFS('List of Ledgers '!K:K,'List of Ledgers '!$E:$E,Drs_Crs!$A$28,'List of Ledgers '!$B:$B,Drs_Crs!$A71) -> 0 | F71: =SUMIFS('List of Ledgers '!L:L,'List of Ledgers '!$E:$E,Drs_Crs!$A$28,'List of Ledgers '!$B:$B,Drs_Crs!$A71) -> 0 | H71: =SUMIFS('List of Ledgers '!N:N,'List of Ledgers '!$E:$E,Drs_Crs!$A$28,'List of Ledgers '!$B:$B,Drs_Crs!$A71) -> 0 | I71: =SUMIFS('List of Ledgers '!O:O,'List of Ledgers '!$E:$E,Drs_Crs!$A$28,'List of Ledgers '!$B:$B,Drs_Crs!$A71) -> 0 | J71: =SUMIFS('List of Ledgers '!P:P,'List of Ledgers '!$E:$E,Drs_Crs!$A$28,'List of Ledgers '!$B:$B,Drs_Crs!$A71) -> 0 | K71: =SUMIFS('List of Ledgers '!Q:Q,'List of Ledgers '!$E:$E,Drs_Crs!$A$28,'List of Ledgers '!$B:$B,Drs_Crs!$A71) -> 0
A72: KingS It World | B72: =VLOOKUP(A72,'List of Ledgers '!B:G,6,0) -> Bluestreak | C72: =SUMIFS('List of Ledgers '!I:I,'List of Ledgers '!$E:$E,Drs_Crs!$A$28,'List of Ledgers '!$B:$B,Drs_Crs!$A72) -> 0 | D72: =SUMIFS('List of Ledgers '!J:J,'List of Ledgers '!$E:$E,Drs_Crs!$A$28,'List of Ledgers '!$B:$B,Drs_Crs!$A72) -> 0 | E72: =SUMIFS('List of Ledgers '!K:K,'List of Ledgers '!$E:$E,Drs_Crs!$A$28,'List of Ledgers '!$B:$B,Drs_Crs!$A72) -> 0 | F72: =SUMIFS('List of Ledgers '!L:L,'List of Ledgers '!$E:$E,Drs_Crs!$A$28,'List of Ledgers '!$B:$B,Drs_Crs!$A72) -> 0 | H72: =SUMIFS('List of Ledgers '!N:N,'List of Ledgers '!$E:$E,Drs_Crs!$A$28,'List of Ledgers '!$B:$B,Drs_Crs!$A72) -> 0 | I72: =SUMIFS('List of Ledgers '!O:O,'List of Ledgers '!$E:$E,Drs_Crs!$A$28,'List of Ledgers '!$B:$B,Drs_Crs!$A72) -> 0 | J72: =SUMIFS('List of Ledgers '!P:P,'List of Ledgers '!$E:$E,Drs_Crs!$A$28,'List of Ledgers '!$B:$B,Drs_Crs!$A72) -> 0 | K72: =SUMIFS('List of Ledgers '!Q:Q,'List of Ledgers '!$E:$E,Drs_Crs!$A$28,'List of Ledgers '!$B:$B,Drs_Crs!$A72) -> 0
A73: Krupa Electronic | B73: =VLOOKUP(A73,'List of Ledgers '!B:G,6,0) -> Bluestreak | C73: =SUMIFS('List of Ledgers '!I:I,'List of Ledgers '!$E:$E,Drs_Crs!$A$28,'List of Ledgers '!$B:$B,Drs_Crs!$A73) -> 0 | D73: =SUMIFS('List of Ledgers '!J:J,'List of Ledgers '!$E:$E,Drs_Crs!$A$28,'List of Ledgers '!$B:$B,Drs_Crs!$A73) -> 0 | E73: =SUMIFS('List of Ledgers '!K:K,'List of Ledgers '!$E:$E,Drs_Crs!$A$28,'List of Ledgers '!$B:$B,Drs_Crs!$A73) -> 0 | F73: =SUMIFS('List of Ledgers '!L:L,'List of Ledgers '!$E:$E,Drs_Crs!$A$28,'List of Ledgers '!$B:$B,Drs_Crs!$A73) -> 0 | H73: =SUMIFS('List of Ledgers '!N:N,'List of Ledgers '!$E:$E,Drs_Crs!$A$28,'List of Ledgers '!$B:$B,Drs_Crs!$A73) -> 0 | I73: =SUMIFS('List of Ledgers '!O:O,'List of Ledgers '!$E:$E,Drs_Crs!$A$28,'List of Ledgers '!$B:$B,Drs_Crs!$A73) -> 25960 | J73: =SUMIFS('List of Ledgers '!P:P,'List of Ledgers '!$E:$E,Drs_Crs!$A$28,'List of Ledgers '!$B:$B,Drs_Crs!$A73) -> 25960 | K73: =SUMIFS('List of Ledgers '!Q:Q,'List of Ledgers '!$E:$E,Drs_Crs!$A$28,'List of Ledgers '!$B:$B,Drs_Crs!$A73) -> 0
A74: Lalit Computer And Appliances | B74: =VLOOKUP(A74,'List of Ledgers '!B:G,6,0) -> Bluestreak | C74: =SUMIFS('List of Ledgers '!I:I,'List of Ledgers '!$E:$E,Drs_Crs!$A$28,'List of Ledgers '!$B:$B,Drs_Crs!$A74) -> 0 | D74: =SUMIFS('List of Ledgers '!J:J,'List of Ledgers '!$E:$E,Drs_Crs!$A$28,'List of Ledgers '!$B:$B,Drs_Crs!$A74) -> 0 | E74: =SUMIFS('List of Ledgers '!K:K,'List of Ledgers '!$E:$E,Drs_Crs!$A$28,'List of Ledgers '!$B:$B,Drs_Crs!$A74) -> 0 | F74: =SUMIFS('List of Ledgers '!L:L,'List of Ledgers '!$E:$E,Drs_Crs!$A$28,'List of Ledgers '!$B:$B,Drs_Crs!$A74) -> 0 | H74: =SUMIFS('List of Ledgers '!N:N,'List of Ledgers '!$E:$E,Drs_Crs!$A$28,'List of Ledgers '!$B:$B,Drs_Crs!$A74) -> 0 | I74: =SUMIFS('List of Ledgers '!O:O,'List of Ledgers '!$E:$E,Drs_Crs!$A$28,'List of Ledgers '!$B:$B,Drs_Crs!$A74) -> 0 | J74: =SUMIFS('List of Ledgers '!P:P,'List of Ledgers '!$E:$E,Drs_Crs!$A$28,'List of Ledgers '!$B:$B,Drs_Crs!$A74) -> 0 | K74: =SUMIFS('List of Ledgers '!Q:Q,'List of Ledgers '!$E:$E,Drs_Crs!$A$28,'List of Ledgers '!$B:$B,Drs_Crs!$A74) -> 0
